Workbook

Sheet Resumen
C1: Validación | D1: =D3+F3+G3+I3+J3+E3+H3 -> 3225204 | F1: =D1-BASE!Q1 -> 0 | K1: =K3-'Eventos B2B_MKT y Turnos DT'!P2 -> 0 | L1: =L3-'Eventos B2B_MKT y Turnos DT'!P3 -> 0 | M1: =M3-'Eventos B2B_MKT y Turnos DT'!P4 -> 0 | N1: =N3-Incidencias!K2 -> 0 | O1: =(D1+K3+L3+M3+N3)-O3 -> 0
D3: =SUBTOTAL(9,D6:D99) -> 1888913 | E3: =SUBTOTAL(9,E6:E99) -> 45378 | F3: =SUBTOTAL(9,F6:F99) -> 1151594 | G3: =SUBTOTAL(9,G6:G99) -> 0 | H3: =SUBTOTAL(9,H6:H99) -> 22689 | I3: =SUBTOTAL(9,I6:I99) -> 68067 | J3: =SUBTOTAL(9,J6:J99) -> 48563 | K3: =SUBTOTAL(9,K6:K99) -> 509750 | ... Q3: =SUBTOTAL(9,Q6:Q99) -> 74426 | R3: =IFERROR(Q3/O3,0) -> 0.018119793 | S3: =SUBTOTAL(9,S6:S99) -> 164999.89 | T3: =SUBTOTAL(9,T6:T99) -> 3406631.1 | U3: =+IF(O3*(1-0.1525)-Q3=T3,"OK","REVISAR") -> OK
B5: RUT | C5: NOMBRE TERAPEUTA | D5: B2C | E5: CERTIFICADO B2C | F5: HOTEL | G5: B2B | H5: CERTIFICADO B2B | I5: ALIANZA | J5: MARKETING | K5: EVENTO B2B | L5: TURNO HOTEL DT | M5: EVENTO MKT | N5: INCIDENCIAS | O5: MONTO BOLETA | P5: DEUDA TOTAL | Q5: DCTO QUINCENA | R5: % DCTO | S5: DEUDA RESTANTE | T5: A PAGO QUINCENA | U5: VALIDADOR
B6: =Nómina!D3 -> 20025768-5 | C6: =Nómina!E3 -> ADOLFO STEPHEN PFENG ROJAS | D6: =SUMIFS(BASE!$Q$3:$Q$453,BASE!$O$3:$O$453,Resumen!D$5,BASE!$B$3:$B$453,Resumen!$B6) -> 0 | E6: =SUMIFS(BASE!$Q$3:$Q$453,BASE!$O$3:$O$453,Resumen!E$5,BASE!$B$3:$B$453,Resumen!$B6) -> 0 | F6: =SUMIFS(BASE!$Q$3:$Q$453,BASE!$O$3:$O$453,Resumen!F$5,BASE!$B$3:$B$453,Resumen!$B6) -> 0 | G6: =SUMIFS(BASE!$Q$3:$Q$453,BASE!$O$3:$O$453,Resumen!G$5,BASE!$B$3:$B$453,Resumen!$B6) -> 0 | H6: =SUMIFS(BASE!$Q$3:$Q$453,BASE!$O$3:$O$453,Resumen!H$5,BASE!$B$3:$B$453,Resumen!$B6) -> 0 | I6: =SUMIFS(BASE!$Q$3:$Q$453,BASE!$O$3:$O$453,Resumen!I$5,BASE!$B$3:$B$453,Resumen!$B6) -> 0 | J6: =SUMIFS(BASE!$Q$3:$Q$453,BASE!$O$3:$O$453,Resumen!J$5,BASE!$B$3:$B$453,Resumen!$B6) -> 0 | K6: =SUMIFS('Eventos B2B_MKT y Turnos DT'!$K$6:$K$456,'Eventos B2B_MKT y Turnos DT'!$D$6:$D$456,Resumen!$B6,'Eventos B2B_MKT y Turnos DT'!$G$6:$G$456,"B2B") -> 0 | L6: =SUMIFS('Eventos B2B_MKT y Turnos DT'!$K$6:$K$456,'Eventos B2B_MKT y Turnos DT'!$D$6:$D$456,Resumen!$B6,'Eventos B2B_MKT y Turnos DT'!$G$6:$G$456,"Hotel") -> 0 | M6: =SUMIFS('Eventos B2B_MKT y Turnos DT'!$K$6:$K$456,'Eventos B2B_MKT y Turnos DT'!$D$6:$D$456,Resumen!$B6,'Eventos B2B_MKT y Turnos DT'!$G$6:$G$456,"Marketing") -> 0 | N6: =SUMIF(Incidencias!$E$4:$E$89,$B6,Incidencias!$K$4:$K$89) -> 0 | O6: =SUM(D6:N6) -> 0 | P6: 128400 | R6: =IFERROR(Q6/O6,0) -> 0 | S6: =IFERROR(P6-Q6,"") -> 128400 | T6: =O6*(1-0.1525)-Q6 -> 0
B7: =Nómina!D4 -> 13715658-K | C7: =Nómina!E4 -> ALEJANDRA PAZ SANCHEZ LENERO | D7: =SUMIFS(BASE!$Q$3:$Q$453,BASE!$O$3:$O$453,Resumen!D$5,BASE!$B$3:$B$453,Resumen!$B7) -> 68067 | E7: =SUMIFS(BASE!$Q$3:$Q$453,BASE!$O$3:$O$453,Resumen!E$5,BASE!$B$3:$B$453,Resumen!$B7) -> 0 | F7: =SUMIFS(BASE!$Q$3:$Q$453,BASE!$O$3:$O$453,Resumen!F$5,BASE!$B$3:$B$453,Resumen!$B7) -> 110924 | G7: =SUMIFS(BASE!$Q$3:$Q$453,BASE!$O$3:$O$453,Resumen!G$5,BASE!$B$3:$B$453,Resumen!$B7) -> 0 | H7: =SUMIFS(BASE!$Q$3:$Q$453,BASE!$O$3:$O$453,Resumen!H$5,BASE!$B$3:$B$453,Resumen!$B7) -> 0 | I7: =SUMIFS(BASE!$Q$3:$Q$453,BASE!$O$3:$O$453,Resumen!I$5,BASE!$B$3:$B$453,Resumen!$B7) -> 0 | J7: =SUMIFS(BASE!$Q$3:$Q$453,BASE!$O$3:$O$453,Resumen!J$5,BASE!$B$3:$B$453,Resumen!$B7) -> 0 | K7: =SUMIFS('Eventos B2B_MKT y Turnos DT'!$K$6:$K$456,'Eventos B2B_MKT y Turnos DT'!$D$6:$D$456,Resumen!$B7,'Eventos B2B_MKT y Turnos DT'!$G$6:$G$456,"B2B") -> 0 | L7: =SUMIFS('Eventos B2B_MKT y Turnos DT'!$K$6:$K$456,'Eventos B2B_MKT y Turnos DT'!$D$6:$D$456,Resumen!$B7,'Eventos B2B_MKT y Turnos DT'!$G$6:$G$456,"Hotel") -> 23392 | M7: =SUMIFS('Eventos B2B_MKT y Turnos DT'!$K$6:$K$456,'Eventos B2B_MKT y Turnos DT'!$D$6:$D$456,Resumen!$B7,'Eventos B2B_MKT y Turnos DT'!$G$6:$G$456,"Marketing") -> 0 | N7: =SUMIF(Incidencias!$E$4:$E$89,$B7,Incidencias!$K$4:$K$89) -> 0 | O7: =SUM(D7:N7) -> 202383 | P7: 0 | Q7: =+IF(AND(P7<>0,P7>O7*0.2),O7*0.2,P7) -> 0 | R7: =IFERROR(Q7/O7,0) -> 0 | S7: =IFERROR(P7-Q7,"") -> 0 | T7: =O7*(1-0.1525)-Q7 -> 171519.59 | U7: =+IF(O7*(1-0.1525)-Q7=T7,"OK","REVISAR") -> OK
B8: =Nómina!D5 -> 15939313-5 | C8: =Nómina!E5 -> ANA MARIA ORTEGA RIVAS | D8: =SUMIFS(BASE!$Q$3:$Q$453,BASE!$O$3:$O$453,Resumen!D$5,BASE!$B$3:$B$453,Resumen!$B8) -> 0 | E8: =SUMIFS(BASE!$Q$3:$Q$453,BASE!$O$3:$O$453,Resumen!E$5,BASE!$B$3:$B$453,Resumen!$B8) -> 0 | F8: =SUMIFS(BASE!$Q$3:$Q$453,BASE!$O$3:$O$453,Resumen!F$5,BASE!$B$3:$B$453,Resumen!$B8) -> 0 | G8: =SUMIFS(BASE!$Q$3:$Q$453,BASE!$O$3:$O$453,Resumen!G$5,BASE!$B$3:$B$453,Resumen!$B8) -> 0 | H8: =SUMIFS(BASE!$Q$3:$Q$453,BASE!$O$3:$O$453,Resumen!H$5,BASE!$B$3:$B$453,Resumen!$B8) -> 0 | I8: =SUMIFS(BASE!$Q$3:$Q$453,BASE!$O$3:$O$453,Resumen!I$5,BASE!$B$3:$B$453,Resumen!$B8) -> 0 | J8: =SUMIFS(BASE!$Q$3:$Q$453,BASE!$O$3:$O$453,Resumen!J$5,BASE!$B$3:$B$453,Resumen!$B8) -> 0 | K8: =SUMIFS('Eventos B2B_MKT y Turnos DT'!$K$6:$K$456,'Eventos B2B_MKT y Turnos DT'!$D$6:$D$456,Resumen!$B8,'Eventos B2B_MKT y Turnos DT'!$G$6:$G$456,"B2B") -> 0 | L8: =SUMIFS('Eventos B2B_MKT y Turnos DT'!$K$6:$K$456,'Eventos B2B_MKT y Turnos DT'!$D$6:$D$456,Resumen!$B8,'Eventos B2B_MKT y Turnos DT'!$G$6:$G$456,"Hotel") -> 0 | M8: =SUMIFS('Eventos B2B_MKT y Turnos DT'!$K$6:$K$456,'Eventos B2B_MKT y Turnos DT'!$D$6:$D$456,Resumen!$B8,'Eventos B2B_MKT y Turnos DT'!$G$6:$G$456,"Marketing") -> 0 | N8: =SUMIF(Incidencias!$E$4:$E$89,$B8,Incidencias!$K$4:$K$89) -> 0 | O8: =SUM(D8:N8) -> 0 | P8: 29990 | R8: =IFERROR(Q8/O8,0) -> 0 | S8: =IFERROR(P8-Q8,"") -> 29990 | T8: =O8*(1-0.1525)-Q8 -> 0
B9: =Nómina!D6 -> 15688433-2 | C9: =Nómina!E6 -> ANA MARIA POZAS WISTUBA | D9: =SUMIFS(BASE!$Q$3:$Q$453,BASE!$O$3:$O$453,Resumen!D$5,BASE!$B$3:$B$453,Resumen!$B9) -> 0 | E9: =SUMIFS(BASE!$Q$3:$Q$453,BASE!$O$3:$O$453,Resumen!E$5,BASE!$B$3:$B$453,Resumen!$B9) -> 0 | F9: =SUMIFS(BASE!$Q$3:$Q$453,BASE!$O$3:$O$453,Resumen!F$5,BASE!$B$3:$B$453,Resumen!$B9) -> 0 | G9: =SUMIFS(BASE!$Q$3:$Q$453,BASE!$O$3:$O$453,Resumen!G$5,BASE!$B$3:$B$453,Resumen!$B9) -> 0 | H9: =SUMIFS(BASE!$Q$3:$Q$453,BASE!$O$3:$O$453,Resumen!H$5,BASE!$B$3:$B$453,Resumen!$B9) -> 0 | I9: =SUMIFS(BASE!$Q$3:$Q$453,BASE!$O$3:$O$453,Resumen!I$5,BASE!$B$3:$B$453,Resumen!$B9) -> 0 | J9: =SUMIFS(BASE!$Q$3:$Q$453,BASE!$O$3:$O$453,Resumen!J$5,BASE!$B$3:$B$453,Resumen!$B9) -> 0 | K9: =SUMIFS('Eventos B2B_MKT y Turnos DT'!$K$6:$K$456,'Eventos B2B_MKT y Turnos DT'!$D$6:$D$456,Resumen!$B9,'Eventos B2B_MKT y Turnos DT'!$G$6:$G$456,"B2B") -> 0 | L9: =SUMIFS('Eventos B2B_MKT y Turnos DT'!$K$6:$K$456,'Eventos B2B_MKT y Turnos DT'!$D$6:$D$456,Resumen!$B9,'Eventos B2B_MKT y Turnos DT'!$G$6:$G$456,"Hotel") -> 0 | M9: =SUMIFS('Eventos B2B_MKT y Turnos DT'!$K$6:$K$456,'Eventos B2B_MKT y Turnos DT'!$D$6:$D$456,Resumen!$B9,'Eventos B2B_MKT y Turnos DT'!$G$6:$G$456,"Marketing") -> 0 | N9: =SUMIF(Incidencias!$E$4:$E$89,$B9,Incidencias!$K$4:$K$89) -> 0 | O9: =SUM(D9:N9) -> 0 | P9: 85000 | R9: =IFERROR(Q9/O9,0) -> 0 | S9: =IFERROR(P9-Q9,"") -> 85000 | T9: =O9*(1-0.1525)-Q9 -> 0
B10: =Nómina!D7 -> 18480921-4 | C10: =Nómina!E7 -> ANDREA JUANA ALVAREZ SEPULVEDA | D10: =SUMIFS(BASE!$Q$3:$Q$453,BASE!$O$3:$O$453,Resumen!D$5,BASE!$B$3:$B$453,Resumen!$B10) -> 0 | E10: =SUMIFS(BASE!$Q$3:$Q$453,BASE!$O$3:$O$453,Resumen!E$5,BASE!$B$3:$B$453,Resumen!$B10) -> 0 | F10: =SUMIFS(BASE!$Q$3:$Q$453,BASE!$O$3:$O$453,Resumen!F$5,BASE!$B$3:$B$453,Resumen!$B10) -> 0 | G10: =SUMIFS(BASE!$Q$3:$Q$453,BASE!$O$3:$O$453,Resumen!G$5,BASE!$B$3:$B$453,Resumen!$B10) -> 0 | H10: =SUMIFS(BASE!$Q$3:$Q$453,BASE!$O$3:$O$453,Resumen!H$5,BASE!$B$3:$B$453,Resumen!$B10) -> 0 | I10: =SUMIFS(BASE!$Q$3:$Q$453,BASE!$O$3:$O$453,Resumen!I$5,BASE!$B$3:$B$453,Resumen!$B10) -> 0 | J10: =SUMIFS(BASE!$Q$3:$Q$453,BASE!$O$3:$O$453,Resumen!J$5,BASE!$B$3:$B$453,Resumen!$B10) -> 0 | K10: =SUMIFS('Eventos B2B_MKT y Turnos DT'!$K$6:$K$456,'Eventos B2B_MKT y Turnos DT'!$D$6:$D$456,Resumen!$B10,'Eventos B2B_MKT y Turnos DT'!$G$6:$G$456,"B2B") -> 0 | L10: =SUMIFS('Eventos B2B_MKT y Turnos DT'!$K$6:$K$456,'Eventos B2B_MKT y Turnos DT'!$D$6:$D$456,Resumen!$B10,'Eventos B2B_MKT y Turnos DT'!$G$6:$G$456,"Hotel") -> 0 | M10: =SUMIFS('Eventos B2B_MKT y Turnos DT'!$K$6:$K$456,'Eventos B2B_MKT y Turnos DT'!$D$6:$D$456,Resumen!$B10,'Eventos B2B_MKT y Turnos DT'!$G$6:$G$456,"Marketing") -> 0 | N10: =SUMIF(Incidencias!$E$4:$E$89,$B10,Incidencias!$K$4:$K$89) -> 0 | O10: =SUM(D10:N10) -> 0 | P10: 0 | R10: =IFERROR(Q10/O10,0) -> 0 | S10: =IFERROR(P10-Q10,"") -> 0 | T10: =O10*(1-0.1525)-Q10 -> 0
B11: =Nómina!D8 -> 24133147-4 | C11: =Nómina!E8 -> ANGEL LOPEZ FERNANDEZ | D11: =SUMIFS(BASE!$Q$3:$Q$453,BASE!$O$3:$O$453,Resumen!D$5,BASE!$B$3:$B$453,Resumen!$B11) -> 0 | E11: =SUMIFS(BASE!$Q$3:$Q$453,BASE!$O$3:$O$453,Resumen!E$5,BASE!$B$3:$B$453,Resumen!$B11) -> 0 | F11: =SUMIFS(BASE!$Q$3:$Q$453,BASE!$O$3:$O$453,Resumen!F$5,BASE!$B$3:$B$453,Resumen!$B11) -> 0 | G11: =SUMIFS(BASE!$Q$3:$Q$453,BASE!$O$3:$O$453,Resumen!G$5,BASE!$B$3:$B$453,Resumen!$B11) -> 0 | H11: =SUMIFS(BASE!$Q$3:$Q$453,BASE!$O$3:$O$453,Resumen!H$5,BASE!$B$3:$B$453,Resumen!$B11) -> 0 | I11: =SUMIFS(BASE!$Q$3:$Q$453,BASE!$O$3:$O$453,Resumen!I$5,BASE!$B$3:$B$453,Resumen!$B11) -> 0 | J11: =SUMIFS(BASE!$Q$3:$Q$453,BASE!$O$3:$O$453,Resumen!J$5,BASE!$B$3:$B$453,Resumen!$B11) -> 0 | K11: =SUMIFS('Eventos B2B_MKT y Turnos DT'!$K$6:$K$456,'Eventos B2B_MKT y Turnos DT'!$D$6:$D$456,Resumen!$B11,'Eventos B2B_MKT y Turnos DT'!$G$6:$G$456,"B2B") -> 0 | L11: =SUMIFS('Eventos B2B_MKT y Turnos DT'!$K$6:$K$456,'Eventos B2B_MKT y Turnos DT'!$D$6:$D$456,Resumen!$B11,'Eventos B2B_MKT y Turnos DT'!$G$6:$G$456,"Hotel") -> 0 | M11: =SUMIFS('Eventos B2B_MKT y Turnos DT'!$K$6:$K$456,'Eventos B2B_MKT y Turnos DT'!$D$6:$D$456,Resumen!$B11,'Eventos B2B_MKT y Turnos DT'!$G$6:$G$456,"Marketing") -> 0 | N11: =SUMIF(Incidencias!$E$4:$E$89,$B11,Incidencias!$K$4:$K$89) -> 0 | O11: =SUM(D11:N11) -> 0 | P11: 112420 | R11: =IFERROR(Q11/O11,0) -> 0 | S11: =IFERROR(P11-Q11,"") -> 112420 | T11: =O11*(1-0.1525)-Q11 -> 0
B12: =Nómina!D9 -> 26538149-9 | C12: =Nómina!E9 -> ANGELO JESUS OLMOS DEL VALLE | D12: =SUMIFS(BASE!$Q$3:$Q$453,BASE!$O$3:$O$453,Resumen!D$5,BASE!$B$3:$B$453,Resumen!$B12) -> 0 | E12: =SUMIFS(BASE!$Q$3:$Q$453,BASE!$O$3:$O$453,Resumen!E$5,BASE!$B$3:$B$453,Resumen!$B12) -> 0 | F12: =SUMIFS(BASE!$Q$3:$Q$453,BASE!$O$3:$O$453,Resumen!F$5,BASE!$B$3:$B$453,Resumen!$B12) -> 0 | G12: =SUMIFS(BASE!$Q$3:$Q$453,BASE!$O$3:$O$453,Resumen!G$5,BASE!$B$3:$B$453,Resumen!$B12) -> 0 | H12: =SUMIFS(BASE!$Q$3:$Q$453,BASE!$O$3:$O$453,Resumen!H$5,BASE!$B$3:$B$453,Resumen!$B12) -> 0 | I12: =SUMIFS(BASE!$Q$3:$Q$453,BASE!$O$3:$O$453,Resumen!I$5,BASE!$B$3:$B$453,Resumen!$B12) -> 0 | J12: =SUMIFS(BASE!$Q$3:$Q$453,BASE!$O$3:$O$453,Resumen!J$5,BASE!$B$3:$B$453,Resumen!$B12) -> 0 | K12: =SUMIFS('Eventos B2B_MKT y Turnos DT'!$K$6:$K$456,'Eventos B2B_MKT y Turnos DT'!$D$6:$D$456,Resumen!$B12,'Eventos B2B_MKT y Turnos DT'!$G$6:$G$456,"B2B") -> 0 | L12: =SUMIFS('Eventos B2B_MKT y Turnos DT'!$K$6:$K$456,'Eventos B2B_MKT y Turnos DT'!$D$6:$D$456,Resumen!$B12,'Eventos B2B_MKT y Turnos DT'!$G$6:$G$456,"Hotel") -> 0 | M12: =SUMIFS('Eventos B2B_MKT y Turnos DT'!$K$6:$K$456,'Eventos B2B_MKT y Turnos DT'!$D$6:$D$456,Resumen!$B12,'Eventos B2B_MKT y Turnos DT'!$G$6:$G$456,"Marketing") -> 0 | N12: =SUMIF(Incidencias!$E$4:$E$89,$B12,Incidencias!$K$4:$K$89) -> 0 | O12: =SUM(D12:N12) -> 0 | P12: 48500 | Q12: 9500 | R12: =IFERROR(Q12/O12,0) -> 0 | S12: =IFERROR(P12-Q12,"") -> 39000 | T12: =O12*(1-0.1525)-Q12 -> -9500 | U12: =+IF(O12*(1-0.1525)-Q12=T12,"OK","REVISAR") -> OK
B13: =Nómina!D10 -> 26920431-1 | C13: =Nómina!E10 -> ARLIDIS MARIA SANCHEZ CAMACHO | D13: =SUMIFS(BASE!$Q$3:$Q$453,BASE!$O$3:$O$453,Resumen!D$5,BASE!$B$3:$B$453,Resumen!$B13) -> 0 | E13: =SUMIFS(BASE!$Q$3:$Q$453,BASE!$O$3:$O$453,Resumen!E$5,BASE!$B$3:$B$453,Resumen!$B13) -> 0 | F13: =SUMIFS(BASE!$Q$3:$Q$453,BASE!$O$3:$O$453,Resumen!F$5,BASE!$B$3:$B$453,Resumen!$B13) -> 0 | G13: =SUMIFS(BASE!$Q$3:$Q$453,BASE!$O$3:$O$453,Resumen!G$5,BASE!$B$3:$B$453,Resumen!$B13) -> 0 | H13: =SUMIFS(BASE!$Q$3:$Q$453,BASE!$O$3:$O$453,Resumen!H$5,BASE!$B$3:$B$453,Resumen!$B13) -> 0 | I13: =SUMIFS(BASE!$Q$3:$Q$453,BASE!$O$3:$O$453,Resumen!I$5,BASE!$B$3:$B$453,Resumen!$B13) -> 0 | J13: =SUMIFS(BASE!$Q$3:$Q$453,BASE!$O$3:$O$453,Resumen!J$5,BASE!$B$3:$B$453,Resumen!$B13) -> 0 | K13: =SUMIFS('Eventos B2B_MKT y Turnos DT'!$K$6:$K$456,'Eventos B2B_MKT y Turnos DT'!$D$6:$D$456,Resumen!$B13,'Eventos B2B_MKT y Turnos DT'!$G$6:$G$456,"B2B") -> 0 | L13: =SUMIFS('Eventos B2B_MKT y Turnos DT'!$K$6:$K$456,'Eventos B2B_MKT y Turnos DT'!$D$6:$D$456,Resumen!$B13,'Eventos B2B_MKT y Turnos DT'!$G$6:$G$456,"Hotel") -> 0 | M13: =SUMIFS('Eventos B2B_MKT y Turnos DT'!$K$6:$K$456,'Eventos B2B_MKT y Turnos DT'!$D$6:$D$456,Resumen!$B13,'Eventos B2B_MKT y Turnos DT'!$G$6:$G$456,"Marketing") -> 0 | N13: =SUMIF(Incidencias!$E$4:$E$89,$B13,Incidencias!$K$4:$K$89) -> 0 | O13: =SUM(D13:N13) -> 0 | P13: 58473 | R13: =IFERROR(Q13/O13,0) -> 0 | S13: =IFERROR(P13-Q13,"") -> 58473 | T13: =O13*(1-0.1525)-Q13 -> 0
B14: =Nómina!D11 -> 16586101-9 | C14: =Nómina!E11 -> BETTINA GAJARDO | D14: =SUMIFS(BASE!$Q$3:$Q$453,BASE!$O$3:$O$453,Resumen!D$5,BASE!$B$3:$B$453,Resumen!$B14) -> 0 | E14: =SUMIFS(BASE!$Q$3:$Q$453,BASE!$O$3:$O$453,Resumen!E$5,BASE!$B$3:$B$453,Resumen!$B14) -> 0 | F14: =SUMIFS(BASE!$Q$3:$Q$453,BASE!$O$3:$O$453,Resumen!F$5,BASE!$B$3:$B$453,Resumen!$B14) -> 0 | G14: =SUMIFS(BASE!$Q$3:$Q$453,BASE!$O$3:$O$453,Resumen!G$5,BASE!$B$3:$B$453,Resumen!$B14) -> 0 | H14: =SUMIFS(BASE!$Q$3:$Q$453,BASE!$O$3:$O$453,Resumen!H$5,BASE!$B$3:$B$453,Resumen!$B14) -> 0 | I14: =SUMIFS(BASE!$Q$3:$Q$453,BASE!$O$3:$O$453,Resumen!I$5,BASE!$B$3:$B$453,Resumen!$B14) -> 22689 | J14: =SUMIFS(BASE!$Q$3:$Q$453,BASE!$O$3:$O$453,Resumen!J$5,BASE!$B$3:$B$453,Resumen!$B14) -> 0 | K14: =SUMIFS('Eventos B2B_MKT y Turnos DT'!$K$6:$K$456,'Eventos B2B_MKT y Turnos DT'!$D$6:$D$456,Resumen!$B14,'Eventos B2B_MKT y Turnos DT'!$G$6:$G$456,"B2B") -> 0 | L14: =SUMIFS('Eventos B2B_MKT y Turnos DT'!$K$6:$K$456,'Eventos B2B_MKT y Turnos DT'!$D$6:$D$456,Resumen!$B14,'Eventos B2B_MKT y Turnos DT'!$G$6:$G$456,"Hotel") -> 0 | M14: =SUMIFS('Eventos B2B_MKT y Turnos DT'!$K$6:$K$456,'Eventos B2B_MKT y Turnos DT'!$D$6:$D$456,Resumen!$B14,'Eventos B2B_MKT y Turnos DT'!$G$6:$G$456,"Marketing") -> 0 | N14: =SUMIF(Incidencias!$E$4:$E$89,$B14,Incidencias!$K$4:$K$89) -> 0 | O14: =SUM(D14:N14) -> 22689 | P14: 0 | Q14: =+IF(AND(P14<>0,P14>O14*0.2),O14*0.2,P14) -> 0 | R14: =IFERROR(Q14/O14,0) -> 0 | S14: =IFERROR(P14-Q14,"") -> 0 | T14: =O14*(1-0.1525)-Q14 -> 19228.928 | U14: =+IF(O14*(1-0.1525)-Q14=T14,"OK","REVISAR") -> OK
B15: =Nómina!D12 -> 16910373-9 | C15: =Nómina!E12 -> CAMILA ANDREA VILLASECA AZOCAR | D15: =SUMIFS(BASE!$Q$3:$Q$453,BASE!$O$3:$O$453,Resumen!D$5,BASE!$B$3:$B$453,Resumen!$B15) -> 0 | E15: =SUMIFS(BASE!$Q$3:$Q$453,BASE!$O$3:$O$453,Resumen!E$5,BASE!$B$3:$B$453,Resumen!$B15) -> 0 | F15: =SUMIFS(BASE!$Q$3:$Q$453,BASE!$O$3:$O$453,Resumen!F$5,BASE!$B$3:$B$453,Resumen!$B15) -> 0 | G15: =SUMIFS(BASE!$Q$3:$Q$453,BASE!$O$3:$O$453,Resumen!G$5,BASE!$B$3:$B$453,Resumen!$B15) -> 0 | H15: =SUMIFS(BASE!$Q$3:$Q$453,BASE!$O$3:$O$453,Resumen!H$5,BASE!$B$3:$B$453,Resumen!$B15) -> 0 | I15: =SUMIFS(BASE!$Q$3:$Q$453,BASE!$O$3:$O$453,Resumen!I$5,BASE!$B$3:$B$453,Resumen!$B15) -> 0 | J15: =SUMIFS(BASE!$Q$3:$Q$453,BASE!$O$3:$O$453,Resumen!J$5,BASE!$B$3:$B$453,Resumen!$B15) -> 0 | K15: =SUMIFS('Eventos B2B_MKT y Turnos DT'!$K$6:$K$456,'Eventos B2B_MKT y Turnos DT'!$D$6:$D$456,Resumen!$B15,'Eventos B2B_MKT y Turnos DT'!$G$6:$G$456,"B2B") -> 0 | L15: =SUMIFS('Eventos B2B_MKT y Turnos DT'!$K$6:$K$456,'Eventos B2B_MKT y Turnos DT'!$D$6:$D$456,Resumen!$B15,'Eventos B2B_MKT y Turnos DT'!$G$6:$G$456,"Hotel") -> 0 | M15: =SUMIFS('Eventos B2B_MKT y Turnos DT'!$K$6:$K$456,'Eventos B2B_MKT y Turnos DT'!$D$6:$D$456,Resumen!$B15,'Eventos B2B_MKT y Turnos DT'!$G$6:$G$456,"Marketing") -> 0 | N15: =SUMIF(Incidencias!$E$4:$E$89,$B15,Incidencias!$K$4:$K$89) -> 0 | O15: =SUM(D15:N15) -> 0 | P15: 97999.697 | Q15: 19106 | R15: =IFERROR(Q15/O15,0) -> 0 | S15: =IFERROR(P15-Q15,"") -> 78893.697 | T15: =O15*(1-0.1525)-Q15 -> -19106 | U15: =+IF(O15*(1-0.1525)-Q15=T15,"OK","REVISAR") -> OK
B16: =Nómina!D13 -> 17326936-6 | C16: =Nómina!E13 -> CAMILO LOPEZ OMINAMI | D16: =SUMIFS(BASE!$Q$3:$Q$453,BASE!$O$3:$O$453,Resumen!D$5,BASE!$B$3:$B$453,Resumen!$B16) -> 0 | E16: =SUMIFS(BASE!$Q$3:$Q$453,BASE!$O$3:$O$453,Resumen!E$5,BASE!$B$3:$B$453,Resumen!$B16) -> 0 | F16: =SUMIFS(BASE!$Q$3:$Q$453,BASE!$O$3:$O$453,Resumen!F$5,BASE!$B$3:$B$453,Resumen!$B16) -> 0 | G16: =SUMIFS(BASE!$Q$3:$Q$453,BASE!$O$3:$O$453,Resumen!G$5,BASE!$B$3:$B$453,Resumen!$B16) -> 0 | H16: =SUMIFS(BASE!$Q$3:$Q$453,BASE!$O$3:$O$453,Resumen!H$5,BASE!$B$3:$B$453,Resumen!$B16) -> 0 | I16: =SUMIFS(BASE!$Q$3:$Q$453,BASE!$O$3:$O$453,Resumen!I$5,BASE!$B$3:$B$453,Resumen!$B16) -> 0 | J16: =SUMIFS(BASE!$Q$3:$Q$453,BASE!$O$3:$O$453,Resumen!J$5,BASE!$B$3:$B$453,Resumen!$B16) -> 0 | K16: =SUMIFS('Eventos B2B_MKT y Turnos DT'!$K$6:$K$456,'Eventos B2B_MKT y Turnos DT'!$D$6:$D$456,Resumen!$B16,'Eventos B2B_MKT y Turnos DT'!$G$6:$G$456,"B2B") -> 0 | L16: =SUMIFS('Eventos B2B_MKT y Turnos DT'!$K$6:$K$456,'Eventos B2B_MKT y Turnos DT'!$D$6:$D$456,Resumen!$B16,'Eventos B2B_MKT y Turnos DT'!$G$6:$G$456,"Hotel") -> 0 | M16: =SUMIFS('Eventos B2B_MKT y Turnos DT'!$K$6:$K$456,'Eventos B2B_MKT y Turnos DT'!$D$6:$D$456,Resumen!$B16,'Eventos B2B_MKT y Turnos DT'!$G$6:$G$456,"Marketing") -> 0 | N16: =SUMIF(Incidencias!$E$4:$E$89,$B16,Incidencias!$K$4:$K$89) -> 0 | O16: =SUM(D16:N16) -> 0 | P16: 4.9960036e-16 | Q16: =+IF(AND(P16<>0,P16>O16*0.2),O16*0.2,P16) -> 0 | R16: =IFERROR(Q16/O16,0) -> 0 | S16: =IFERROR(P16-Q16,"") -> 4.9960036e-16 | T16: =O16*(1-0.1525)-Q16 -> 0 | U16: =+IF(O16*(1-0.1525)-Q16=T16,"OK","REVISAR") -> OK
B17: =Nómina!D14 -> 21870821-8 | C17: =Nómina!E14 -> CARLA IRELA CARMONA ARTURO | D17: =SUMIFS(BASE!$Q$3:$Q$453,BASE!$O$3:$O$453,Resumen!D$5,BASE!$B$3:$B$453,Resumen!$B17) -> 0 | E17: =SUMIFS(BASE!$Q$3:$Q$453,BASE!$O$3:$O$453,Resumen!E$5,BASE!$B$3:$B$453,Resumen!$B17) -> 0 | F17: =SUMIFS(BASE!$Q$3:$Q$453,BASE!$O$3:$O$453,Resumen!F$5,BASE!$B$3:$B$453,Resumen!$B17) -> 0 | G17: =SUMIFS(BASE!$Q$3:$Q$453,BASE!$O$3:$O$453,Resumen!G$5,BASE!$B$3:$B$453,Resumen!$B17) -> 0 | H17: =SUMIFS(BASE!$Q$3:$Q$453,BASE!$O$3:$O$453,Resumen!H$5,BASE!$B$3:$B$453,Resumen!$B17) -> 0 | I17: =SUMIFS(BASE!$Q$3:$Q$453,BASE!$O$3:$O$453,Resumen!I$5,BASE!$B$3:$B$453,Resumen!$B17) -> 0 | J17: =SUMIFS(BASE!$Q$3:$Q$453,BASE!$O$3:$O$453,Resumen!J$5,BASE!$B$3:$B$453,Resumen!$B17) -> 0 | K17: =SUMIFS('Eventos B2B_MKT y Turnos DT'!$K$6:$K$456,'Eventos B2B_MKT y Turnos DT'!$D$6:$D$456,Resumen!$B17,'Eventos B2B_MKT y Turnos DT'!$G$6:$G$456,"B2B") -> 0 | L17: =SUMIFS('Eventos B2B_MKT y Turnos DT'!$K$6:$K$456,'Eventos B2B_MKT y Turnos DT'!$D$6:$D$456,Resumen!$B17,'Eventos B2B_MKT y Turnos DT'!$G$6:$G$456,"Hotel") -> 0 | M17: =SUMIFS('Eventos B2B_MKT y Turnos DT'!$K$6:$K$456,'Eventos B2B_MKT y Turnos DT'!$D$6:$D$456,Resumen!$B17,'Eventos B2B_MKT y Turnos DT'!$G$6:$G$456,"Marketing") -> 0 | N17: =SUMIF(Incidencias!$E$4:$E$89,$B17,Incidencias!$K$4:$K$89) -> 0 | O17: =SUM(D17:N17) -> 0 | P17: 136000.03 | R17: =IFERROR(Q17/O17,0) -> 0 | S17: =IFERROR(P17-Q17,"") -> 136000.03 | T17: =O17*(1-0.1525)-Q17 -> 0
B18: =Nómina!D15 -> 17664480-K | C18: =Nómina!E15 -> CARLA VERGARA FUENZALIDA | D18: =SUMIFS(BASE!$Q$3:$Q$453,BASE!$O$3:$O$453,Resumen!D$5,BASE!$B$3:$B$453,Resumen!$B18) -> 0 | E18: =SUMIFS(BASE!$Q$3:$Q$453,BASE!$O$3:$O$453,Resumen!E$5,BASE!$B$3:$B$453,Resumen!$B18) -> 0 | F18: =SUMIFS(BASE!$Q$3:$Q$453,BASE!$O$3:$O$453,Resumen!F$5,BASE!$B$3:$B$453,Resumen!$B18) -> 0 | G18: =SUMIFS(BASE!$Q$3:$Q$453,BASE!$O$3:$O$453,Resumen!G$5,BASE!$B$3:$B$453,Resumen!$B18) -> 0 | H18: =SUMIFS(BASE!$Q$3:$Q$453,BASE!$O$3:$O$453,Resumen!H$5,BASE!$B$3:$B$453,Resumen!$B18) -> 0 | I18: =SUMIFS(BASE!$Q$3:$Q$453,BASE!$O$3:$O$453,Resumen!I$5,BASE!$B$3:$B$453,Resumen!$B18) -> 0 | J18: =SUMIFS(BASE!$Q$3:$Q$453,BASE!$O$3:$O$453,Resumen!J$5,BASE!$B$3:$B$453,Resumen!$B18) -> 0 | K18: =SUMIFS('Eventos B2B_MKT y Turnos DT'!$K$6:$K$456,'Eventos B2B_MKT y Turnos DT'!$D$6:$D$456,Resumen!$B18,'Eventos B2B_MKT y Turnos DT'!$G$6:$G$456,"B2B") -> 0 | L18: =SUMIFS('Eventos B2B_MKT y Turnos DT'!$K$6:$K$456,'Eventos B2B_MKT y Turnos DT'!$D$6:$D$456,Resumen!$B18,'Eventos B2B_MKT y Turnos DT'!$G$6:$G$456,"Hotel") -> 0 | M18: =SUMIFS('Eventos B2B_MKT y Turnos DT'!$K$6:$K$456,'Eventos B2B_MKT y Turnos DT'!$D$6:$D$456,Resumen!$B18,'Eventos B2B_MKT y Turnos DT'!$G$6:$G$456,"Marketing") -> 0 | N18: =SUMIF(Incidencias!$E$4:$E$89,$B18,Incidencias!$K$4:$K$89) -> 0 | O18: =SUM(D18:N18) -> 0 | P18: 90000 | R18: =IFERROR(Q18/O18,0) -> 0 | S18: =IFERROR(P18-Q18,"") -> 90000 | T18: =O18*(1-0.1525)-Q18 -> 0
B19: =Nómina!D16 -> 18444844-0 | C19: =Nómina!E16 -> CARMEN GLORIA ADARO CARTAGENA | D19: =SUMIFS(BASE!$Q$3:$Q$453,BASE!$O$3:$O$453,Resumen!D$5,BASE!$B$3:$B$453,Resumen!$B19) -> 0 | E19: =SUMIFS(BASE!$Q$3:$Q$453,BASE!$O$3:$O$453,Resumen!E$5,BASE!$B$3:$B$453,Resumen!$B19) -> 0 | F19: =SUMIFS(BASE!$Q$3:$Q$453,BASE!$O$3:$O$453,Resumen!F$5,BASE!$B$3:$B$453,Resumen!$B19) -> 0 | G19: =SUMIFS(BASE!$Q$3:$Q$453,BASE!$O$3:$O$453,Resumen!G$5,BASE!$B$3:$B$453,Resumen!$B19) -> 0 | H19: =SUMIFS(BASE!$Q$3:$Q$453,BASE!$O$3:$O$453,Resumen!H$5,BASE!$B$3:$B$453,Resumen!$B19) -> 0 | I19: =SUMIFS(BASE!$Q$3:$Q$453,BASE!$O$3:$O$453,Resumen!I$5,BASE!$B$3:$B$453,Resumen!$B19) -> 0 | J19: =SUMIFS(BASE!$Q$3:$Q$453,BASE!$O$3:$O$453,Resumen!J$5,BASE!$B$3:$B$453,Resumen!$B19) -> 0 | K19: =SUMIFS('Eventos B2B_MKT y Turnos DT'!$K$6:$K$456,'Eventos B2B_MKT y Turnos DT'!$D$6:$D$456,Resumen!$B19,'Eventos B2B_MKT y Turnos DT'!$G$6:$G$456,"B2B") -> 0 | L19: =SUMIFS('Eventos B2B_MKT y Turnos DT'!$K$6:$K$456,'Eventos B2B_MKT y Turnos DT'!$D$6:$D$456,Resumen!$B19,'Eventos B2B_MKT y Turnos DT'!$G$6:$G$456,"Hotel") -> 0 | M19: =SUMIFS('Eventos B2B_MKT y Turnos DT'!$K$6:$K$456,'Eventos B2B_MKT y Turnos DT'!$D$6:$D$456,Resumen!$B19,'Eventos B2B_MKT y Turnos DT'!$G$6:$G$456,"Marketing") -> 0 | N19: =SUMIF(Incidencias!$E$4:$E$89,$B19,Incidencias!$K$4:$K$89) -> 0 | O19: =SUM(D19:N19) -> 0 | P19: 133390 | R19: =IFERROR(Q19/O19,0) -> 0 | S19: =IFERROR(P19-Q19,"") -> 133390 | T19: =O19*(1-0.1525)-Q19 -> 0
B20: =Nómina!D17 -> 11229241-1 | C20: =Nómina!E17 -> CARMEN GLORIA TAPIA MORA | D20: =SUMIFS(BASE!$Q$3:$Q$453,BASE!$O$3:$O$453,Resumen!D$5,BASE!$B$3:$B$453,Resumen!$B20) -> 0 | E20: =SUMIFS(BASE!$Q$3:$Q$453,BASE!$O$3:$O$453,Resumen!E$5,BASE!$B$3:$B$453,Resumen!$B20) -> 0 | F20: =SUMIFS(BASE!$Q$3:$Q$453,BASE!$O$3:$O$453,Resumen!F$5,BASE!$B$3:$B$453,Resumen!$B20) -> 0 | G20: =SUMIFS(BASE!$Q$3:$Q$453,BASE!$O$3:$O$453,Resumen!G$5,BASE!$B$3:$B$453,Resumen!$B20) -> 0 | H20: =SUMIFS(BASE!$Q$3:$Q$453,BASE!$O$3:$O$453,Resumen!H$5,BASE!$B$3:$B$453,Resumen!$B20) -> 0 | I20: =SUMIFS(BASE!$Q$3:$Q$453,BASE!$O$3:$O$453,Resumen!I$5,BASE!$B$3:$B$453,Resumen!$B20) -> 0 | J20: =SUMIFS(BASE!$Q$3:$Q$453,BASE!$O$3:$O$453,Resumen!J$5,BASE!$B$3:$B$453,Resumen!$B20) -> 0 | K20: =SUMIFS('Eventos B2B_MKT y Turnos DT'!$K$6:$K$456,'Eventos B2B_MKT y Turnos DT'!$D$6:$D$456,Resumen!$B20,'Eventos B2B_MKT y Turnos DT'!$G$6:$G$456,"B2B") -> 0 | L20: =SUMIFS('Eventos B2B_MKT y Turnos DT'!$K$6:$K$456,'Eventos B2B_MKT y Turnos DT'!$D$6:$D$456,Resumen!$B20,'Eventos B2B_MKT y Turnos DT'!$G$6:$G$456,"Hotel") -> 0 | M20: =SUMIFS('Eventos B2B_MKT y Turnos DT'!$K$6:$K$456,'Eventos B2B_MKT y Turnos DT'!$D$6:$D$456,Resumen!$B20,'Eventos B2B_MKT y Turnos DT'!$G$6:$G$456,"Marketing") -> 0 | N20: =SUMIF(Incidencias!$E$4:$E$89,$B20,Incidencias!$K$4:$K$89) -> 0 | O20: =SUM(D20:N20) -> 0 | P20: 29499 | R20: =IFERROR(Q20/O20,0) -> 0 | S20: =IFERROR(P20-Q20,"") -> 29499 | T20: =O20*(1-0.1525)-Q20 -> 0 | U20: =+IF(O20*(1-0.1525)-Q20=T20,"OK","REVISAR") -> OK
B21: =Nómina!D18 -> 18268581-K | C21: =Nómina!E18 -> CAROLINA ANDREA BUSTOS PONCE | D21: =SUMIFS(BASE!$Q$3:$Q$453,BASE!$O$3:$O$453,Resumen!D$5,BASE!$B$3:$B$453,Resumen!$B21) -> 0 | E21: =SUMIFS(BASE!$Q$3:$Q$453,BASE!$O$3:$O$453,Resumen!E$5,BASE!$B$3:$B$453,Resumen!$B21) -> 0 | F21: =SUMIFS(BASE!$Q$3:$Q$453,BASE!$O$3:$O$453,Resumen!F$5,BASE!$B$3:$B$453,Resumen!$B21) -> 0 | G21: =SUMIFS(BASE!$Q$3:$Q$453,BASE!$O$3:$O$453,Resumen!G$5,BASE!$B$3:$B$453,Resumen!$B21) -> 0 | H21: =SUMIFS(BASE!$Q$3:$Q$453,BASE!$O$3:$O$453,Resumen!H$5,BASE!$B$3:$B$453,Resumen!$B21) -> 0 | I21: =SUMIFS(BASE!$Q$3:$Q$453,BASE!$O$3:$O$453,Resumen!I$5,BASE!$B$3:$B$453,Resumen!$B21) -> 0 | J21: =SUMIFS(BASE!$Q$3:$Q$453,BASE!$O$3:$O$453,Resumen!J$5,BASE!$B$3:$B$453,Resumen!$B21) -> 0 | K21: =SUMIFS('Eventos B2B_MKT y Turnos DT'!$K$6:$K$456,'Eventos B2B_MKT y Turnos DT'!$D$6:$D$456,Resumen!$B21,'Eventos B2B_MKT y Turnos DT'!$G$6:$G$456,"B2B") -> 0 | L21: =SUMIFS('Eventos B2B_MKT y Turnos DT'!$K$6:$K$456,'Eventos B2B_MKT y Turnos DT'!$D$6:$D$456,Resumen!$B21,'Eventos B2B_MKT y Turnos DT'!$G$6:$G$456,"Hotel") -> 0 | M21: =SUMIFS('Eventos B2B_MKT y Turnos DT'!$K$6:$K$456,'Eventos B2B_MKT y Turnos DT'!$D$6:$D$456,Resumen!$B21,'Eventos B2B_MKT y Turnos DT'!$G$6:$G$456,"Marketing") -> 0 | N21: =SUMIF(Incidencias!$E$4:$E$89,$B21,Incidencias!$K$4:$K$89) -> 0 | O21: =SUM(D21:N21) -> 0 | P21: 84000 | R21: =IFERROR(Q21/O21,0) -> 0 | S21: =IFERROR(P21-Q21,"") -> 84000 | T21: =O21*(1-0.1525)-Q21 -> 0
B22: =Nómina!D19 -> 12080901-6 | C22: =Nómina!E19 -> CECILIA CARRAZANA | D22: =SUMIFS(BASE!$Q$3:$Q$453,BASE!$O$3:$O$453,Resumen!D$5,BASE!$B$3:$B$453,Resumen!$B22) -> 0 | E22: =SUMIFS(BASE!$Q$3:$Q$453,BASE!$O$3:$O$453,Resumen!E$5,BASE!$B$3:$B$453,Resumen!$B22) -> 0 | F22: =SUMIFS(BASE!$Q$3:$Q$453,BASE!$O$3:$O$453,Resumen!F$5,BASE!$B$3:$B$453,Resumen!$B22) -> 0 | G22: =SUMIFS(BASE!$Q$3:$Q$453,BASE!$O$3:$O$453,Resumen!G$5,BASE!$B$3:$B$453,Resumen!$B22) -> 0 | H22: =SUMIFS(BASE!$Q$3:$Q$453,BASE!$O$3:$O$453,Resumen!H$5,BASE!$B$3:$B$453,Resumen!$B22) -> 0 | I22: =SUMIFS(BASE!$Q$3:$Q$453,BASE!$O$3:$O$453,Resumen!I$5,BASE!$B$3:$B$453,Resumen!$B22) -> 0 | J22: =SUMIFS(BASE!$Q$3:$Q$453,BASE!$O$3:$O$453,Resumen!J$5,BASE!$B$3:$B$453,Resumen!$B22) -> 0 | K22: =SUMIFS('Eventos B2B_MKT y Turnos DT'!$K$6:$K$456,'Eventos B2B_MKT y Turnos DT'!$D$6:$D$456,Resumen!$B22,'Eventos B2B_MKT y Turnos DT'!$G$6:$G$456,"B2B") -> 0 | L22: =SUMIFS('Eventos B2B_MKT y Turnos DT'!$K$6:$K$456,'Eventos B2B_MKT y Turnos DT'!$D$6:$D$456,Resumen!$B22,'Eventos B2B_MKT y Turnos DT'!$G$6:$G$456,"Hotel") -> 0 | M22: =SUMIFS('Eventos B2B_MKT y Turnos DT'!$K$6:$K$456,'Eventos B2B_MKT y Turnos DT'!$D$6:$D$456,Resumen!$B22,'Eventos B2B_MKT y Turnos DT'!$G$6:$G$456,"Marketing") -> 0 | N22: =SUMIF(Incidencias!$E$4:$E$89,$B22,Incidencias!$K$4:$K$89) -> 0 | O22: =SUM(D22:N22) -> 0 | P22: 84000 | Q22: 6000 | R22: =IFERROR(Q22/O22,0) -> 0 | S22: =IFERROR(P22-Q22,"") -> 78000 | T22: =O22*(1-0.1525)-Q22 -> -6000 | U22: =+IF(O22*(1-0.1525)-Q22=T22,"OK","REVISAR") -> OK
B23: =Nómina!D20 -> 15353076-9 | C23: =Nómina!E20 -> CLAUDIA ALEJANDRA GUZMAN RIGORDI | D23: =SUMIFS(BASE!$Q$3:$Q$453,BASE!$O$3:$O$453,Resumen!D$5,BASE!$B$3:$B$453,Resumen!$B23) -> 99831 | E23: =SUMIFS(BASE!$Q$3:$Q$453,BASE!$O$3:$O$453,Resumen!E$5,BASE!$B$3:$B$453,Resumen!$B23) -> 0 | F23: =SUMIFS(BASE!$Q$3:$Q$453,BASE!$O$3:$O$453,Resumen!F$5,BASE!$B$3:$B$453,Resumen!$B23) -> 0 | G23: =SUMIFS(BASE!$Q$3:$Q$453,BASE!$O$3:$O$453,Resumen!G$5,BASE!$B$3:$B$453,Resumen!$B23) -> 0 | H23: =SUMIFS(BASE!$Q$3:$Q$453,BASE!$O$3:$O$453,Resumen!H$5,BASE!$B$3:$B$453,Resumen!$B23) -> 0 | I23: =SUMIFS(BASE!$Q$3:$Q$453,BASE!$O$3:$O$453,Resumen!I$5,BASE!$B$3:$B$453,Resumen!$B23) -> 0 | J23: =SUMIFS(BASE!$Q$3:$Q$453,BASE!$O$3:$O$453,Resumen!J$5,BASE!$B$3:$B$453,Resumen!$B23) -> 0 | K23: =SUMIFS('Eventos B2B_MKT y Turnos DT'!$K$6:$K$456,'Eventos B2B_MKT y Turnos DT'!$D$6:$D$456,Resumen!$B23,'Eventos B2B_MKT y Turnos DT'!$G$6:$G$456,"B2B") -> 0 | L23: =SUMIFS('Eventos B2B_MKT y Turnos DT'!$K$6:$K$456,'Eventos B2B_MKT y Turnos DT'!$D$6:$D$456,Resumen!$B23,'Eventos B2B_MKT y Turnos DT'!$G$6:$G$456,"Hotel") -> 0 | M23: =SUMIFS('Eventos B2B_MKT y Turnos DT'!$K$6:$K$456,'Eventos B2B_MKT y Turnos DT'!$D$6:$D$456,Resumen!$B23,'Eventos B2B_MKT y Turnos DT'!$G$6:$G$456,"Marketing") -> 0 | N23: =SUMIF(Incidencias!$E$4:$E$89,$B23,Incidencias!$K$4:$K$89) -> 0 | O23: =SUM(D23:N23) -> 99831 | P23: 0 | Q23: =+IF(AND(P23<>0,P23>O23*0.2),O23*0.2,P23) -> 0 | R23: =IFERROR(Q23/O23,0) -> 0 | S23: =IFERROR(P23-Q23,"") -> 0 | T23: =O23*(1-0.1525)-Q23 -> 84606.773 | U23: =+IF(O23*(1-0.1525)-Q23=T23,"OK","REVISAR") -> OK
B24: =Nómina!D21 -> 16725537-K | C24: =Nómina!E21 -> CLAUDIA ANDREA LEYTON FREDES | D24: =SUMIFS(BASE!$Q$3:$Q$453,BASE!$O$3:$O$453,Resumen!D$5,BASE!$B$3:$B$453,Resumen!$B24) -> 0 | E24: =SUMIFS(BASE!$Q$3:$Q$453,BASE!$O$3:$O$453,Resumen!E$5,BASE!$B$3:$B$453,Resumen!$B24) -> 0 | F24: =SUMIFS(BASE!$Q$3:$Q$453,BASE!$O$3:$O$453,Resumen!F$5,BASE!$B$3:$B$453,Resumen!$B24) -> 0 | G24: =SUMIFS(BASE!$Q$3:$Q$453,BASE!$O$3:$O$453,Resumen!G$5,BASE!$B$3:$B$453,Resumen!$B24) -> 0 | H24: =SUMIFS(BASE!$Q$3:$Q$453,BASE!$O$3:$O$453,Resumen!H$5,BASE!$B$3:$B$453,Resumen!$B24) -> 0 | I24: =SUMIFS(BASE!$Q$3:$Q$453,BASE!$O$3:$O$453,Resumen!I$5,BASE!$B$3:$B$453,Resumen!$B24) -> 0 | J24: =SUMIFS(BASE!$Q$3:$Q$453,BASE!$O$3:$O$453,Resumen!J$5,BASE!$B$3:$B$453,Resumen!$B24) -> 0 | K24: =SUMIFS('Eventos B2B_MKT y Turnos DT'!$K$6:$K$456,'Eventos B2B_MKT y Turnos DT'!$D$6:$D$456,Resumen!$B24,'Eventos B2B_MKT y Turnos DT'!$G$6:$G$456,"B2B") -> 0 | L24: =SUMIFS('Eventos B2B_MKT y Turnos DT'!$K$6:$K$456,'Eventos B2B_MKT y Turnos DT'!$D$6:$D$456,Resumen!$B24,'Eventos B2B_MKT y Turnos DT'!$G$6:$G$456,"Hotel") -> 0 | M24: =SUMIFS('Eventos B2B_MKT y Turnos DT'!$K$6:$K$456,'Eventos B2B_MKT y Turnos DT'!$D$6:$D$456,Resumen!$B24,'Eventos B2B_MKT y Turnos DT'!$G$6:$G$456,"Marketing") -> 0 | N24: =SUMIF(Incidencias!$E$4:$E$89,$B24,Incidencias!$K$4:$K$89) -> 0 | O24: =SUM(D24:N24) -> 0 | P24: 273000 | R24: =IFERROR(Q24/O24,0) -> 0 | S24: =IFERROR(P24-Q24,"") -> 273000 | T24: =O24*(1-0.1525)-Q24 -> 0 | U24: =+IF(O24*(1-0.1525)-Q24=T24,"OK","REVISAR") -> OK
B25: =Nómina!D22 -> 13441148-1 | C25: =Nómina!E22 -> CLAUDIA ESTRELLA ESPINOZA CANIUQUEO | D25: =SUMIFS(BASE!$Q$3:$Q$453,BASE!$O$3:$O$453,Resumen!D$5,BASE!$B$3:$B$453,Resumen!$B25) -> 65546 | E25: =SUMIFS(BASE!$Q$3:$Q$453,BASE!$O$3:$O$453,Resumen!E$5,BASE!$B$3:$B$453,Resumen!$B25) -> 0 | F25: =SUMIFS(BASE!$Q$3:$Q$453,BASE!$O$3:$O$453,Resumen!F$5,BASE!$B$3:$B$453,Resumen!$B25) -> 51428 | G25: =SUMIFS(BASE!$Q$3:$Q$453,BASE!$O$3:$O$453,Resumen!G$5,BASE!$B$3:$B$453,Resumen!$B25) -> 0 | H25: =SUMIFS(BASE!$Q$3:$Q$453,BASE!$O$3:$O$453,Resumen!H$5,BASE!$B$3:$B$453,Resumen!$B25) -> 22689 | I25: =SUMIFS(BASE!$Q$3:$Q$453,BASE!$O$3:$O$453,Resumen!I$5,BASE!$B$3:$B$453,Resumen!$B25) -> 0 | J25: =SUMIFS(BASE!$Q$3:$Q$453,BASE!$O$3:$O$453,Resumen!J$5,BASE!$B$3:$B$453,Resumen!$B25) -> 0 | K25: =SUMIFS('Eventos B2B_MKT y Turnos DT'!$K$6:$K$456,'Eventos B2B_MKT y Turnos DT'!$D$6:$D$456,Resumen!$B25,'Eventos B2B_MKT y Turnos DT'!$G$6:$G$456,"B2B") -> 106639 | L25: =SUMIFS('Eventos B2B_MKT y Turnos DT'!$K$6:$K$456,'Eventos B2B_MKT y Turnos DT'!$D$6:$D$456,Resumen!$B25,'Eventos B2B_MKT y Turnos DT'!$G$6:$G$456,"Hotel") -> 23392 | M25: =SUMIFS('Eventos B2B_MKT y Turnos DT'!$K$6:$K$456,'Eventos B2B_MKT y Turnos DT'!$D$6:$D$456,Resumen!$B25,'Eventos B2B_MKT y Turnos DT'!$G$6:$G$456,"Marketing") -> 0 | N25: =SUMIF(Incidencias!$E$4:$E$89,$B25,Incidencias!$K$4:$K$89) -> 0 | O25: =SUM(D25:N25) -> 269694 | P25: 0 | Q25: =+IF(AND(P25<>0,P25>O25*0.2),O25*0.2,P25) -> 0 | R25: =IFERROR(Q25/O25,0) -> 0 | S25: =IFERROR(P25-Q25,"") -> 0 | T25: =O25*(1-0.1525)-Q25 -> 228565.67 | U25: =+IF(O25*(1-0.1525)-Q25=T25,"OK","REVISAR") -> OK
B26: =Nómina!D23 -> 23098075-6 | C26: =Nómina!E23 -> CLAUDIA MARIA HERNANDEZ CONTRERAS | D26: =SUMIFS(BASE!$Q$3:$Q$453,BASE!$O$3:$O$453,Resumen!D$5,BASE!$B$3:$B$453,Resumen!$B26) -> 22689 | E26: =SUMIFS(BASE!$Q$3:$Q$453,BASE!$O$3:$O$453,Resumen!E$5,BASE!$B$3:$B$453,Resumen!$B26) -> 0 | F26: =SUMIFS(BASE!$Q$3:$Q$453,BASE!$O$3:$O$453,Resumen!F$5,BASE!$B$3:$B$453,Resumen!$B26) -> 0 | G26: =SUMIFS(BASE!$Q$3:$Q$453,BASE!$O$3:$O$453,Resumen!G$5,BASE!$B$3:$B$453,Resumen!$B26) -> 0 | H26: =SUMIFS(BASE!$Q$3:$Q$453,BASE!$O$3:$O$453,Resumen!H$5,BASE!$B$3:$B$453,Resumen!$B26) -> 0 | I26: =SUMIFS(BASE!$Q$3:$Q$453,BASE!$O$3:$O$453,Resumen!I$5,BASE!$B$3:$B$453,Resumen!$B26) -> 0 | J26: =SUMIFS(BASE!$Q$3:$Q$453,BASE!$O$3:$O$453,Resumen!J$5,BASE!$B$3:$B$453,Resumen!$B26) -> 0 | K26: =SUMIFS('Eventos B2B_MKT y Turnos DT'!$K$6:$K$456,'Eventos B2B_MKT y Turnos DT'!$D$6:$D$456,Resumen!$B26,'Eventos B2B_MKT y Turnos DT'!$G$6:$G$456,"B2B") -> 0 | L26: =SUMIFS('Eventos B2B_MKT y Turnos DT'!$K$6:$K$456,'Eventos B2B_MKT y Turnos DT'!$D$6:$D$456,Resumen!$B26,'Eventos B2B_MKT y Turnos DT'!$G$6:$G$456,"Hotel") -> 0 | M26: =SUMIFS('Eventos B2B_MKT y Turnos DT'!$K$6:$K$456,'Eventos B2B_MKT y Turnos DT'!$D$6:$D$456,Resumen!$B26,'Eventos B2B_MKT y Turnos DT'!$G$6:$G$456,"Marketing") -> 0 | N26: =SUMIF(Incidencias!$E$4:$E$89,$B26,Incidencias!$K$4:$K$89) -> 0 | O26: =SUM(D26:N26) -> 22689 | P26: 0 | Q26: =+IF(AND(P26<>0,P26>O26*0.2),O26*0.2,P26) -> 0 | R26: =IFERROR(Q26/O26,0) -> 0 | S26: =IFERROR(P26-Q26,"") -> 0 | T26: =O26*(1-0.1525)-Q26 -> 19228.928 | U26: =+IF(O26*(1-0.1525)-Q26=T26,"OK","REVISAR") -> OK
B27: =Nómina!D24 -> 24560038-0 | C27: =Nómina!E24 -> CLAUDIA MILENA DUQUE RAMIREZ | D27: =SUMIFS(BASE!$Q$3:$Q$453,BASE!$O$3:$O$453,Resumen!D$5,BASE!$B$3:$B$453,Resumen!$B27) -> 0 | E27: =SUMIFS(BASE!$Q$3:$Q$453,BASE!$O$3:$O$453,Resumen!E$5,BASE!$B$3:$B$453,Resumen!$B27) -> 0 | F27: =SUMIFS(BASE!$Q$3:$Q$453,BASE!$O$3:$O$453,Resumen!F$5,BASE!$B$3:$B$453,Resumen!$B27) -> 0 | G27: =SUMIFS(BASE!$Q$3:$Q$453,BASE!$O$3:$O$453,Resumen!G$5,BASE!$B$3:$B$453,Resumen!$B27) -> 0 | H27: =SUMIFS(BASE!$Q$3:$Q$453,BASE!$O$3:$O$453,Resumen!H$5,BASE!$B$3:$B$453,Resumen!$B27) -> 0 | I27: =SUMIFS(BASE!$Q$3:$Q$453,BASE!$O$3:$O$453,Resumen!I$5,BASE!$B$3:$B$453,Resumen!$B27) -> 0 | J27: =SUMIFS(BASE!$Q$3:$Q$453,BASE!$O$3:$O$453,Resumen!J$5,BASE!$B$3:$B$453,Resumen!$B27) -> 0 | K27: =SUMIFS('Eventos B2B_MKT y Turnos DT'!$K$6:$K$456,'Eventos B2B_MKT y Turnos DT'!$D$6:$D$456,Resumen!$B27,'Eventos B2B_MKT y Turnos DT'!$G$6:$G$456,"B2B") -> 0 | L27: =SUMIFS('Eventos B2B_MKT y Turnos DT'!$K$6:$K$456,'Eventos B2B_MKT y Turnos DT'!$D$6:$D$456,Resumen!$B27,'Eventos B2B_MKT y Turnos DT'!$G$6:$G$456,"Hotel") -> 0 | M27: =SUMIFS('Eventos B2B_MKT y Turnos DT'!$K$6:$K$456,'Eventos B2B_MKT y Turnos DT'!$D$6:$D$456,Resumen!$B27,'Eventos B2B_MKT y Turnos DT'!$G$6:$G$456,"Marketing") -> 0 | N27: =SUMIF(Incidencias!$E$4:$E$89,$B27,Incidencias!$K$4:$K$89) -> 0 | O27: =SUM(D27:N27) -> 0 | P27: 34499.59 | R27: =IFERROR(Q27/O27,0) -> 0 | S27: =IFERROR(P27-Q27,"") -> 34499.59 | T27: =O27*(1-0.1525)-Q27 -> 0 | U27: =+IF(O27*(1-0.1525)-Q27=T27,"OK","REVISAR") -> OK
B28: =Nómina!D25 -> 19585499-8 | C28: =Nómina!E25 -> DANIEL ABRAHAM ISAAC PEÑA HERNANDEZ | D28: =SUMIFS(BASE!$Q$3:$Q$453,BASE!$O$3:$O$453,Resumen!D$5,BASE!$B$3:$B$453,Resumen!$B28) -> 0 | E28: =SUMIFS(BASE!$Q$3:$Q$453,BASE!$O$3:$O$453,Resumen!E$5,BASE!$B$3:$B$453,Resumen!$B28) -> 0 | F28: =SUMIFS(BASE!$Q$3:$Q$453,BASE!$O$3:$O$453,Resumen!F$5,BASE!$B$3:$B$453,Resumen!$B28) -> 0 | G28: =SUMIFS(BASE!$Q$3:$Q$453,BASE!$O$3:$O$453,Resumen!G$5,BASE!$B$3:$B$453,Resumen!$B28) -> 0 | H28: =SUMIFS(BASE!$Q$3:$Q$453,BASE!$O$3:$O$453,Resumen!H$5,BASE!$B$3:$B$453,Resumen!$B28) -> 0 | I28: =SUMIFS(BASE!$Q$3:$Q$453,BASE!$O$3:$O$453,Resumen!I$5,BASE!$B$3:$B$453,Resumen!$B28) -> 0 | J28: =SUMIFS(BASE!$Q$3:$Q$453,BASE!$O$3:$O$453,Resumen!J$5,BASE!$B$3:$B$453,Resumen!$B28) -> 0 | K28: =SUMIFS('Eventos B2B_MKT y Turnos DT'!$K$6:$K$456,'Eventos B2B_MKT y Turnos DT'!$D$6:$D$456,Resumen!$B28,'Eventos B2B_MKT y Turnos DT'!$G$6:$G$456,"B2B") -> 0 | L28: =SUMIFS('Eventos B2B_MKT y Turnos DT'!$K$6:$K$456,'Eventos B2B_MKT y Turnos DT'!$D$6:$D$456,Resumen!$B28,'Eventos B2B_MKT y Turnos DT'!$G$6:$G$456,"Hotel") -> 0 | M28: =SUMIFS('Eventos B2B_MKT y Turnos DT'!$K$6:$K$456,'Eventos B2B_MKT y Turnos DT'!$D$6:$D$456,Resumen!$B28,'Eventos B2B_MKT y Turnos DT'!$G$6:$G$456,"Marketing") -> 0 | N28: =SUMIF(Incidencias!$E$4:$E$89,$B28,Incidencias!$K$4:$K$89) -> 0 | O28: =SUM(D28:N28) -> 0 | P28: 0 | Q28: =+IF(AND(P28<>0,P28>O28*0.2),O28*0.2,P28) -> 0 | R28: =IFERROR(Q28/O28,0) -> 0 | S28: =IFERROR(P28-Q28,"") -> 0 | T28: =O28*(1-0.1525)-Q28 -> 0 | U28: =+IF(O28*(1-0.1525)-Q28=T28,"OK","REVISAR") -> OK
B29: =Nómina!D26 -> 15893769-7 | C29: =Nómina!E26 -> DANIELA ANTONIA ALARCON ELIZALDE | D29: =SUMIFS(BASE!$Q$3:$Q$453,BASE!$O$3:$O$453,Resumen!D$5,BASE!$B$3:$B$453,Resumen!$B29) -> 182176 | E29: =SUMIFS(BASE!$Q$3:$Q$453,BASE!$O$3:$O$453,Resumen!E$5,BASE!$B$3:$B$453,Resumen!$B29) -> 0 | F29: =SUMIFS(BASE!$Q$3:$Q$453,BASE!$O$3:$O$453,Resumen!F$5,BASE!$B$3:$B$453,Resumen!$B29) -> 0 | G29: =SUMIFS(BASE!$Q$3:$Q$453,BASE!$O$3:$O$453,Resumen!G$5,BASE!$B$3:$B$453,Resumen!$B29) -> 0 | H29: =SUMIFS(BASE!$Q$3:$Q$453,BASE!$O$3:$O$453,Resumen!H$5,BASE!$B$3:$B$453,Resumen!$B29) -> 0 | I29: =SUMIFS(BASE!$Q$3:$Q$453,BASE!$O$3:$O$453,Resumen!I$5,BASE!$B$3:$B$453,Resumen!$B29) -> 22689 | J29: =SUMIFS(BASE!$Q$3:$Q$453,BASE!$O$3:$O$453,Resumen!J$5,BASE!$B$3:$B$453,Resumen!$B29) -> 0 | K29: =SUMIFS('Eventos B2B_MKT y Turnos DT'!$K$6:$K$456,'Eventos B2B_MKT y Turnos DT'!$D$6:$D$456,Resumen!$B29,'Eventos B2B_MKT y Turnos DT'!$G$6:$G$456,"B2B") -> 0 | L29: =SUMIFS('Eventos B2B_MKT y Turnos DT'!$K$6:$K$456,'Eventos B2B_MKT y Turnos DT'!$D$6:$D$456,Resumen!$B29,'Eventos B2B_MKT y Turnos DT'!$G$6:$G$456,"Hotel") -> 23392 | M29: =SUMIFS('Eventos B2B_MKT y Turnos DT'!$K$6:$K$456,'Eventos B2B_MKT y Turnos DT'!$D$6:$D$456,Resumen!$B29,'Eventos B2B_MKT y Turnos DT'!$G$6:$G$456,"Marketing") -> 0 | N29: =SUMIF(Incidencias!$E$4:$E$89,$B29,Incidencias!$K$4:$K$89) -> 0 | O29: =SUM(D29:N29) -> 228257 | P29: 0 | Q29: =+IF(AND(P29<>0,P29>O29*0.2),O29*0.2,P29) -> 0 | R29: =IFERROR(Q29/O29,0) -> 0 | S29: =IFERROR(P29-Q29,"") -> 0 | T29: =O29*(1-0.1525)-Q29 -> 193447.81 | U29: =+IF(O29*(1-0.1525)-Q29=T29,"OK","REVISAR") -> OK
B30: =Nómina!D27 -> 19948116-9 | C30: =Nómina!E27 -> DANIELA MARIA VARAS DIAZ | D30: =SUMIFS(BASE!$Q$3:$Q$453,BASE!$O$3:$O$453,Resumen!D$5,BASE!$B$3:$B$453,Resumen!$B30) -> 0 | E30: =SUMIFS(BASE!$Q$3:$Q$453,BASE!$O$3:$O$453,Resumen!E$5,BASE!$B$3:$B$453,Resumen!$B30) -> 0 | F30: =SUMIFS(BASE!$Q$3:$Q$453,BASE!$O$3:$O$453,Resumen!F$5,BASE!$B$3:$B$453,Resumen!$B30) -> 0 | G30: =SUMIFS(BASE!$Q$3:$Q$453,BASE!$O$3:$O$453,Resumen!G$5,BASE!$B$3:$B$453,Resumen!$B30) -> 0 | H30: =SUMIFS(BASE!$Q$3:$Q$453,BASE!$O$3:$O$453,Resumen!H$5,BASE!$B$3:$B$453,Resumen!$B30) -> 0 | I30: =SUMIFS(BASE!$Q$3:$Q$453,BASE!$O$3:$O$453,Resumen!I$5,BASE!$B$3:$B$453,Resumen!$B30) -> 0 | J30: =SUMIFS(BASE!$Q$3:$Q$453,BASE!$O$3:$O$453,Resumen!J$5,BASE!$B$3:$B$453,Resumen!$B30) -> 0 | K30: =SUMIFS('Eventos B2B_MKT y Turnos DT'!$K$6:$K$456,'Eventos B2B_MKT y Turnos DT'!$D$6:$D$456,Resumen!$B30,'Eventos B2B_MKT y Turnos DT'!$G$6:$G$456,"B2B") -> 0 | L30: =SUMIFS('Eventos B2B_MKT y Turnos DT'!$K$6:$K$456,'Eventos B2B_MKT y Turnos DT'!$D$6:$D$456,Resumen!$B30,'Eventos B2B_MKT y Turnos DT'!$G$6:$G$456,"Hotel") -> 0 | M30: =SUMIFS('Eventos B2B_MKT y Turnos DT'!$K$6:$K$456,'Eventos B2B_MKT y Turnos DT'!$D$6:$D$456,Resumen!$B30,'Eventos B2B_MKT y Turnos DT'!$G$6:$G$456,"Marketing") -> 0 | N30: =SUMIF(Incidencias!$E$4:$E$89,$B30,Incidencias!$K$4:$K$89) -> 0 | O30: =SUM(D30:N30) -> 0 | P30: 61500 | Q30: 7500 | R30: =IFERROR(Q30/O30,0) -> 0 | S30: =IFERROR(P30-Q30,"") -> 54000 | T30: =O30*(1-0.1525)-Q30 -> -7500 | U30: =+IF(O30*(1-0.1525)-Q30=T30,"OK","REVISAR") -> OK
B31: =Nómina!D28 -> 19668624-K | C31: =Nómina!E28 -> DIEGO JOSE GUERRERO ULLOA | D31: =SUMIFS(BASE!$Q$3:$Q$453,BASE!$O$3:$O$453,Resumen!D$5,BASE!$B$3:$B$453,Resumen!$B31) -> 0 | E31: =SUMIFS(BASE!$Q$3:$Q$453,BASE!$O$3:$O$453,Resumen!E$5,BASE!$B$3:$B$453,Resumen!$B31) -> 0 | F31: =SUMIFS(BASE!$Q$3:$Q$453,BASE!$O$3:$O$453,Resumen!F$5,BASE!$B$3:$B$453,Resumen!$B31) -> 0 | G31: =SUMIFS(BASE!$Q$3:$Q$453,BASE!$O$3:$O$453,Resumen!G$5,BASE!$B$3:$B$453,Resumen!$B31) -> 0 | H31: =SUMIFS(BASE!$Q$3:$Q$453,BASE!$O$3:$O$453,Resumen!H$5,BASE!$B$3:$B$453,Resumen!$B31) -> 0 | I31: =SUMIFS(BASE!$Q$3:$Q$453,BASE!$O$3:$O$453,Resumen!I$5,BASE!$B$3:$B$453,Resumen!$B31) -> 0 | J31: =SUMIFS(BASE!$Q$3:$Q$453,BASE!$O$3:$O$453,Resumen!J$5,BASE!$B$3:$B$453,Resumen!$B31) -> 0 | K31: =SUMIFS('Eventos B2B_MKT y Turnos DT'!$K$6:$K$456,'Eventos B2B_MKT y Turnos DT'!$D$6:$D$456,Resumen!$B31,'Eventos B2B_MKT y Turnos DT'!$G$6:$G$456,"B2B") -> 0 | L31: =SUMIFS('Eventos B2B_MKT y Turnos DT'!$K$6:$K$456,'Eventos B2B_MKT y Turnos DT'!$D$6:$D$456,Resumen!$B31,'Eventos B2B_MKT y Turnos DT'!$G$6:$G$456,"Hotel") -> 0 | M31: =SUMIFS('Eventos B2B_MKT y Turnos DT'!$K$6:$K$456,'Eventos B2B_MKT y Turnos DT'!$D$6:$D$456,Resumen!$B31,'Eventos B2B_MKT y Turnos DT'!$G$6:$G$456,"Marketing") -> 0 | N31: =SUMIF(Incidencias!$E$4:$E$89,$B31,Incidencias!$K$4:$K$89) -> 0 | O31: =SUM(D31:N31) -> 0 | P31: 0 | R31: =IFERROR(Q31/O31,0) -> 0 | S31: =IFERROR(P31-Q31,"") -> 0 | T31: =O31*(1-0.1525)-Q31 -> 0
B32: =Nómina!D29 -> 23785099-8 | C32: =Nómina!E29 -> DIEGO TOBIAS CARDENAS GARCIA | D32: =SUMIFS(BASE!$Q$3:$Q$453,BASE!$O$3:$O$453,Resumen!D$5,BASE!$B$3:$B$453,Resumen!$B32) -> 0 | E32: =SUMIFS(BASE!$Q$3:$Q$453,BASE!$O$3:$O$453,Resumen!E$5,BASE!$B$3:$B$453,Resumen!$B32) -> 0 | F32: =SUMIFS(BASE!$Q$3:$Q$453,BASE!$O$3:$O$453,Resumen!F$5,BASE!$B$3:$B$453,Resumen!$B32) -> 0 | G32: =SUMIFS(BASE!$Q$3:$Q$453,BASE!$O$3:$O$453,Resumen!G$5,BASE!$B$3:$B$453,Resumen!$B32) -> 0 | H32: =SUMIFS(BASE!$Q$3:$Q$453,BASE!$O$3:$O$453,Resumen!H$5,BASE!$B$3:$B$453,Resumen!$B32) -> 0 | I32: =SUMIFS(BASE!$Q$3:$Q$453,BASE!$O$3:$O$453,Resumen!I$5,BASE!$B$3:$B$453,Resumen!$B32) -> 0 | J32: =SUMIFS(BASE!$Q$3:$Q$453,BASE!$O$3:$O$453,Resumen!J$5,BASE!$B$3:$B$453,Resumen!$B32) -> 0 | K32: =SUMIFS('Eventos B2B_MKT y Turnos DT'!$K$6:$K$456,'Eventos B2B_MKT y Turnos DT'!$D$6:$D$456,Resumen!$B32,'Eventos B2B_MKT y Turnos DT'!$G$6:$G$456,"B2B") -> 0 | L32: =SUMIFS('Eventos B2B_MKT y Turnos DT'!$K$6:$K$456,'Eventos B2B_MKT y Turnos DT'!$D$6:$D$456,Resumen!$B32,'Eventos B2B_MKT y Turnos DT'!$G$6:$G$456,"Hotel") -> 0 | M32: =SUMIFS('Eventos B2B_MKT y Turnos DT'!$K$6:$K$456,'Eventos B2B_MKT y Turnos DT'!$D$6:$D$456,Resumen!$B32,'Eventos B2B_MKT y Turnos DT'!$G$6:$G$456,"Marketing") -> 0 | N32: =SUMIF(Incidencias!$E$4:$E$89,$B32,Incidencias!$K$4:$K$89) -> 0 | O32: =SUM(D32:N32) -> 0 | P32: 113273 | R32: =IFERROR(Q32/O32,0) -> 0 | S32: =IFERROR(P32-Q32,"") -> 113273 | T32: =O32*(1-0.1525)-Q32 -> 0
B33: =Nómina!D30 -> 15300506-0 | C33: =Nómina!E30 -> DOMITILA DEL PILAR SERON ALMONACID | D33: =SUMIFS(BASE!$Q$3:$Q$453,BASE!$O$3:$O$453,Resumen!D$5,BASE!$B$3:$B$453,Resumen!$B33) -> 0 | E33: =SUMIFS(BASE!$Q$3:$Q$453,BASE!$O$3:$O$453,Resumen!E$5,BASE!$B$3:$B$453,Resumen!$B33) -> 0 | F33: =SUMIFS(BASE!$Q$3:$Q$453,BASE!$O$3:$O$453,Resumen!F$5,BASE!$B$3:$B$453,Resumen!$B33) -> 0 | G33: =SUMIFS(BASE!$Q$3:$Q$453,BASE!$O$3:$O$453,Resumen!G$5,BASE!$B$3:$B$453,Resumen!$B33) -> 0 | H33: =SUMIFS(BASE!$Q$3:$Q$453,BASE!$O$3:$O$453,Resumen!H$5,BASE!$B$3:$B$453,Resumen!$B33) -> 0 | I33: =SUMIFS(BASE!$Q$3:$Q$453,BASE!$O$3:$O$453,Resumen!I$5,BASE!$B$3:$B$453,Resumen!$B33) -> 0 | J33: =SUMIFS(BASE!$Q$3:$Q$453,BASE!$O$3:$O$453,Resumen!J$5,BASE!$B$3:$B$453,Resumen!$B33) -> 0 | K33: =SUMIFS('Eventos B2B_MKT y Turnos DT'!$K$6:$K$456,'Eventos B2B_MKT y Turnos DT'!$D$6:$D$456,Resumen!$B33,'Eventos B2B_MKT y Turnos DT'!$G$6:$G$456,"B2B") -> 0 | L33: =SUMIFS('Eventos B2B_MKT y Turnos DT'!$K$6:$K$456,'Eventos B2B_MKT y Turnos DT'!$D$6:$D$456,Resumen!$B33,'Eventos B2B_MKT y Turnos DT'!$G$6:$G$456,"Hotel") -> 0 | M33: =SUMIFS('Eventos B2B_MKT y Turnos DT'!$K$6:$K$456,'Eventos B2B_MKT y Turnos DT'!$D$6:$D$456,Resumen!$B33,'Eventos B2B_MKT y Turnos DT'!$G$6:$G$456,"Marketing") -> 0 | N33: =SUMIF(Incidencias!$E$4:$E$89,$B33,Incidencias!$K$4:$K$89) -> 0 | O33: =SUM(D33:N33) -> 0 | P33: 120773 | R33: =IFERROR(Q33/O33,0) -> 0 | S33: =IFERROR(P33-Q33,"") -> 120773 | T33: =O33*(1-0.1525)-Q33 -> 0 | U33: =+IF(O33*(1-0.1525)-Q33=T33,"OK","REVISAR") -> OK
B34: =Nómina!D31 -> 18531533-9 | C34: =Nómina!E31 -> EDUARDO DE LA CUADRA PINO | D34: =SUMIFS(BASE!$Q$3:$Q$453,BASE!$O$3:$O$453,Resumen!D$5,BASE!$B$3:$B$453,Resumen!$B34) -> 0 | E34: =SUMIFS(BASE!$Q$3:$Q$453,BASE!$O$3:$O$453,Resumen!E$5,BASE!$B$3:$B$453,Resumen!$B34) -> 0 | F34: =SUMIFS(BASE!$Q$3:$Q$453,BASE!$O$3:$O$453,Resumen!F$5,BASE!$B$3:$B$453,Resumen!$B34) -> 0 | G34: =SUMIFS(BASE!$Q$3:$Q$453,BASE!$O$3:$O$453,Resumen!G$5,BASE!$B$3:$B$453,Resumen!$B34) -> 0 | H34: =SUMIFS(BASE!$Q$3:$Q$453,BASE!$O$3:$O$453,Resumen!H$5,BASE!$B$3:$B$453,Resumen!$B34) -> 0 | I34: =SUMIFS(BASE!$Q$3:$Q$453,BASE!$O$3:$O$453,Resumen!I$5,BASE!$B$3:$B$453,Resumen!$B34) -> 0 | J34: =SUMIFS(BASE!$Q$3:$Q$453,BASE!$O$3:$O$453,Resumen!J$5,BASE!$B$3:$B$453,Resumen!$B34) -> 0 | K34: =SUMIFS('Eventos B2B_MKT y Turnos DT'!$K$6:$K$456,'Eventos B2B_MKT y Turnos DT'!$D$6:$D$456,Resumen!$B34,'Eventos B2B_MKT y Turnos DT'!$G$6:$G$456,"B2B") -> 0 | L34: =SUMIFS('Eventos B2B_MKT y Turnos DT'!$K$6:$K$456,'Eventos B2B_MKT y Turnos DT'!$D$6:$D$456,Resumen!$B34,'Eventos B2B_MKT y Turnos DT'!$G$6:$G$456,"Hotel") -> 0 | M34: =SUMIFS('Eventos B2B_MKT y Turnos DT'!$K$6:$K$456,'Eventos B2B_MKT y Turnos DT'!$D$6:$D$456,Resumen!$B34,'Eventos B2B_MKT y Turnos DT'!$G$6:$G$456,"Marketing") -> 0 | N34: =SUMIF(Incidencias!$E$4:$E$89,$B34,Incidencias!$K$4:$K$89) -> 0 | O34: =SUM(D34:N34) -> 0 | P34: 28000 | R34: =IFERROR(Q34/O34,0) -> 0 | S34: =IFERROR(P34-Q34,"") -> 28000 | T34: =O34*(1-0.1525)-Q34 -> 0
B35: =Nómina!D32 -> 17495969-2 | C35: =Nómina!E32 -> ELENA MUÑOZ MUÑOZ | D35: =SUMIFS(BASE!$Q$3:$Q$453,BASE!$O$3:$O$453,Resumen!D$5,BASE!$B$3:$B$453,Resumen!$B35) -> 0 | E35: =SUMIFS(BASE!$Q$3:$Q$453,BASE!$O$3:$O$453,Resumen!E$5,BASE!$B$3:$B$453,Resumen!$B35) -> 0 | F35: =SUMIFS(BASE!$Q$3:$Q$453,BASE!$O$3:$O$453,Resumen!F$5,BASE!$B$3:$B$453,Resumen!$B35) -> 0 | G35: =SUMIFS(BASE!$Q$3:$Q$453,BASE!$O$3:$O$453,Resumen!G$5,BASE!$B$3:$B$453,Resumen!$B35) -> 0 | H35: =SUMIFS(BASE!$Q$3:$Q$453,BASE!$O$3:$O$453,Resumen!H$5,BASE!$B$3:$B$453,Resumen!$B35) -> 0 | I35: =SUMIFS(BASE!$Q$3:$Q$453,BASE!$O$3:$O$453,Resumen!I$5,BASE!$B$3:$B$453,Resumen!$B35) -> 0 | J35: =SUMIFS(BASE!$Q$3:$Q$453,BASE!$O$3:$O$453,Resumen!J$5,BASE!$B$3:$B$453,Resumen!$B35) -> 0 | K35: =SUMIFS('Eventos B2B_MKT y Turnos DT'!$K$6:$K$456,'Eventos B2B_MKT y Turnos DT'!$D$6:$D$456,Resumen!$B35,'Eventos B2B_MKT y Turnos DT'!$G$6:$G$456,"B2B") -> 0 | L35: =SUMIFS('Eventos B2B_MKT y Turnos DT'!$K$6:$K$456,'Eventos B2B_MKT y Turnos DT'!$D$6:$D$456,Resumen!$B35,'Eventos B2B_MKT y Turnos DT'!$G$6:$G$456,"Hotel") -> 0 | M35: =SUMIFS('Eventos B2B_MKT y Turnos DT'!$K$6:$K$456,'Eventos B2B_MKT y Turnos DT'!$D$6:$D$456,Resumen!$B35,'Eventos B2B_MKT y Turnos DT'!$G$6:$G$456,"Marketing") -> 0 | N35: =SUMIF(Incidencias!$E$4:$E$89,$B35,Incidencias!$K$4:$K$89) -> 0 | O35: =SUM(D35:N35) -> 0 | P35: 0 | R35: =IFERROR(Q35/O35,0) -> 0 | S35: =IFERROR(P35-Q35,"") -> 0 | T35: =O35*(1-0.1525)-Q35 -> 0 | U35: =+IF(O35*(1-0.1525)-Q35=T35,"OK","REVISAR") -> OK
B36: =Nómina!D33 -> 13230370-3 | C36: =Nómina!E33 -> ESTEBAN MELLA GALLARDO | D36: =SUMIFS(BASE!$Q$3:$Q$453,BASE!$O$3:$O$453,Resumen!D$5,BASE!$B$3:$B$453,Resumen!$B36) -> 0 | E36: =SUMIFS(BASE!$Q$3:$Q$453,BASE!$O$3:$O$453,Resumen!E$5,BASE!$B$3:$B$453,Resumen!$B36) -> 0 | F36: =SUMIFS(BASE!$Q$3:$Q$453,BASE!$O$3:$O$453,Resumen!F$5,BASE!$B$3:$B$453,Resumen!$B36) -> 0 | G36: =SUMIFS(BASE!$Q$3:$Q$453,BASE!$O$3:$O$453,Resumen!G$5,BASE!$B$3:$B$453,Resumen!$B36) -> 0 | H36: =SUMIFS(BASE!$Q$3:$Q$453,BASE!$O$3:$O$453,Resumen!H$5,BASE!$B$3:$B$453,Resumen!$B36) -> 0 | I36: =SUMIFS(BASE!$Q$3:$Q$453,BASE!$O$3:$O$453,Resumen!I$5,BASE!$B$3:$B$453,Resumen!$B36) -> 0 | J36: =SUMIFS(BASE!$Q$3:$Q$453,BASE!$O$3:$O$453,Resumen!J$5,BASE!$B$3:$B$453,Resumen!$B36) -> 0 | K36: =SUMIFS('Eventos B2B_MKT y Turnos DT'!$K$6:$K$456,'Eventos B2B_MKT y Turnos DT'!$D$6:$D$456,Resumen!$B36,'Eventos B2B_MKT y Turnos DT'!$G$6:$G$456,"B2B") -> 0 | L36: =SUMIFS('Eventos B2B_MKT y Turnos DT'!$K$6:$K$456,'Eventos B2B_MKT y Turnos DT'!$D$6:$D$456,Resumen!$B36,'Eventos B2B_MKT y Turnos DT'!$G$6:$G$456,"Hotel") -> 0 | M36: =SUMIFS('Eventos B2B_MKT y Turnos DT'!$K$6:$K$456,'Eventos B2B_MKT y Turnos DT'!$D$6:$D$456,Resumen!$B36,'Eventos B2B_MKT y Turnos DT'!$G$6:$G$456,"Marketing") -> 0 | N36: =SUMIF(Incidencias!$E$4:$E$89,$B36,Incidencias!$K$4:$K$89) -> 0 | O36: =SUM(D36:N36) -> 0 | P36: 0 | R36: =IFERROR(Q36/O36,0) -> 0 | S36: =IFERROR(P36-Q36,"") -> 0 | T36: =O36*(1-0.1525)-Q36 -> 0
B37: =Nómina!D34 -> 12897620-5 | C37: =Nómina!E34 -> EUGENIA ISABEL MONTOYA VIELMA | D37: =SUMIFS(BASE!$Q$3:$Q$453,BASE!$O$3:$O$453,Resumen!D$5,BASE!$B$3:$B$453,Resumen!$B37) -> 70588 | E37: =SUMIFS(BASE!$Q$3:$Q$453,BASE!$O$3:$O$453,Resumen!E$5,BASE!$B$3:$B$453,Resumen!$B37) -> 0 | F37: =SUMIFS(BASE!$Q$3:$Q$453,BASE!$O$3:$O$453,Resumen!F$5,BASE!$B$3:$B$453,Resumen!$B37) -> 22689 | G37: =SUMIFS(BASE!$Q$3:$Q$453,BASE!$O$3:$O$453,Resumen!G$5,BASE!$B$3:$B$453,Resumen!$B37) -> 0 | H37: =SUMIFS(BASE!$Q$3:$Q$453,BASE!$O$3:$O$453,Resumen!H$5,BASE!$B$3:$B$453,Resumen!$B37) -> 0 | I37: =SUMIFS(BASE!$Q$3:$Q$453,BASE!$O$3:$O$453,Resumen!I$5,BASE!$B$3:$B$453,Resumen!$B37) -> 0 | J37: =SUMIFS(BASE!$Q$3:$Q$453,BASE!$O$3:$O$453,Resumen!J$5,BASE!$B$3:$B$453,Resumen!$B37) -> 0 | K37: =SUMIFS('Eventos B2B_MKT y Turnos DT'!$K$6:$K$456,'Eventos B2B_MKT y Turnos DT'!$D$6:$D$456,Resumen!$B37,'Eventos B2B_MKT y Turnos DT'!$G$6:$G$456,"B2B") -> 0 | L37: =SUMIFS('Eventos B2B_MKT y Turnos DT'!$K$6:$K$456,'Eventos B2B_MKT y Turnos DT'!$D$6:$D$456,Resumen!$B37,'Eventos B2B_MKT y Turnos DT'!$G$6:$G$456,"Hotel") -> 0 | M37: =SUMIFS('Eventos B2B_MKT y Turnos DT'!$K$6:$K$456,'Eventos B2B_MKT y Turnos DT'!$D$6:$D$456,Resumen!$B37,'Eventos B2B_MKT y Turnos DT'!$G$6:$G$456,"Marketing") -> 0 | N37: =SUMIF(Incidencias!$E$4:$E$89,$B37,Incidencias!$K$4:$K$89) -> 15000 | O37: =SUM(D37:N37) -> 108277 | P37: 0 | Q37: =+IF(AND(P37<>0,P37>O37*0.2),O37*0.2,P37) -> 0 | R37: =IFERROR(Q37/O37,0) -> 0 | S37: =IFERROR(P37-Q37,"") -> 0 | T37: =O37*(1-0.1525)-Q37 -> 91764.758 | U37: =+IF(O37*(1-0.1525)-Q37=T37,"OK","REVISAR") -> OK
B38: =Nómina!D35 -> 17379695-1 | C38: =Nómina!E35 -> FRANCISCA ANGELICA ROJAS VILCH | D38: =SUMIFS(BASE!$Q$3:$Q$453,BASE!$O$3:$O$453,Resumen!D$5,BASE!$B$3:$B$453,Resumen!$B38) -> 0 | E38: =SUMIFS(BASE!$Q$3:$Q$453,BASE!$O$3:$O$453,Resumen!E$5,BASE!$B$3:$B$453,Resumen!$B38) -> 0 | F38: =SUMIFS(BASE!$Q$3:$Q$453,BASE!$O$3:$O$453,Resumen!F$5,BASE!$B$3:$B$453,Resumen!$B38) -> 0 | G38: =SUMIFS(BASE!$Q$3:$Q$453,BASE!$O$3:$O$453,Resumen!G$5,BASE!$B$3:$B$453,Resumen!$B38) -> 0 | H38: =SUMIFS(BASE!$Q$3:$Q$453,BASE!$O$3:$O$453,Resumen!H$5,BASE!$B$3:$B$453,Resumen!$B38) -> 0 | I38: =SUMIFS(BASE!$Q$3:$Q$453,BASE!$O$3:$O$453,Resumen!I$5,BASE!$B$3:$B$453,Resumen!$B38) -> 0 | J38: =SUMIFS(BASE!$Q$3:$Q$453,BASE!$O$3:$O$453,Resumen!J$5,BASE!$B$3:$B$453,Resumen!$B38) -> 0 | K38: =SUMIFS('Eventos B2B_MKT y Turnos DT'!$K$6:$K$456,'Eventos B2B_MKT y Turnos DT'!$D$6:$D$456,Resumen!$B38,'Eventos B2B_MKT y Turnos DT'!$G$6:$G$456,"B2B") -> 0 | L38: =SUMIFS('Eventos B2B_MKT y Turnos DT'!$K$6:$K$456,'Eventos B2B_MKT y Turnos DT'!$D$6:$D$456,Resumen!$B38,'Eventos B2B_MKT y Turnos DT'!$G$6:$G$456,"Hotel") -> 0 | M38: =SUMIFS('Eventos B2B_MKT y Turnos DT'!$K$6:$K$456,'Eventos B2B_MKT y Turnos DT'!$D$6:$D$456,Resumen!$B38,'Eventos B2B_MKT y Turnos DT'!$G$6:$G$456,"Marketing") -> 0 | N38: =SUMIF(Incidencias!$E$4:$E$89,$B38,Incidencias!$K$4:$K$89) -> 0 | O38: =SUM(D38:N38) -> 0 | P38: 0 | R38: =IFERROR(Q38/O38,0) -> 0 | S38: =IFERROR(P38-Q38,"") -> 0 | T38: =O38*(1-0.1525)-Q38 -> 0 | U38: =+IF(O38*(1-0.1525)-Q38=T38,"OK","REVISAR") -> OK
B39: =Nómina!D36 -> 18786881-5 | C39: =Nómina!E36 -> FRANCISCA ARAYA OLGUIN | D39: =SUMIFS(BASE!$Q$3:$Q$453,BASE!$O$3:$O$453,Resumen!D$5,BASE!$B$3:$B$453,Resumen!$B39) -> 0 | E39: =SUMIFS(BASE!$Q$3:$Q$453,BASE!$O$3:$O$453,Resumen!E$5,BASE!$B$3:$B$453,Resumen!$B39) -> 0 | F39: =SUMIFS(BASE!$Q$3:$Q$453,BASE!$O$3:$O$453,Resumen!F$5,BASE!$B$3:$B$453,Resumen!$B39) -> 0 | G39: =SUMIFS(BASE!$Q$3:$Q$453,BASE!$O$3:$O$453,Resumen!G$5,BASE!$B$3:$B$453,Resumen!$B39) -> 0 | H39: =SUMIFS(BASE!$Q$3:$Q$453,BASE!$O$3:$O$453,Resumen!H$5,BASE!$B$3:$B$453,Resumen!$B39) -> 0 | I39: =SUMIFS(BASE!$Q$3:$Q$453,BASE!$O$3:$O$453,Resumen!I$5,BASE!$B$3:$B$453,Resumen!$B39) -> 0 | J39: =SUMIFS(BASE!$Q$3:$Q$453,BASE!$O$3:$O$453,Resumen!J$5,BASE!$B$3:$B$453,Resumen!$B39) -> 0 | K39: =SUMIFS('Eventos B2B_MKT y Turnos DT'!$K$6:$K$456,'Eventos B2B_MKT y Turnos DT'!$D$6:$D$456,Resumen!$B39,'Eventos B2B_MKT y Turnos DT'!$G$6:$G$456,"B2B") -> 0 | L39: =SUMIFS('Eventos B2B_MKT y Turnos DT'!$K$6:$K$456,'Eventos B2B_MKT y Turnos DT'!$D$6:$D$456,Resumen!$B39,'Eventos B2B_MKT y Turnos DT'!$G$6:$G$456,"Hotel") -> 0 | M39: =SUMIFS('Eventos B2B_MKT y Turnos DT'!$K$6:$K$456,'Eventos B2B_MKT y Turnos DT'!$D$6:$D$456,Resumen!$B39,'Eventos B2B_MKT y Turnos DT'!$G$6:$G$456,"Marketing") -> 0 | N39: =SUMIF(Incidencias!$E$4:$E$89,$B39,Incidencias!$K$4:$K$89) -> 0 | O39: =SUM(D39:N39) -> 0 | P39: 0 | R39: =IFERROR(Q39/O39,0) -> 0 | S39: =IFERROR(P39-Q39,"") -> 0 | T39: =O39*(1-0.1525)-Q39 -> 0 | U39: =+IF(O39*(1-0.1525)-Q39=T39,"OK","REVISAR") -> OK
B40: =Nómina!D37 -> 16744004-5 | C40: =Nómina!E37 -> FRANCISCA PAULA SAAVEDRA ROJAS | D40: =SUMIFS(BASE!$Q$3:$Q$453,BASE!$O$3:$O$453,Resumen!D$5,BASE!$B$3:$B$453,Resumen!$B40) -> 0 | E40: =SUMIFS(BASE!$Q$3:$Q$453,BASE!$O$3:$O$453,Resumen!E$5,BASE!$B$3:$B$453,Resumen!$B40) -> 0 | F40: =SUMIFS(BASE!$Q$3:$Q$453,BASE!$O$3:$O$453,Resumen!F$5,BASE!$B$3:$B$453,Resumen!$B40) -> 0 | G40: =SUMIFS(BASE!$Q$3:$Q$453,BASE!$O$3:$O$453,Resumen!G$5,BASE!$B$3:$B$453,Resumen!$B40) -> 0 | H40: =SUMIFS(BASE!$Q$3:$Q$453,BASE!$O$3:$O$453,Resumen!H$5,BASE!$B$3:$B$453,Resumen!$B40) -> 0 | I40: =SUMIFS(BASE!$Q$3:$Q$453,BASE!$O$3:$O$453,Resumen!I$5,BASE!$B$3:$B$453,Resumen!$B40) -> 0 | J40: =SUMIFS(BASE!$Q$3:$Q$453,BASE!$O$3:$O$453,Resumen!J$5,BASE!$B$3:$B$453,Resumen!$B40) -> 0 | K40: =SUMIFS('Eventos B2B_MKT y Turnos DT'!$K$6:$K$456,'Eventos B2B_MKT y Turnos DT'!$D$6:$D$456,Resumen!$B40,'Eventos B2B_MKT y Turnos DT'!$G$6:$G$456,"B2B") -> 0 | L40: =SUMIFS('Eventos B2B_MKT y Turnos DT'!$K$6:$K$456,'Eventos B2B_MKT y Turnos DT'!$D$6:$D$456,Resumen!$B40,'Eventos B2B_MKT y Turnos DT'!$G$6:$G$456,"Hotel") -> 0 | M40: =SUMIFS('Eventos B2B_MKT y Turnos DT'!$K$6:$K$456,'Eventos B2B_MKT y Turnos DT'!$D$6:$D$456,Resumen!$B40,'Eventos B2B_MKT y Turnos DT'!$G$6:$G$456,"Marketing") -> 0 | N40: =SUMIF(Incidencias!$E$4:$E$89,$B40,Incidencias!$K$4:$K$89) -> 0 | O40: =SUM(D40:N40) -> 0 | P40: 18500 | R40: =IFERROR(Q40/O40,0) -> 0 | S40: =IFERROR(P40-Q40,"") -> 18500 | T40: =O40*(1-0.1525)-Q40 -> 0 | U40: =+IF(O40*(1-0.1525)-Q40=T40,"OK","REVISAR") -> OK
B41: =Nómina!D38 -> 26598096-1 | C41: =Nómina!E38 -> GENESIS DANIELA PIMENTEL HERRERA | D41: =SUMIFS(BASE!$Q$3:$Q$453,BASE!$O$3:$O$453,Resumen!D$5,BASE!$B$3:$B$453,Resumen!$B41) -> 183025 | E41: =SUMIFS(BASE!$Q$3:$Q$453,BASE!$O$3:$O$453,Resumen!E$5,BASE!$B$3:$B$453,Resumen!$B41) -> 0 | F41: =SUMIFS(BASE!$Q$3:$Q$453,BASE!$O$3:$O$453,Resumen!F$5,BASE!$B$3:$B$453,Resumen!$B41) -> 65546 | G41: =SUMIFS(BASE!$Q$3:$Q$453,BASE!$O$3:$O$453,Resumen!G$5,BASE!$B$3:$B$453,Resumen!$B41) -> 0 | H41: =SUMIFS(BASE!$Q$3:$Q$453,BASE!$O$3:$O$453,Resumen!H$5,BASE!$B$3:$B$453,Resumen!$B41) -> 0 | I41: =SUMIFS(BASE!$Q$3:$Q$453,BASE!$O$3:$O$453,Resumen!I$5,BASE!$B$3:$B$453,Resumen!$B41) -> 0 | J41: =SUMIFS(BASE!$Q$3:$Q$453,BASE!$O$3:$O$453,Resumen!J$5,BASE!$B$3:$B$453,Resumen!$B41) -> 0 | K41: =SUMIFS('Eventos B2B_MKT y Turnos DT'!$K$6:$K$456,'Eventos B2B_MKT y Turnos DT'!$D$6:$D$456,Resumen!$B41,'Eventos B2B_MKT y Turnos DT'!$G$6:$G$456,"B2B") -> 0 | L41: =SUMIFS('Eventos B2B_MKT y Turnos DT'!$K$6:$K$456,'Eventos B2B_MKT y Turnos DT'!$D$6:$D$456,Resumen!$B41,'Eventos B2B_MKT y Turnos DT'!$G$6:$G$456,"Hotel") -> 23392 | M41: =SUMIFS('Eventos B2B_MKT y Turnos DT'!$K$6:$K$456,'Eventos B2B_MKT y Turnos DT'!$D$6:$D$456,Resumen!$B41,'Eventos B2B_MKT y Turnos DT'!$G$6:$G$456,"Marketing") -> 0 | N41: =SUMIF(Incidencias!$E$4:$E$89,$B41,Incidencias!$K$4:$K$89) -> 0 | O41: =SUM(D41:N41) -> 271963 | P41: 0 | Q41: =+IF(AND(P41<>0,P41>O41*0.2),O41*0.2,P41) -> 0 | R41: =IFERROR(Q41/O41,0) -> 0 | S41: =IFERROR(P41-Q41,"") -> 0 | T41: =O41*(1-0.1525)-Q41 -> 230488.64 | U41: =+IF(O41*(1-0.1525)-Q41=T41,"OK","REVISAR") -> OK
B42: =Nómina!D39 -> 27828546-4 | C42: =Nómina!E39 -> GENESIS VALENTINA SALAZAR GUEVARA | D42: =SUMIFS(BASE!$Q$3:$Q$453,BASE!$O$3:$O$453,Resumen!D$5,BASE!$B$3:$B$453,Resumen!$B42) -> 177134 | E42: =SUMIFS(BASE!$Q$3:$Q$453,BASE!$O$3:$O$453,Resumen!E$5,BASE!$B$3:$B$453,Resumen!$B42) -> 0 | F42: =SUMIFS(BASE!$Q$3:$Q$453,BASE!$O$3:$O$453,Resumen!F$5,BASE!$B$3:$B$453,Resumen!$B42) -> 118487 | G42: =SUMIFS(BASE!$Q$3:$Q$453,BASE!$O$3:$O$453,Resumen!G$5,BASE!$B$3:$B$453,Resumen!$B42) -> 0 | H42: =SUMIFS(BASE!$Q$3:$Q$453,BASE!$O$3:$O$453,Resumen!H$5,BASE!$B$3:$B$453,Resumen!$B42) -> 0 | I42: =SUMIFS(BASE!$Q$3:$Q$453,BASE!$O$3:$O$453,Resumen!I$5,BASE!$B$3:$B$453,Resumen!$B42) -> 0 | J42: =SUMIFS(BASE!$Q$3:$Q$453,BASE!$O$3:$O$453,Resumen!J$5,BASE!$B$3:$B$453,Resumen!$B42) -> 0 | K42: =SUMIFS('Eventos B2B_MKT y Turnos DT'!$K$6:$K$456,'Eventos B2B_MKT y Turnos DT'!$D$6:$D$456,Resumen!$B42,'Eventos B2B_MKT y Turnos DT'!$G$6:$G$456,"B2B") -> 0 | L42: =SUMIFS('Eventos B2B_MKT y Turnos DT'!$K$6:$K$456,'Eventos B2B_MKT y Turnos DT'!$D$6:$D$456,Resumen!$B42,'Eventos B2B_MKT y Turnos DT'!$G$6:$G$456,"Hotel") -> 0 | M42: =SUMIFS('Eventos B2B_MKT y Turnos DT'!$K$6:$K$456,'Eventos B2B_MKT y Turnos DT'!$D$6:$D$456,Resumen!$B42,'Eventos B2B_MKT y Turnos DT'!$G$6:$G$456,"Marketing") -> 0 | N42: =SUMIF(Incidencias!$E$4:$E$89,$B42,Incidencias!$K$4:$K$89) -> 0 | O42: =SUM(D42:N42) -> 295621 | P42: 0 | Q42: =+IF(AND(P42<>0,P42>O42*0.2),O42*0.2,P42) -> 0 | R42: =IFERROR(Q42/O42,0) -> 0 | S42: =IFERROR(P42-Q42,"") -> 0 | T42: =O42*(1-0.1525)-Q42 -> 250538.8 | U42: =+IF(O42*(1-0.1525)-Q42=T42,"OK","REVISAR") -> OK
B43: =Nómina!D40 -> 17681238-9 | C43: =Nómina!E40 -> IVVO LEANDRO VERGARA SALINAS | D43: =SUMIFS(BASE!$Q$3:$Q$453,BASE!$O$3:$O$453,Resumen!D$5,BASE!$B$3:$B$453,Resumen!$B43) -> 25210 | E43: =SUMIFS(BASE!$Q$3:$Q$453,BASE!$O$3:$O$453,Resumen!E$5,BASE!$B$3:$B$453,Resumen!$B43) -> 0 | F43: =SUMIFS(BASE!$Q$3:$Q$453,BASE!$O$3:$O$453,Resumen!F$5,BASE!$B$3:$B$453,Resumen!$B43) -> 82185 | G43: =SUMIFS(BASE!$Q$3:$Q$453,BASE!$O$3:$O$453,Resumen!G$5,BASE!$B$3:$B$453,Resumen!$B43) -> 0 | H43: =SUMIFS(BASE!$Q$3:$Q$453,BASE!$O$3:$O$453,Resumen!H$5,BASE!$B$3:$B$453,Resumen!$B43) -> 0 | I43: =SUMIFS(BASE!$Q$3:$Q$453,BASE!$O$3:$O$453,Resumen!I$5,BASE!$B$3:$B$453,Resumen!$B43) -> 0 | J43: =SUMIFS(BASE!$Q$3:$Q$453,BASE!$O$3:$O$453,Resumen!J$5,BASE!$B$3:$B$453,Resumen!$B43) -> 0 | K43: =SUMIFS('Eventos B2B_MKT y Turnos DT'!$K$6:$K$456,'Eventos B2B_MKT y Turnos DT'!$D$6:$D$456,Resumen!$B43,'Eventos B2B_MKT y Turnos DT'!$G$6:$G$456,"B2B") -> 0 | L43: =SUMIFS('Eventos B2B_MKT y Turnos DT'!$K$6:$K$456,'Eventos B2B_MKT y Turnos DT'!$D$6:$D$456,Resumen!$B43,'Eventos B2B_MKT y Turnos DT'!$G$6:$G$456,"Hotel") -> 46784 | M43: =SUMIFS('Eventos B2B_MKT y Turnos DT'!$K$6:$K$456,'Eventos B2B_MKT y Turnos DT'!$D$6:$D$456,Resumen!$B43,'Eventos B2B_MKT y Turnos DT'!$G$6:$G$456,"Marketing") -> 0 | N43: =SUMIF(Incidencias!$E$4:$E$89,$B43,Incidencias!$K$4:$K$89) -> 15000 | O43: =SUM(D43:N43) -> 169179 | P43: 0 | Q43: =+IF(AND(P43<>0,P43>O43*0.2),O43*0.2,P43) -> 0 | R43: =IFERROR(Q43/O43,0) -> 0 | S43: =IFERROR(P43-Q43,"") -> 0 | T43: =O43*(1-0.1525)-Q43 -> 143379.2 | U43: =+IF(O43*(1-0.1525)-Q43=T43,"OK","REVISAR") -> OK
B44: =Nómina!D41 -> 19232974-4 | C44: =Nómina!E41 -> JOSE IGNACIO PALMA CASANOVA | D44: =SUMIFS(BASE!$Q$3:$Q$453,BASE!$O$3:$O$453,Resumen!D$5,BASE!$B$3:$B$453,Resumen!$B44) -> 22689 | E44: =SUMIFS(BASE!$Q$3:$Q$453,BASE!$O$3:$O$453,Resumen!E$5,BASE!$B$3:$B$453,Resumen!$B44) -> 0 | F44: =SUMIFS(BASE!$Q$3:$Q$453,BASE!$O$3:$O$453,Resumen!F$5,BASE!$B$3:$B$453,Resumen!$B44) -> 55462 | G44: =SUMIFS(BASE!$Q$3:$Q$453,BASE!$O$3:$O$453,Resumen!G$5,BASE!$B$3:$B$453,Resumen!$B44) -> 0 | H44: =SUMIFS(BASE!$Q$3:$Q$453,BASE!$O$3:$O$453,Resumen!H$5,BASE!$B$3:$B$453,Resumen!$B44) -> 0 | I44: =SUMIFS(BASE!$Q$3:$Q$453,BASE!$O$3:$O$453,Resumen!I$5,BASE!$B$3:$B$453,Resumen!$B44) -> 0 | J44: =SUMIFS(BASE!$Q$3:$Q$453,BASE!$O$3:$O$453,Resumen!J$5,BASE!$B$3:$B$453,Resumen!$B44) -> 0 | K44: =SUMIFS('Eventos B2B_MKT y Turnos DT'!$K$6:$K$456,'Eventos B2B_MKT y Turnos DT'!$D$6:$D$456,Resumen!$B44,'Eventos B2B_MKT y Turnos DT'!$G$6:$G$456,"B2B") -> 0 | L44: =SUMIFS('Eventos B2B_MKT y Turnos DT'!$K$6:$K$456,'Eventos B2B_MKT y Turnos DT'!$D$6:$D$456,Resumen!$B44,'Eventos B2B_MKT y Turnos DT'!$G$6:$G$456,"Hotel") -> 46784 | M44: =SUMIFS('Eventos B2B_MKT y Turnos DT'!$K$6:$K$456,'Eventos B2B_MKT y Turnos DT'!$D$6:$D$456,Resumen!$B44,'Eventos B2B_MKT y Turnos DT'!$G$6:$G$456,"Marketing") -> 0 | N44: =SUMIF(Incidencias!$E$4:$E$89,$B44,Incidencias!$K$4:$K$89) -> 0 | O44: =SUM(D44:N44) -> 124935 | P44: 11250 | Q44: =+IF(AND(P44<>0,P44>O44*0.2),O44*0.2,P44) -> 11250 | R44: =IFERROR(Q44/O44,0) -> 0.090046824 | S44: =IFERROR(P44-Q44,"") -> 0 | T44: =O44*(1-0.1525)-Q44 -> 94632.413 | U44: =+IF(O44*(1-0.1525)-Q44=T44,"OK","REVISAR") -> OK
B45: =Nómina!D42 -> 9384198-0 | C45: =Nómina!E42 -> KARIN BRILOVICH KLEINKOPF | D45: =SUMIFS(BASE!$Q$3:$Q$453,BASE!$O$3:$O$453,Resumen!D$5,BASE!$B$3:$B$453,Resumen!$B45) -> 35958 | E45: =SUMIFS(BASE!$Q$3:$Q$453,BASE!$O$3:$O$453,Resumen!E$5,BASE!$B$3:$B$453,Resumen!$B45) -> 0 | F45: =SUMIFS(BASE!$Q$3:$Q$453,BASE!$O$3:$O$453,Resumen!F$5,BASE!$B$3:$B$453,Resumen!$B45) -> 0 | G45: =SUMIFS(BASE!$Q$3:$Q$453,BASE!$O$3:$O$453,Resumen!G$5,BASE!$B$3:$B$453,Resumen!$B45) -> 0 | H45: =SUMIFS(BASE!$Q$3:$Q$453,BASE!$O$3:$O$453,Resumen!H$5,BASE!$B$3:$B$453,Resumen!$B45) -> 0 | I45: =SUMIFS(BASE!$Q$3:$Q$453,BASE!$O$3:$O$453,Resumen!I$5,BASE!$B$3:$B$453,Resumen!$B45) -> 0 | J45: =SUMIFS(BASE!$Q$3:$Q$453,BASE!$O$3:$O$453,Resumen!J$5,BASE!$B$3:$B$453,Resumen!$B45) -> 0 | K45: =SUMIFS('Eventos B2B_MKT y Turnos DT'!$K$6:$K$456,'Eventos B2B_MKT y Turnos DT'!$D$6:$D$456,Resumen!$B45,'Eventos B2B_MKT y Turnos DT'!$G$6:$G$456,"B2B") -> 0 | L45: =SUMIFS('Eventos B2B_MKT y Turnos DT'!$K$6:$K$456,'Eventos B2B_MKT y Turnos DT'!$D$6:$D$456,Resumen!$B45,'Eventos B2B_MKT y Turnos DT'!$G$6:$G$456,"Hotel") -> 0 | M45: =SUMIFS('Eventos B2B_MKT y Turnos DT'!$K$6:$K$456,'Eventos B2B_MKT y Turnos DT'!$D$6:$D$456,Resumen!$B45,'Eventos B2B_MKT y Turnos DT'!$G$6:$G$456,"Marketing") -> 0 | N45: =SUMIF(Incidencias!$E$4:$E$89,$B45,Incidencias!$K$4:$K$89) -> 0 | O45: =SUM(D45:N45) -> 35958 | P45: 75425.891 | Q45: 10426 | R45: =IFERROR(Q45/O45,0) -> 0.28994939 | S45: =IFERROR(P45-Q45,"") -> 64999.891 | T45: =O45*(1-0.1525)-Q45 -> 20048.405 | U45: =+IF(O45*(1-0.1525)-Q45=T45,"OK","REVISAR") -> OK
B46: =Nómina!D43 -> 20615813-1 | C46: =Nómina!E43 -> KEIJI NAOKI HAMASAKI ARANGUIZ | D46: =SUMIFS(BASE!$Q$3:$Q$453,BASE!$O$3:$O$453,Resumen!D$5,BASE!$B$3:$B$453,Resumen!$B46) -> 0 | E46: =SUMIFS(BASE!$Q$3:$Q$453,BASE!$O$3:$O$453,Resumen!E$5,BASE!$B$3:$B$453,Resumen!$B46) -> 0 | F46: =SUMIFS(BASE!$Q$3:$Q$453,BASE!$O$3:$O$453,Resumen!F$5,BASE!$B$3:$B$453,Resumen!$B46) -> 0 | G46: =SUMIFS(BASE!$Q$3:$Q$453,BASE!$O$3:$O$453,Resumen!G$5,BASE!$B$3:$B$453,Resumen!$B46) -> 0 | H46: =SUMIFS(BASE!$Q$3:$Q$453,BASE!$O$3:$O$453,Resumen!H$5,BASE!$B$3:$B$453,Resumen!$B46) -> 0 | I46: =SUMIFS(BASE!$Q$3:$Q$453,BASE!$O$3:$O$453,Resumen!I$5,BASE!$B$3:$B$453,Resumen!$B46) -> 0 | J46: =SUMIFS(BASE!$Q$3:$Q$453,BASE!$O$3:$O$453,Resumen!J$5,BASE!$B$3:$B$453,Resumen!$B46) -> 0 | K46: =SUMIFS('Eventos B2B_MKT y Turnos DT'!$K$6:$K$456,'Eventos B2B_MKT y Turnos DT'!$D$6:$D$456,Resumen!$B46,'Eventos B2B_MKT y Turnos DT'!$G$6:$G$456,"B2B") -> 0 | L46: =SUMIFS('Eventos B2B_MKT y Turnos DT'!$K$6:$K$456,'Eventos B2B_MKT y Turnos DT'!$D$6:$D$456,Resumen!$B46,'Eventos B2B_MKT y Turnos DT'!$G$6:$G$456,"Hotel") -> 0 | M46: =SUMIFS('Eventos B2B_MKT y Turnos DT'!$K$6:$K$456,'Eventos B2B_MKT y Turnos DT'!$D$6:$D$456,Resumen!$B46,'Eventos B2B_MKT y Turnos DT'!$G$6:$G$456,"Marketing") -> 0 | N46: =SUMIF(Incidencias!$E$4:$E$89,$B46,Incidencias!$K$4:$K$89) -> 0 | O46: =SUM(D46:N46) -> 0 | P46: 65000 | Q46: 13000 | R46: =IFERROR(Q46/O46,0) -> 0 | S46: =IFERROR(P46-Q46,"") -> 52000 | T46: =O46*(1-0.1525)-Q46 -> -13000 | U46: =+IF(O46*(1-0.1525)-Q46=T46,"OK","REVISAR") -> OK
B47: =Nómina!D44 -> 19229987-K | C47: =Nómina!E44 -> KIMBERLY NAOMI ORTEGA DUARTE | D47: =SUMIFS(BASE!$Q$3:$Q$453,BASE!$O$3:$O$453,Resumen!D$5,BASE!$B$3:$B$453,Resumen!$B47) -> 0 | E47: =SUMIFS(BASE!$Q$3:$Q$453,BASE!$O$3:$O$453,Resumen!E$5,BASE!$B$3:$B$453,Resumen!$B47) -> 0 | F47: =SUMIFS(BASE!$Q$3:$Q$453,BASE!$O$3:$O$453,Resumen!F$5,BASE!$B$3:$B$453,Resumen!$B47) -> 0 | G47: =SUMIFS(BASE!$Q$3:$Q$453,BASE!$O$3:$O$453,Resumen!G$5,BASE!$B$3:$B$453,Resumen!$B47) -> 0 | H47: =SUMIFS(BASE!$Q$3:$Q$453,BASE!$O$3:$O$453,Resumen!H$5,BASE!$B$3:$B$453,Resumen!$B47) -> 0 | I47: =SUMIFS(BASE!$Q$3:$Q$453,BASE!$O$3:$O$453,Resumen!I$5,BASE!$B$3:$B$453,Resumen!$B47) -> 0 | J47: =SUMIFS(BASE!$Q$3:$Q$453,BASE!$O$3:$O$453,Resumen!J$5,BASE!$B$3:$B$453,Resumen!$B47) -> 0 | K47: =SUMIFS('Eventos B2B_MKT y Turnos DT'!$K$6:$K$456,'Eventos B2B_MKT y Turnos DT'!$D$6:$D$456,Resumen!$B47,'Eventos B2B_MKT y Turnos DT'!$G$6:$G$456,"B2B") -> 0 | L47: =SUMIFS('Eventos B2B_MKT y Turnos DT'!$K$6:$K$456,'Eventos B2B_MKT y Turnos DT'!$D$6:$D$456,Resumen!$B47,'Eventos B2B_MKT y Turnos DT'!$G$6:$G$456,"Hotel") -> 0 | M47: =SUMIFS('Eventos B2B_MKT y Turnos DT'!$K$6:$K$456,'Eventos B2B_MKT y Turnos DT'!$D$6:$D$456,Resumen!$B47,'Eventos B2B_MKT y Turnos DT'!$G$6:$G$456,"Marketing") -> 0 | N47: =SUMIF(Incidencias!$E$4:$E$89,$B47,Incidencias!$K$4:$K$89) -> 0 | O47: =SUM(D47:N47) -> 0 | P47: 57000 | R47: =IFERROR(Q47/O47,0) -> 0 | S47: =IFERROR(P47-Q47,"") -> 57000 | T47: =O47*(1-0.1525)-Q47 -> 0
B48: =Nómina!D45 -> 23019501-3 | C48: =Nómina!E45 -> LEIDY ESPINOZA MONTOYA | D48: =SUMIFS(BASE!$Q$3:$Q$453,BASE!$O$3:$O$453,Resumen!D$5,BASE!$B$3:$B$453,Resumen!$B48) -> 0 | E48: =SUMIFS(BASE!$Q$3:$Q$453,BASE!$O$3:$O$453,Resumen!E$5,BASE!$B$3:$B$453,Resumen!$B48) -> 0 | F48: =SUMIFS(BASE!$Q$3:$Q$453,BASE!$O$3:$O$453,Resumen!F$5,BASE!$B$3:$B$453,Resumen!$B48) -> 0 | G48: =SUMIFS(BASE!$Q$3:$Q$453,BASE!$O$3:$O$453,Resumen!G$5,BASE!$B$3:$B$453,Resumen!$B48) -> 0 | H48: =SUMIFS(BASE!$Q$3:$Q$453,BASE!$O$3:$O$453,Resumen!H$5,BASE!$B$3:$B$453,Resumen!$B48) -> 0 | I48: =SUMIFS(BASE!$Q$3:$Q$453,BASE!$O$3:$O$453,Resumen!I$5,BASE!$B$3:$B$453,Resumen!$B48) -> 0 | J48: =SUMIFS(BASE!$Q$3:$Q$453,BASE!$O$3:$O$453,Resumen!J$5,BASE!$B$3:$B$453,Resumen!$B48) -> 0 | K48: =SUMIFS('Eventos B2B_MKT y Turnos DT'!$K$6:$K$456,'Eventos B2B_MKT y Turnos DT'!$D$6:$D$456,Resumen!$B48,'Eventos B2B_MKT y Turnos DT'!$G$6:$G$456,"B2B") -> 0 | L48: =SUMIFS('Eventos B2B_MKT y Turnos DT'!$K$6:$K$456,'Eventos B2B_MKT y Turnos DT'!$D$6:$D$456,Resumen!$B48,'Eventos B2B_MKT y Turnos DT'!$G$6:$G$456,"Hotel") -> 0 | M48: =SUMIFS('Eventos B2B_MKT y Turnos DT'!$K$6:$K$456,'Eventos B2B_MKT y Turnos DT'!$D$6:$D$456,Resumen!$B48,'Eventos B2B_MKT y Turnos DT'!$G$6:$G$456,"Marketing") -> 0 | N48: =SUMIF(Incidencias!$E$4:$E$89,$B48,Incidencias!$K$4:$K$89) -> 0 | O48: =SUM(D48:N48) -> 0 | P48: 13000 | R48: =IFERROR(Q48/O48,0) -> 0 | S48: =IFERROR(P48-Q48,"") -> 13000 | T48: =O48*(1-0.1525)-Q48 -> 0
B49: =Nómina!D46 -> 14565839-K | C49: =Nómina!E46 -> LILIANA ALEJANDRA FERNÁNDEZ ABARCA | D49: =SUMIFS(BASE!$Q$3:$Q$453,BASE!$O$3:$O$453,Resumen!D$5,BASE!$B$3:$B$453,Resumen!$B49) -> 0 | E49: =SUMIFS(BASE!$Q$3:$Q$453,BASE!$O$3:$O$453,Resumen!E$5,BASE!$B$3:$B$453,Resumen!$B49) -> 0 | F49: =SUMIFS(BASE!$Q$3:$Q$453,BASE!$O$3:$O$453,Resumen!F$5,BASE!$B$3:$B$453,Resumen!$B49) -> 0 | G49: =SUMIFS(BASE!$Q$3:$Q$453,BASE!$O$3:$O$453,Resumen!G$5,BASE!$B$3:$B$453,Resumen!$B49) -> 0 | H49: =SUMIFS(BASE!$Q$3:$Q$453,BASE!$O$3:$O$453,Resumen!H$5,BASE!$B$3:$B$453,Resumen!$B49) -> 0 | I49: =SUMIFS(BASE!$Q$3:$Q$453,BASE!$O$3:$O$453,Resumen!I$5,BASE!$B$3:$B$453,Resumen!$B49) -> 0 | J49: =SUMIFS(BASE!$Q$3:$Q$453,BASE!$O$3:$O$453,Resumen!J$5,BASE!$B$3:$B$453,Resumen!$B49) -> 0 | K49: =SUMIFS('Eventos B2B_MKT y Turnos DT'!$K$6:$K$456,'Eventos B2B_MKT y Turnos DT'!$D$6:$D$456,Resumen!$B49,'Eventos B2B_MKT y Turnos DT'!$G$6:$G$456,"B2B") -> 0 | L49: =SUMIFS('Eventos B2B_MKT y Turnos DT'!$K$6:$K$456,'Eventos B2B_MKT y Turnos DT'!$D$6:$D$456,Resumen!$B49,'Eventos B2B_MKT y Turnos DT'!$G$6:$G$456,"Hotel") -> 0 | M49: =SUMIFS('Eventos B2B_MKT y Turnos DT'!$K$6:$K$456,'Eventos B2B_MKT y Turnos DT'!$D$6:$D$456,Resumen!$B49,'Eventos B2B_MKT y Turnos DT'!$G$6:$G$456,"Marketing") -> 0 | N49: =SUMIF(Incidencias!$E$4:$E$89,$B49,Incidencias!$K$4:$K$89) -> 0 | O49: =SUM(D49:N49) -> 0 | P49: 0 | R49: =IFERROR(Q49/O49,0) -> 0 | S49: =IFERROR(P49-Q49,"") -> 0 | T49: =O49*(1-0.1525)-Q49 -> 0
B50: =Nómina!D47 -> 16746463-7 | C50: =Nómina!E47 -> LORENA ESPARZA AGUILAR | D50: =SUMIFS(BASE!$Q$3:$Q$453,BASE!$O$3:$O$453,Resumen!D$5,BASE!$B$3:$B$453,Resumen!$B50) -> 0 | E50: =SUMIFS(BASE!$Q$3:$Q$453,BASE!$O$3:$O$453,Resumen!E$5,BASE!$B$3:$B$453,Resumen!$B50) -> 0 | F50: =SUMIFS(BASE!$Q$3:$Q$453,BASE!$O$3:$O$453,Resumen!F$5,BASE!$B$3:$B$453,Resumen!$B50) -> 0 | G50: =SUMIFS(BASE!$Q$3:$Q$453,BASE!$O$3:$O$453,Resumen!G$5,BASE!$B$3:$B$453,Resumen!$B50) -> 0 | H50: =SUMIFS(BASE!$Q$3:$Q$453,BASE!$O$3:$O$453,Resumen!H$5,BASE!$B$3:$B$453,Resumen!$B50) -> 0 | I50: =SUMIFS(BASE!$Q$3:$Q$453,BASE!$O$3:$O$453,Resumen!I$5,BASE!$B$3:$B$453,Resumen!$B50) -> 0 | J50: =SUMIFS(BASE!$Q$3:$Q$453,BASE!$O$3:$O$453,Resumen!J$5,BASE!$B$3:$B$453,Resumen!$B50) -> 0 | K50: =SUMIFS('Eventos B2B_MKT y Turnos DT'!$K$6:$K$456,'Eventos B2B_MKT y Turnos DT'!$D$6:$D$456,Resumen!$B50,'Eventos B2B_MKT y Turnos DT'!$G$6:$G$456,"B2B") -> 0 | L50: =SUMIFS('Eventos B2B_MKT y Turnos DT'!$K$6:$K$456,'Eventos B2B_MKT y Turnos DT'!$D$6:$D$456,Resumen!$B50,'Eventos B2B_MKT y Turnos DT'!$G$6:$G$456,"Hotel") -> 0 | M50: =SUMIFS('Eventos B2B_MKT y Turnos DT'!$K$6:$K$456,'Eventos B2B_MKT y Turnos DT'!$D$6:$D$456,Resumen!$B50,'Eventos B2B_MKT y Turnos DT'!$G$6:$G$456,"Marketing") -> 0 | N50: =SUMIF(Incidencias!$E$4:$E$89,$B50,Incidencias!$K$4:$K$89) -> 0 | O50: =SUM(D50:N50) -> 0 | P50: 0 | Q50: =P50 -> 0 | R50: =IFERROR(Q50/O50,0) -> 0 | S50: =IFERROR(P50-Q50,"") -> 0 | T50: =O50*(1-0.1525)-Q50 -> 0 | U50: =+IF(O50*(1-0.1525)-Q50=T50,"OK","REVISAR") -> OK
B51: =Nómina!D48 -> 19774861-3 | C51: =Nómina!E48 -> LUCERO ALEXANDRA ZAVALA VILLARROEL | D51: =SUMIFS(BASE!$Q$3:$Q$453,BASE!$O$3:$O$453,Resumen!D$5,BASE!$B$3:$B$453,Resumen!$B51) -> 0 | E51: =SUMIFS(BASE!$Q$3:$Q$453,BASE!$O$3:$O$453,Resumen!E$5,BASE!$B$3:$B$453,Resumen!$B51) -> 0 | F51: =SUMIFS(BASE!$Q$3:$Q$453,BASE!$O$3:$O$453,Resumen!F$5,BASE!$B$3:$B$453,Resumen!$B51) -> 0 | G51: =SUMIFS(BASE!$Q$3:$Q$453,BASE!$O$3:$O$453,Resumen!G$5,BASE!$B$3:$B$453,Resumen!$B51) -> 0 | H51: =SUMIFS(BASE!$Q$3:$Q$453,BASE!$O$3:$O$453,Resumen!H$5,BASE!$B$3:$B$453,Resumen!$B51) -> 0 | I51: =SUMIFS(BASE!$Q$3:$Q$453,BASE!$O$3:$O$453,Resumen!I$5,BASE!$B$3:$B$453,Resumen!$B51) -> 0 | J51: =SUMIFS(BASE!$Q$3:$Q$453,BASE!$O$3:$O$453,Resumen!J$5,BASE!$B$3:$B$453,Resumen!$B51) -> 0 | K51: =SUMIFS('Eventos B2B_MKT y Turnos DT'!$K$6:$K$456,'Eventos B2B_MKT y Turnos DT'!$D$6:$D$456,Resumen!$B51,'Eventos B2B_MKT y Turnos DT'!$G$6:$G$456,"B2B") -> 0 | L51: =SUMIFS('Eventos B2B_MKT y Turnos DT'!$K$6:$K$456,'Eventos B2B_MKT y Turnos DT'!$D$6:$D$456,Resumen!$B51,'Eventos B2B_MKT y Turnos DT'!$G$6:$G$456,"Hotel") -> 0 | M51: =SUMIFS('Eventos B2B_MKT y Turnos DT'!$K$6:$K$456,'Eventos B2B_MKT y Turnos DT'!$D$6:$D$456,Resumen!$B51,'Eventos B2B_MKT y Turnos DT'!$G$6:$G$456,"Marketing") -> 0 | N51: =SUMIF(Incidencias!$E$4:$E$89,$B51,Incidencias!$K$4:$K$89) -> 0 | O51: =SUM(D51:N51) -> 0 | P51: 331260 | R51: =IFERROR(Q51/O51,0) -> 0 | S51: =IFERROR(P51-Q51,"") -> 331260 | T51: =O51*(1-0.1525)-Q51 -> 0
B52: =Nómina!D49 -> 17325262-5 | C52: =Nómina!E49 -> MACARENA SOFIA GONZALEZ BORQUEZ | D52: =SUMIFS(BASE!$Q$3:$Q$453,BASE!$O$3:$O$453,Resumen!D$5,BASE!$B$3:$B$453,Resumen!$B52) -> 0 | E52: =SUMIFS(BASE!$Q$3:$Q$453,BASE!$O$3:$O$453,Resumen!E$5,BASE!$B$3:$B$453,Resumen!$B52) -> 0 | F52: =SUMIFS(BASE!$Q$3:$Q$453,BASE!$O$3:$O$453,Resumen!F$5,BASE!$B$3:$B$453,Resumen!$B52) -> 0 | G52: =SUMIFS(BASE!$Q$3:$Q$453,BASE!$O$3:$O$453,Resumen!G$5,BASE!$B$3:$B$453,Resumen!$B52) -> 0 | H52: =SUMIFS(BASE!$Q$3:$Q$453,BASE!$O$3:$O$453,Resumen!H$5,BASE!$B$3:$B$453,Resumen!$B52) -> 0 | I52: =SUMIFS(BASE!$Q$3:$Q$453,BASE!$O$3:$O$453,Resumen!I$5,BASE!$B$3:$B$453,Resumen!$B52) -> 0 | J52: =SUMIFS(BASE!$Q$3:$Q$453,BASE!$O$3:$O$453,Resumen!J$5,BASE!$B$3:$B$453,Resumen!$B52) -> 48563 | K52: =SUMIFS('Eventos B2B_MKT y Turnos DT'!$K$6:$K$456,'Eventos B2B_MKT y Turnos DT'!$D$6:$D$456,Resumen!$B52,'Eventos B2B_MKT y Turnos DT'!$G$6:$G$456,"B2B") -> 0 | L52: =SUMIFS('Eventos B2B_MKT y Turnos DT'!$K$6:$K$456,'Eventos B2B_MKT y Turnos DT'!$D$6:$D$456,Resumen!$B52,'Eventos B2B_MKT y Turnos DT'!$G$6:$G$456,"Hotel") -> 0 | M52: =SUMIFS('Eventos B2B_MKT y Turnos DT'!$K$6:$K$456,'Eventos B2B_MKT y Turnos DT'!$D$6:$D$456,Resumen!$B52,'Eventos B2B_MKT y Turnos DT'!$G$6:$G$456,"Marketing") -> 0 | N52: =SUMIF(Incidencias!$E$4:$E$89,$B52,Incidencias!$K$4:$K$89) -> 0 | O52: =SUM(D52:N52) -> 48563 | P52: 15000 | Q52: 15000 | R52: =IFERROR(Q52/O52,0) -> 0.30887713 | S52: =IFERROR(P52-Q52,"") -> 0 | T52: =O52*(1-0.1525)-Q52 -> 26157.143 | U52: =+IF(O52*(1-0.1525)-Q52=T52,"OK","REVISAR") -> OK
B53: =Nómina!D50 -> 17364919-3 | C53: =Nómina!E50 -> MARCELA MATAMALA | D53: =SUMIFS(BASE!$Q$3:$Q$453,BASE!$O$3:$O$453,Resumen!D$5,BASE!$B$3:$B$453,Resumen!$B53) -> 0 | E53: =SUMIFS(BASE!$Q$3:$Q$453,BASE!$O$3:$O$453,Resumen!E$5,BASE!$B$3:$B$453,Resumen!$B53) -> 0 | F53: =SUMIFS(BASE!$Q$3:$Q$453,BASE!$O$3:$O$453,Resumen!F$5,BASE!$B$3:$B$453,Resumen!$B53) -> 0 | G53: =SUMIFS(BASE!$Q$3:$Q$453,BASE!$O$3:$O$453,Resumen!G$5,BASE!$B$3:$B$453,Resumen!$B53) -> 0 | H53: =SUMIFS(BASE!$Q$3:$Q$453,BASE!$O$3:$O$453,Resumen!H$5,BASE!$B$3:$B$453,Resumen!$B53) -> 0 | I53: =SUMIFS(BASE!$Q$3:$Q$453,BASE!$O$3:$O$453,Resumen!I$5,BASE!$B$3:$B$453,Resumen!$B53) -> 0 | J53: =SUMIFS(BASE!$Q$3:$Q$453,BASE!$O$3:$O$453,Resumen!J$5,BASE!$B$3:$B$453,Resumen!$B53) -> 0 | K53: =SUMIFS('Eventos B2B_MKT y Turnos DT'!$K$6:$K$456,'Eventos B2B_MKT y Turnos DT'!$D$6:$D$456,Resumen!$B53,'Eventos B2B_MKT y Turnos DT'!$G$6:$G$456,"B2B") -> 0 | L53: =SUMIFS('Eventos B2B_MKT y Turnos DT'!$K$6:$K$456,'Eventos B2B_MKT y Turnos DT'!$D$6:$D$456,Resumen!$B53,'Eventos B2B_MKT y Turnos DT'!$G$6:$G$456,"Hotel") -> 0 | M53: =SUMIFS('Eventos B2B_MKT y Turnos DT'!$K$6:$K$456,'Eventos B2B_MKT y Turnos DT'!$D$6:$D$456,Resumen!$B53,'Eventos B2B_MKT y Turnos DT'!$G$6:$G$456,"Marketing") -> 0 | N53: =SUMIF(Incidencias!$E$4:$E$89,$B53,Incidencias!$K$4:$K$89) -> 0 | O53: =SUM(D53:N53) -> 0 | P53: 0 | R53: =IFERROR(Q53/O53,0) -> 0 | S53: =IFERROR(P53-Q53,"") -> 0 | T53: =O53*(1-0.1525)-Q53 -> 0 | U53: =+IF(O53*(1-0.1525)-Q53=T53,"OK","REVISAR") -> OK
B54: =Nómina!D51 -> 17003238-1 | C54: =Nómina!E51 -> MARCIA ANGELICA VILLEGAS BARRIOS | D54: =SUMIFS(BASE!$Q$3:$Q$453,BASE!$O$3:$O$453,Resumen!D$5,BASE!$B$3:$B$453,Resumen!$B54) -> 55462 | E54: =SUMIFS(BASE!$Q$3:$Q$453,BASE!$O$3:$O$453,Resumen!E$5,BASE!$B$3:$B$453,Resumen!$B54) -> 0 | F54: =SUMIFS(BASE!$Q$3:$Q$453,BASE!$O$3:$O$453,Resumen!F$5,BASE!$B$3:$B$453,Resumen!$B54) -> 0 | G54: =SUMIFS(BASE!$Q$3:$Q$453,BASE!$O$3:$O$453,Resumen!G$5,BASE!$B$3:$B$453,Resumen!$B54) -> 0 | H54: =SUMIFS(BASE!$Q$3:$Q$453,BASE!$O$3:$O$453,Resumen!H$5,BASE!$B$3:$B$453,Resumen!$B54) -> 0 | I54: =SUMIFS(BASE!$Q$3:$Q$453,BASE!$O$3:$O$453,Resumen!I$5,BASE!$B$3:$B$453,Resumen!$B54) -> 0 | J54: =SUMIFS(BASE!$Q$3:$Q$453,BASE!$O$3:$O$453,Resumen!J$5,BASE!$B$3:$B$453,Resumen!$B54) -> 0 | K54: =SUMIFS('Eventos B2B_MKT y Turnos DT'!$K$6:$K$456,'Eventos B2B_MKT y Turnos DT'!$D$6:$D$456,Resumen!$B54,'Eventos B2B_MKT y Turnos DT'!$G$6:$G$456,"B2B") -> 0 | L54: =SUMIFS('Eventos B2B_MKT y Turnos DT'!$K$6:$K$456,'Eventos B2B_MKT y Turnos DT'!$D$6:$D$456,Resumen!$B54,'Eventos B2B_MKT y Turnos DT'!$G$6:$G$456,"Hotel") -> 0 | M54: =SUMIFS('Eventos B2B_MKT y Turnos DT'!$K$6:$K$456,'Eventos B2B_MKT y Turnos DT'!$D$6:$D$456,Resumen!$B54,'Eventos B2B_MKT y Turnos DT'!$G$6:$G$456,"Marketing") -> 0 | N54: =SUMIF(Incidencias!$E$4:$E$89,$B54,Incidencias!$K$4:$K$89) -> 0 | O54: =SUM(D54:N54) -> 55462 | P54: 0 | Q54: =+IF(AND(P54<>0,P54>O54*0.2),O54*0.2,P54) -> 0 | R54: =IFERROR(Q54/O54,0) -> 0 | S54: =IFERROR(P54-Q54,"") -> 0 | T54: =O54*(1-0.1525)-Q54 -> 47004.045 | U54: =+IF(O54*(1-0.1525)-Q54=T54,"OK","REVISAR") -> OK
B55: =Nómina!D52 -> 15168787-3 | C55: =Nómina!E52 -> MARIA ELIANA BENAVIDES HIGUERA | D55: =SUMIFS(BASE!$Q$3:$Q$453,BASE!$O$3:$O$453,Resumen!D$5,BASE!$B$3:$B$453,Resumen!$B55) -> 78151 | E55: =SUMIFS(BASE!$Q$3:$Q$453,BASE!$O$3:$O$453,Resumen!E$5,BASE!$B$3:$B$453,Resumen!$B55) -> 0 | F55: =SUMIFS(BASE!$Q$3:$Q$453,BASE!$O$3:$O$453,Resumen!F$5,BASE!$B$3:$B$453,Resumen!$B55) -> 89243 | G55: =SUMIFS(BASE!$Q$3:$Q$453,BASE!$O$3:$O$453,Resumen!G$5,BASE!$B$3:$B$453,Resumen!$B55) -> 0 | H55: =SUMIFS(BASE!$Q$3:$Q$453,BASE!$O$3:$O$453,Resumen!H$5,BASE!$B$3:$B$453,Resumen!$B55) -> 0 | I55: =SUMIFS(BASE!$Q$3:$Q$453,BASE!$O$3:$O$453,Resumen!I$5,BASE!$B$3:$B$453,Resumen!$B55) -> 0 | J55: =SUMIFS(BASE!$Q$3:$Q$453,BASE!$O$3:$O$453,Resumen!J$5,BASE!$B$3:$B$453,Resumen!$B55) -> 0 | K55: =SUMIFS('Eventos B2B_MKT y Turnos DT'!$K$6:$K$456,'Eventos B2B_MKT y Turnos DT'!$D$6:$D$456,Resumen!$B55,'Eventos B2B_MKT y Turnos DT'!$G$6:$G$456,"B2B") -> 0 | L55: =SUMIFS('Eventos B2B_MKT y Turnos DT'!$K$6:$K$456,'Eventos B2B_MKT y Turnos DT'!$D$6:$D$456,Resumen!$B55,'Eventos B2B_MKT y Turnos DT'!$G$6:$G$456,"Hotel") -> 0 | M55: =SUMIFS('Eventos B2B_MKT y Turnos DT'!$K$6:$K$456,'Eventos B2B_MKT y Turnos DT'!$D$6:$D$456,Resumen!$B55,'Eventos B2B_MKT y Turnos DT'!$G$6:$G$456,"Marketing") -> 0 | N55: =SUMIF(Incidencias!$E$4:$E$89,$B55,Incidencias!$K$4:$K$89) -> 0 | O55: =SUM(D55:N55) -> 167394 | P55: 0 | Q55: =+IF(AND(P55<>0,P55>O55*0.2),O55*0.2,P55) -> 0 | R55: =IFERROR(Q55/O55,0) -> 0 | S55: =IFERROR(P55-Q55,"") -> 0 | T55: =O55*(1-0.1525)-Q55 -> 141866.42 | U55: =+IF(O55*(1-0.1525)-Q55=T55,"OK","REVISAR") -> OK
B56: =Nómina!D53 -> 18639536-0 | C56: =Nómina!E53 -> MARIA FRANCISCA FREUNDT GOMEZ | D56: =SUMIFS(BASE!$Q$3:$Q$453,BASE!$O$3:$O$453,Resumen!D$5,BASE!$B$3:$B$453,Resumen!$B56) -> 0 | E56: =SUMIFS(BASE!$Q$3:$Q$453,BASE!$O$3:$O$453,Resumen!E$5,BASE!$B$3:$B$453,Resumen!$B56) -> 0 | F56: =SUMIFS(BASE!$Q$3:$Q$453,BASE!$O$3:$O$453,Resumen!F$5,BASE!$B$3:$B$453,Resumen!$B56) -> 0 | G56: =SUMIFS(BASE!$Q$3:$Q$453,BASE!$O$3:$O$453,Resumen!G$5,BASE!$B$3:$B$453,Resumen!$B56) -> 0 | H56: =SUMIFS(BASE!$Q$3:$Q$453,BASE!$O$3:$O$453,Resumen!H$5,BASE!$B$3:$B$453,Resumen!$B56) -> 0 | I56: =SUMIFS(BASE!$Q$3:$Q$453,BASE!$O$3:$O$453,Resumen!I$5,BASE!$B$3:$B$453,Resumen!$B56) -> 0 | J56: =SUMIFS(BASE!$Q$3:$Q$453,BASE!$O$3:$O$453,Resumen!J$5,BASE!$B$3:$B$453,Resumen!$B56) -> 0 | K56: =SUMIFS('Eventos B2B_MKT y Turnos DT'!$K$6:$K$456,'Eventos B2B_MKT y Turnos DT'!$D$6:$D$456,Resumen!$B56,'Eventos B2B_MKT y Turnos DT'!$G$6:$G$456,"B2B") -> 0 | L56: =SUMIFS('Eventos B2B_MKT y Turnos DT'!$K$6:$K$456,'Eventos B2B_MKT y Turnos DT'!$D$6:$D$456,Resumen!$B56,'Eventos B2B_MKT y Turnos DT'!$G$6:$G$456,"Hotel") -> 0 | M56: =SUMIFS('Eventos B2B_MKT y Turnos DT'!$K$6:$K$456,'Eventos B2B_MKT y Turnos DT'!$D$6:$D$456,Resumen!$B56,'Eventos B2B_MKT y Turnos DT'!$G$6:$G$456,"Marketing") -> 0 | N56: =SUMIF(Incidencias!$E$4:$E$89,$B56,Incidencias!$K$4:$K$89) -> 0 | O56: =SUM(D56:N56) -> 0 | P56: 193999.57 | R56: =IFERROR(Q56/O56,0) -> 0 | S56: =IFERROR(P56-Q56,"") -> 193999.57 | T56: =O56*(1-0.1525)-Q56 -> 0 | U56: =+IF(O56*(1-0.1525)-Q56=T56,"OK","REVISAR") -> OK
B57: =Nómina!D54 -> 17416146-1 | C57: =Nómina!E54 -> MARIA JOSE BUSTOS PINCHULEF | D57: =SUMIFS(BASE!$Q$3:$Q$453,BASE!$O$3:$O$453,Resumen!D$5,BASE!$B$3:$B$453,Resumen!$B57) -> 0 | E57: =SUMIFS(BASE!$Q$3:$Q$453,BASE!$O$3:$O$453,Resumen!E$5,BASE!$B$3:$B$453,Resumen!$B57) -> 0 | F57: =SUMIFS(BASE!$Q$3:$Q$453,BASE!$O$3:$O$453,Resumen!F$5,BASE!$B$3:$B$453,Resumen!$B57) -> 0 | G57: =SUMIFS(BASE!$Q$3:$Q$453,BASE!$O$3:$O$453,Resumen!G$5,BASE!$B$3:$B$453,Resumen!$B57) -> 0 | H57: =SUMIFS(BASE!$Q$3:$Q$453,BASE!$O$3:$O$453,Resumen!H$5,BASE!$B$3:$B$453,Resumen!$B57) -> 0 | I57: =SUMIFS(BASE!$Q$3:$Q$453,BASE!$O$3:$O$453,Resumen!I$5,BASE!$B$3:$B$453,Resumen!$B57) -> 0 | J57: =SUMIFS(BASE!$Q$3:$Q$453,BASE!$O$3:$O$453,Resumen!J$5,BASE!$B$3:$B$453,Resumen!$B57) -> 0 | K57: =SUMIFS('Eventos B2B_MKT y Turnos DT'!$K$6:$K$456,'Eventos B2B_MKT y Turnos DT'!$D$6:$D$456,Resumen!$B57,'Eventos B2B_MKT y Turnos DT'!$G$6:$G$456,"B2B") -> 0 | L57: =SUMIFS('Eventos B2B_MKT y Turnos DT'!$K$6:$K$456,'Eventos B2B_MKT y Turnos DT'!$D$6:$D$456,Resumen!$B57,'Eventos B2B_MKT y Turnos DT'!$G$6:$G$456,"Hotel") -> 0 | M57: =SUMIFS('Eventos B2B_MKT y Turnos DT'!$K$6:$K$456,'Eventos B2B_MKT y Turnos DT'!$D$6:$D$456,Resumen!$B57,'Eventos B2B_MKT y Turnos DT'!$G$6:$G$456,"Marketing") -> 0 | N57: =SUMIF(Incidencias!$E$4:$E$89,$B57,Incidencias!$K$4:$K$89) -> 15000 | O57: =SUM(D57:N57) -> 15000 | P57: 111000 | Q57: 11000 | R57: =IFERROR(Q57/O57,0) -> 0.73333333 | S57: =IFERROR(P57-Q57,"") -> 100000 | T57: =O57*(1-0.1525)-Q57 -> 1712.5 | U57: =+IF(O57*(1-0.1525)-Q57=T57,"OK","REVISAR") -> OK
B58: =Nómina!D55 -> 13335240-6 | C58: =Nómina!E55 -> MARIA MAGDALENA CASTRO MORGADO | D58: =SUMIFS(BASE!$Q$3:$Q$453,BASE!$O$3:$O$453,Resumen!D$5,BASE!$B$3:$B$453,Resumen!$B58) -> 144429 | E58: =SUMIFS(BASE!$Q$3:$Q$453,BASE!$O$3:$O$453,Resumen!E$5,BASE!$B$3:$B$453,Resumen!$B58) -> 0 | F58: =SUMIFS(BASE!$Q$3:$Q$453,BASE!$O$3:$O$453,Resumen!F$5,BASE!$B$3:$B$453,Resumen!$B58) -> 22689 | G58: =SUMIFS(BASE!$Q$3:$Q$453,BASE!$O$3:$O$453,Resumen!G$5,BASE!$B$3:$B$453,Resumen!$B58) -> 0 | H58: =SUMIFS(BASE!$Q$3:$Q$453,BASE!$O$3:$O$453,Resumen!H$5,BASE!$B$3:$B$453,Resumen!$B58) -> 0 | I58: =SUMIFS(BASE!$Q$3:$Q$453,BASE!$O$3:$O$453,Resumen!I$5,BASE!$B$3:$B$453,Resumen!$B58) -> 0 | J58: =SUMIFS(BASE!$Q$3:$Q$453,BASE!$O$3:$O$453,Resumen!J$5,BASE!$B$3:$B$453,Resumen!$B58) -> 0 | K58: =SUMIFS('Eventos B2B_MKT y Turnos DT'!$K$6:$K$456,'Eventos B2B_MKT y Turnos DT'!$D$6:$D$456,Resumen!$B58,'Eventos B2B_MKT y Turnos DT'!$G$6:$G$456,"B2B") -> 0 | L58: =SUMIFS('Eventos B2B_MKT y Turnos DT'!$K$6:$K$456,'Eventos B2B_MKT y Turnos DT'!$D$6:$D$456,Resumen!$B58,'Eventos B2B_MKT y Turnos DT'!$G$6:$G$456,"Hotel") -> 0 | M58: =SUMIFS('Eventos B2B_MKT y Turnos DT'!$K$6:$K$456,'Eventos B2B_MKT y Turnos DT'!$D$6:$D$456,Resumen!$B58,'Eventos B2B_MKT y Turnos DT'!$G$6:$G$456,"Marketing") -> 0 | N58: =SUMIF(Incidencias!$E$4:$E$89,$B58,Incidencias!$K$4:$K$89) -> 0 | O58: =SUM(D58:N58) -> 167118 | P58: 0 | Q58: =+IF(AND(P58<>0,P58>O58*0.2),O58*0.2,P58) -> 0 | R58: =IFERROR(Q58/O58,0) -> 0 | S58: =IFERROR(P58-Q58,"") -> 0 | T58: =O58*(1-0.1525)-Q58 -> 141632.51 | U58: =+IF(O58*(1-0.1525)-Q58=T58,"OK","REVISAR") -> OK
B59: =Nómina!D56 -> 22038238-9 | C59: =Nómina!E56 -> MARIELA MITA GALLEGUILLOS | D59: =SUMIFS(BASE!$Q$3:$Q$453,BASE!$O$3:$O$453,Resumen!D$5,BASE!$B$3:$B$453,Resumen!$B59) -> 0 | E59: =SUMIFS(BASE!$Q$3:$Q$453,BASE!$O$3:$O$453,Resumen!E$5,BASE!$B$3:$B$453,Resumen!$B59) -> 0 | F59: =SUMIFS(BASE!$Q$3:$Q$453,BASE!$O$3:$O$453,Resumen!F$5,BASE!$B$3:$B$453,Resumen!$B59) -> 0 | G59: =SUMIFS(BASE!$Q$3:$Q$453,BASE!$O$3:$O$453,Resumen!G$5,BASE!$B$3:$B$453,Resumen!$B59) -> 0 | H59: =SUMIFS(BASE!$Q$3:$Q$453,BASE!$O$3:$O$453,Resumen!H$5,BASE!$B$3:$B$453,Resumen!$B59) -> 0 | I59: =SUMIFS(BASE!$Q$3:$Q$453,BASE!$O$3:$O$453,Resumen!I$5,BASE!$B$3:$B$453,Resumen!$B59) -> 0 | J59: =SUMIFS(BASE!$Q$3:$Q$453,BASE!$O$3:$O$453,Resumen!J$5,BASE!$B$3:$B$453,Resumen!$B59) -> 0 | K59: =SUMIFS('Eventos B2B_MKT y Turnos DT'!$K$6:$K$456,'Eventos B2B_MKT y Turnos DT'!$D$6:$D$456,Resumen!$B59,'Eventos B2B_MKT y Turnos DT'!$G$6:$G$456,"B2B") -> 0 | L59: =SUMIFS('Eventos B2B_MKT y Turnos DT'!$K$6:$K$456,'Eventos B2B_MKT y Turnos DT'!$D$6:$D$456,Resumen!$B59,'Eventos B2B_MKT y Turnos DT'!$G$6:$G$456,"Hotel") -> 0 | M59: =SUMIFS('Eventos B2B_MKT y Turnos DT'!$K$6:$K$456,'Eventos B2B_MKT y Turnos DT'!$D$6:$D$456,Resumen!$B59,'Eventos B2B_MKT y Turnos DT'!$G$6:$G$456,"Marketing") -> 0 | N59: =SUMIF(Incidencias!$E$4:$E$89,$B59,Incidencias!$K$4:$K$89) -> 0 | O59: =SUM(D59:N59) -> 0 | P59: 128400 | Q59: 14868.54 | R59: =IFERROR(Q59/O59,0) -> 0 | S59: =IFERROR(P59-Q59,"") -> 113531.46 | T59: =O59*(1-0.1525)-Q59 -> -14868.54 | U59: =+IF(O59*(1-0.1525)-Q59=T59,"OK","REVISAR") -> OK
B60: =Nómina!D57 -> 19027666-K | C60: =Nómina!E57 -> MARTA SANHUEZA | D60: =SUMIFS(BASE!$Q$3:$Q$453,BASE!$O$3:$O$453,Resumen!D$5,BASE!$B$3:$B$453,Resumen!$B60) -> 0 | E60: =SUMIFS(BASE!$Q$3:$Q$453,BASE!$O$3:$O$453,Resumen!E$5,BASE!$B$3:$B$453,Resumen!$B60) -> 0 | F60: =SUMIFS(BASE!$Q$3:$Q$453,BASE!$O$3:$O$453,Resumen!F$5,BASE!$B$3:$B$453,Resumen!$B60) -> 0 | G60: =SUMIFS(BASE!$Q$3:$Q$453,BASE!$O$3:$O$453,Resumen!G$5,BASE!$B$3:$B$453,Resumen!$B60) -> 0 | H60: =SUMIFS(BASE!$Q$3:$Q$453,BASE!$O$3:$O$453,Resumen!H$5,BASE!$B$3:$B$453,Resumen!$B60) -> 0 | I60: =SUMIFS(BASE!$Q$3:$Q$453,BASE!$O$3:$O$453,Resumen!I$5,BASE!$B$3:$B$453,Resumen!$B60) -> 0 | J60: =SUMIFS(BASE!$Q$3:$Q$453,BASE!$O$3:$O$453,Resumen!J$5,BASE!$B$3:$B$453,Resumen!$B60) -> 0 | K60: =SUMIFS('Eventos B2B_MKT y Turnos DT'!$K$6:$K$456,'Eventos B2B_MKT y Turnos DT'!$D$6:$D$456,Resumen!$B60,'Eventos B2B_MKT y Turnos DT'!$G$6:$G$456,"B2B") -> 0 | L60: =SUMIFS('Eventos B2B_MKT y Turnos DT'!$K$6:$K$456,'Eventos B2B_MKT y Turnos DT'!$D$6:$D$456,Resumen!$B60,'Eventos B2B_MKT y Turnos DT'!$G$6:$G$456,"Hotel") -> 0 | M60: =SUMIFS('Eventos B2B_MKT y Turnos DT'!$K$6:$K$456,'Eventos B2B_MKT y Turnos DT'!$D$6:$D$456,Resumen!$B60,'Eventos B2B_MKT y Turnos DT'!$G$6:$G$456,"Marketing") -> 0 | N60: =SUMIF(Incidencias!$E$4:$E$89,$B60,Incidencias!$K$4:$K$89) -> 0 | O60: =SUM(D60:N60) -> 0 | P60: 0 | R60: =IFERROR(Q60/O60,0) -> 0 | S60: =IFERROR(P60-Q60,"") -> 0 | T60: =O60*(1-0.1525)-Q60 -> 0
B61: =Nómina!D58 -> 20095435-1 | C61: =Nómina!E58 -> MARTIN ALONSO QUINTEROS HENRIQUEZ | D61: =SUMIFS(BASE!$Q$3:$Q$453,BASE!$O$3:$O$453,Resumen!D$5,BASE!$B$3:$B$453,Resumen!$B61) -> 0 | E61: =SUMIFS(BASE!$Q$3:$Q$453,BASE!$O$3:$O$453,Resumen!E$5,BASE!$B$3:$B$453,Resumen!$B61) -> 0 | F61: =SUMIFS(BASE!$Q$3:$Q$453,BASE!$O$3:$O$453,Resumen!F$5,BASE!$B$3:$B$453,Resumen!$B61) -> 0 | G61: =SUMIFS(BASE!$Q$3:$Q$453,BASE!$O$3:$O$453,Resumen!G$5,BASE!$B$3:$B$453,Resumen!$B61) -> 0 | H61: =SUMIFS(BASE!$Q$3:$Q$453,BASE!$O$3:$O$453,Resumen!H$5,BASE!$B$3:$B$453,Resumen!$B61) -> 0 | I61: =SUMIFS(BASE!$Q$3:$Q$453,BASE!$O$3:$O$453,Resumen!I$5,BASE!$B$3:$B$453,Resumen!$B61) -> 0 | J61: =SUMIFS(BASE!$Q$3:$Q$453,BASE!$O$3:$O$453,Resumen!J$5,BASE!$B$3:$B$453,Resumen!$B61) -> 0 | K61: =SUMIFS('Eventos B2B_MKT y Turnos DT'!$K$6:$K$456,'Eventos B2B_MKT y Turnos DT'!$D$6:$D$456,Resumen!$B61,'Eventos B2B_MKT y Turnos DT'!$G$6:$G$456,"B2B") -> 0 | L61: =SUMIFS('Eventos B2B_MKT y Turnos DT'!$K$6:$K$456,'Eventos B2B_MKT y Turnos DT'!$D$6:$D$456,Resumen!$B61,'Eventos B2B_MKT y Turnos DT'!$G$6:$G$456,"Hotel") -> 0 | M61: =SUMIFS('Eventos B2B_MKT y Turnos DT'!$K$6:$K$456,'Eventos B2B_MKT y Turnos DT'!$D$6:$D$456,Resumen!$B61,'Eventos B2B_MKT y Turnos DT'!$G$6:$G$456,"Marketing") -> 0 | N61: =SUMIF(Incidencias!$E$4:$E$89,$B61,Incidencias!$K$4:$K$89) -> 0 | O61: =SUM(D61:N61) -> 0 | P61: 212631.46 | Q61: 21500 | R61: =IFERROR(Q61/O61,0) -> 0 | S61: =IFERROR(P61-Q61,"") -> 191131.46 | T61: =O61*(1-0.1525)-Q61 -> -21500 | U61: =+IF(O61*(1-0.1525)-Q61=T61,"OK","REVISAR") -> OK
B62: =Nómina!D59 -> 9271701-1 | C62: =Nómina!E59 -> MAURICIO SANTIAGO CABRERA MALDONADO | D62: =SUMIFS(BASE!$Q$3:$Q$453,BASE!$O$3:$O$453,Resumen!D$5,BASE!$B$3:$B$453,Resumen!$B62) -> 0 | E62: =SUMIFS(BASE!$Q$3:$Q$453,BASE!$O$3:$O$453,Resumen!E$5,BASE!$B$3:$B$453,Resumen!$B62) -> 0 | F62: =SUMIFS(BASE!$Q$3:$Q$453,BASE!$O$3:$O$453,Resumen!F$5,BASE!$B$3:$B$453,Resumen!$B62) -> 0 | G62: =SUMIFS(BASE!$Q$3:$Q$453,BASE!$O$3:$O$453,Resumen!G$5,BASE!$B$3:$B$453,Resumen!$B62) -> 0 | H62: =SUMIFS(BASE!$Q$3:$Q$453,BASE!$O$3:$O$453,Resumen!H$5,BASE!$B$3:$B$453,Resumen!$B62) -> 0 | I62: =SUMIFS(BASE!$Q$3:$Q$453,BASE!$O$3:$O$453,Resumen!I$5,BASE!$B$3:$B$453,Resumen!$B62) -> 0 | J62: =SUMIFS(BASE!$Q$3:$Q$453,BASE!$O$3:$O$453,Resumen!J$5,BASE!$B$3:$B$453,Resumen!$B62) -> 0 | K62: =SUMIFS('Eventos B2B_MKT y Turnos DT'!$K$6:$K$456,'Eventos B2B_MKT y Turnos DT'!$D$6:$D$456,Resumen!$B62,'Eventos B2B_MKT y Turnos DT'!$G$6:$G$456,"B2B") -> 0 | L62: =SUMIFS('Eventos B2B_MKT y Turnos DT'!$K$6:$K$456,'Eventos B2B_MKT y Turnos DT'!$D$6:$D$456,Resumen!$B62,'Eventos B2B_MKT y Turnos DT'!$G$6:$G$456,"Hotel") -> 0 | M62: =SUMIFS('Eventos B2B_MKT y Turnos DT'!$K$6:$K$456,'Eventos B2B_MKT y Turnos DT'!$D$6:$D$456,Resumen!$B62,'Eventos B2B_MKT y Turnos DT'!$G$6:$G$456,"Marketing") -> 0 | N62: =SUMIF(Incidencias!$E$4:$E$89,$B62,Incidencias!$K$4:$K$89) -> 0 | O62: =SUM(D62:N62) -> 0 | P62: 45000 | R62: =IFERROR(Q62/O62,0) -> 0 | S62: =IFERROR(P62-Q62,"") -> 45000 | T62: =O62*(1-0.1525)-Q62 -> 0
B63: =Nómina!D60 -> 25541617-0 | C63: =Nómina!E60 -> NANCY TIEMPO LEONGAS | D63: =SUMIFS(BASE!$Q$3:$Q$453,BASE!$O$3:$O$453,Resumen!D$5,BASE!$B$3:$B$453,Resumen!$B63) -> 0 | E63: =SUMIFS(BASE!$Q$3:$Q$453,BASE!$O$3:$O$453,Resumen!E$5,BASE!$B$3:$B$453,Resumen!$B63) -> 0 | F63: =SUMIFS(BASE!$Q$3:$Q$453,BASE!$O$3:$O$453,Resumen!F$5,BASE!$B$3:$B$453,Resumen!$B63) -> 0 | G63: =SUMIFS(BASE!$Q$3:$Q$453,BASE!$O$3:$O$453,Resumen!G$5,BASE!$B$3:$B$453,Resumen!$B63) -> 0 | H63: =SUMIFS(BASE!$Q$3:$Q$453,BASE!$O$3:$O$453,Resumen!H$5,BASE!$B$3:$B$453,Resumen!$B63) -> 0 | I63: =SUMIFS(BASE!$Q$3:$Q$453,BASE!$O$3:$O$453,Resumen!I$5,BASE!$B$3:$B$453,Resumen!$B63) -> 0 | J63: =SUMIFS(BASE!$Q$3:$Q$453,BASE!$O$3:$O$453,Resumen!J$5,BASE!$B$3:$B$453,Resumen!$B63) -> 0 | K63: =SUMIFS('Eventos B2B_MKT y Turnos DT'!$K$6:$K$456,'Eventos B2B_MKT y Turnos DT'!$D$6:$D$456,Resumen!$B63,'Eventos B2B_MKT y Turnos DT'!$G$6:$G$456,"B2B") -> 0 | L63: =SUMIFS('Eventos B2B_MKT y Turnos DT'!$K$6:$K$456,'Eventos B2B_MKT y Turnos DT'!$D$6:$D$456,Resumen!$B63,'Eventos B2B_MKT y Turnos DT'!$G$6:$G$456,"Hotel") -> 0 | M63: =SUMIFS('Eventos B2B_MKT y Turnos DT'!$K$6:$K$456,'Eventos B2B_MKT y Turnos DT'!$D$6:$D$456,Resumen!$B63,'Eventos B2B_MKT y Turnos DT'!$G$6:$G$456,"Marketing") -> 0 | N63: =SUMIF(Incidencias!$E$4:$E$89,$B63,Incidencias!$K$4:$K$89) -> 0 | O63: =SUM(D63:N63) -> 0 | P63: 0 | Q63: =+IF(AND(P63<>0,P63>O63*0.2),O63*0.2,P63) -> 0 | R63: =IFERROR(Q63/O63,0) -> 0 | S63: =IFERROR(P63-Q63,"") -> 0 | T63: =O63*(1-0.1525)-Q63 -> 0 | U63: =+IF(O63*(1-0.1525)-Q63=T63,"OK","REVISAR") -> OK
B64: =Nómina!D61 -> 26510057-0 | C64: =Nómina!E61 -> NASTACHA ADELHEI VILLAMIZAR GU | D64: =SUMIFS(BASE!$Q$3:$Q$453,BASE!$O$3:$O$453,Resumen!D$5,BASE!$B$3:$B$453,Resumen!$B64) -> 0 | E64: =SUMIFS(BASE!$Q$3:$Q$453,BASE!$O$3:$O$453,Resumen!E$5,BASE!$B$3:$B$453,Resumen!$B64) -> 0 | F64: =SUMIFS(BASE!$Q$3:$Q$453,BASE!$O$3:$O$453,Resumen!F$5,BASE!$B$3:$B$453,Resumen!$B64) -> 0 | G64: =SUMIFS(BASE!$Q$3:$Q$453,BASE!$O$3:$O$453,Resumen!G$5,BASE!$B$3:$B$453,Resumen!$B64) -> 0 | H64: =SUMIFS(BASE!$Q$3:$Q$453,BASE!$O$3:$O$453,Resumen!H$5,BASE!$B$3:$B$453,Resumen!$B64) -> 0 | I64: =SUMIFS(BASE!$Q$3:$Q$453,BASE!$O$3:$O$453,Resumen!I$5,BASE!$B$3:$B$453,Resumen!$B64) -> 0 | J64: =SUMIFS(BASE!$Q$3:$Q$453,BASE!$O$3:$O$453,Resumen!J$5,BASE!$B$3:$B$453,Resumen!$B64) -> 0 | K64: =SUMIFS('Eventos B2B_MKT y Turnos DT'!$K$6:$K$456,'Eventos B2B_MKT y Turnos DT'!$D$6:$D$456,Resumen!$B64,'Eventos B2B_MKT y Turnos DT'!$G$6:$G$456,"B2B") -> 0 | L64: =SUMIFS('Eventos B2B_MKT y Turnos DT'!$K$6:$K$456,'Eventos B2B_MKT y Turnos DT'!$D$6:$D$456,Resumen!$B64,'Eventos B2B_MKT y Turnos DT'!$G$6:$G$456,"Hotel") -> 0 | M64: =SUMIFS('Eventos B2B_MKT y Turnos DT'!$K$6:$K$456,'Eventos B2B_MKT y Turnos DT'!$D$6:$D$456,Resumen!$B64,'Eventos B2B_MKT y Turnos DT'!$G$6:$G$456,"Marketing") -> 0 | N64: =SUMIF(Incidencias!$E$4:$E$89,$B64,Incidencias!$K$4:$K$89) -> 0 | O64: =SUM(D64:N64) -> 0 | P64: 0 | R64: =IFERROR(Q64/O64,0) -> 0 | S64: =IFERROR(P64-Q64,"") -> 0 | T64: =O64*(1-0.1525)-Q64 -> 0
B65: =Nómina!D62 -> 12051775-9 | C65: =Nómina!E62 -> NATALIA OLMEDO | D65: =SUMIFS(BASE!$Q$3:$Q$453,BASE!$O$3:$O$453,Resumen!D$5,BASE!$B$3:$B$453,Resumen!$B65) -> 0 | E65: =SUMIFS(BASE!$Q$3:$Q$453,BASE!$O$3:$O$453,Resumen!E$5,BASE!$B$3:$B$453,Resumen!$B65) -> 0 | F65: =SUMIFS(BASE!$Q$3:$Q$453,BASE!$O$3:$O$453,Resumen!F$5,BASE!$B$3:$B$453,Resumen!$B65) -> 0 | G65: =SUMIFS(BASE!$Q$3:$Q$453,BASE!$O$3:$O$453,Resumen!G$5,BASE!$B$3:$B$453,Resumen!$B65) -> 0 | H65: =SUMIFS(BASE!$Q$3:$Q$453,BASE!$O$3:$O$453,Resumen!H$5,BASE!$B$3:$B$453,Resumen!$B65) -> 0 | I65: =SUMIFS(BASE!$Q$3:$Q$453,BASE!$O$3:$O$453,Resumen!I$5,BASE!$B$3:$B$453,Resumen!$B65) -> 0 | J65: =SUMIFS(BASE!$Q$3:$Q$453,BASE!$O$3:$O$453,Resumen!J$5,BASE!$B$3:$B$453,Resumen!$B65) -> 0 | K65: =SUMIFS('Eventos B2B_MKT y Turnos DT'!$K$6:$K$456,'Eventos B2B_MKT y Turnos DT'!$D$6:$D$456,Resumen!$B65,'Eventos B2B_MKT y Turnos DT'!$G$6:$G$456,"B2B") -> 0 | L65: =SUMIFS('Eventos B2B_MKT y Turnos DT'!$K$6:$K$456,'Eventos B2B_MKT y Turnos DT'!$D$6:$D$456,Resumen!$B65,'Eventos B2B_MKT y Turnos DT'!$G$6:$G$456,"Hotel") -> 0 | M65: =SUMIFS('Eventos B2B_MKT y Turnos DT'!$K$6:$K$456,'Eventos B2B_MKT y Turnos DT'!$D$6:$D$456,Resumen!$B65,'Eventos B2B_MKT y Turnos DT'!$G$6:$G$456,"Marketing") -> 0 | N65: =SUMIF(Incidencias!$E$4:$E$89,$B65,Incidencias!$K$4:$K$89) -> 0 | O65: =SUM(D65:N65) -> 0 | P65: 68500 | R65: =IFERROR(Q65/O65,0) -> 0 | S65: =IFERROR(P65-Q65,"") -> 68500 | T65: =O65*(1-0.1525)-Q65 -> 0
B66: =Nómina!D63 -> 16371373-K | C66: =Nómina!E63 -> NATALIA VALERIA CRUZ ESCARATE | D66: =SUMIFS(BASE!$Q$3:$Q$453,BASE!$O$3:$O$453,Resumen!D$5,BASE!$B$3:$B$453,Resumen!$B66) -> 0 | E66: =SUMIFS(BASE!$Q$3:$Q$453,BASE!$O$3:$O$453,Resumen!E$5,BASE!$B$3:$B$453,Resumen!$B66) -> 0 | F66: =SUMIFS(BASE!$Q$3:$Q$453,BASE!$O$3:$O$453,Resumen!F$5,BASE!$B$3:$B$453,Resumen!$B66) -> 0 | G66: =SUMIFS(BASE!$Q$3:$Q$453,BASE!$O$3:$O$453,Resumen!G$5,BASE!$B$3:$B$453,Resumen!$B66) -> 0 | H66: =SUMIFS(BASE!$Q$3:$Q$453,BASE!$O$3:$O$453,Resumen!H$5,BASE!$B$3:$B$453,Resumen!$B66) -> 0 | I66: =SUMIFS(BASE!$Q$3:$Q$453,BASE!$O$3:$O$453,Resumen!I$5,BASE!$B$3:$B$453,Resumen!$B66) -> 0 | J66: =SUMIFS(BASE!$Q$3:$Q$453,BASE!$O$3:$O$453,Resumen!J$5,BASE!$B$3:$B$453,Resumen!$B66) -> 0 | K66: =SUMIFS('Eventos B2B_MKT y Turnos DT'!$K$6:$K$456,'Eventos B2B_MKT y Turnos DT'!$D$6:$D$456,Resumen!$B66,'Eventos B2B_MKT y Turnos DT'!$G$6:$G$456,"B2B") -> 0 | L66: =SUMIFS('Eventos B2B_MKT y Turnos DT'!$K$6:$K$456,'Eventos B2B_MKT y Turnos DT'!$D$6:$D$456,Resumen!$B66,'Eventos B2B_MKT y Turnos DT'!$G$6:$G$456,"Hotel") -> 0 | M66: =SUMIFS('Eventos B2B_MKT y Turnos DT'!$K$6:$K$456,'Eventos B2B_MKT y Turnos DT'!$D$6:$D$456,Resumen!$B66,'Eventos B2B_MKT y Turnos DT'!$G$6:$G$456,"Marketing") -> 0 | N66: =SUMIF(Incidencias!$E$4:$E$89,$B66,Incidencias!$K$4:$K$89) -> 0 | O66: =SUM(D66:N66) -> 0 | P66: 2000 | R66: =IFERROR(Q66/O66,0) -> 0 | S66: =IFERROR(P66-Q66,"") -> 2000 | T66: =O66*(1-0.1525)-Q66 -> 0 | U66: =+IF(O66*(1-0.1525)-Q66=T66,"OK","REVISAR") -> OK
B67: =Nómina!D64 -> 16265769-0 | C67: =Nómina!E64 -> NATHALY MARIANELA VALENZUELA ORELLANA | D67: =SUMIFS(BASE!$Q$3:$Q$453,BASE!$O$3:$O$453,Resumen!D$5,BASE!$B$3:$B$453,Resumen!$B67) -> 0 | E67: =SUMIFS(BASE!$Q$3:$Q$453,BASE!$O$3:$O$453,Resumen!E$5,BASE!$B$3:$B$453,Resumen!$B67) -> 0 | F67: =SUMIFS(BASE!$Q$3:$Q$453,BASE!$O$3:$O$453,Resumen!F$5,BASE!$B$3:$B$453,Resumen!$B67) -> 0 | G67: =SUMIFS(BASE!$Q$3:$Q$453,BASE!$O$3:$O$453,Resumen!G$5,BASE!$B$3:$B$453,Resumen!$B67) -> 0 | H67: =SUMIFS(BASE!$Q$3:$Q$453,BASE!$O$3:$O$453,Resumen!H$5,BASE!$B$3:$B$453,Resumen!$B67) -> 0 | I67: =SUMIFS(BASE!$Q$3:$Q$453,BASE!$O$3:$O$453,Resumen!I$5,BASE!$B$3:$B$453,Resumen!$B67) -> 0 | J67: =SUMIFS(BASE!$Q$3:$Q$453,BASE!$O$3:$O$453,Resumen!J$5,BASE!$B$3:$B$453,Resumen!$B67) -> 0 | K67: =SUMIFS('Eventos B2B_MKT y Turnos DT'!$K$6:$K$456,'Eventos B2B_MKT y Turnos DT'!$D$6:$D$456,Resumen!$B67,'Eventos B2B_MKT y Turnos DT'!$G$6:$G$456,"B2B") -> 0 | L67: =SUMIFS('Eventos B2B_MKT y Turnos DT'!$K$6:$K$456,'Eventos B2B_MKT y Turnos DT'!$D$6:$D$456,Resumen!$B67,'Eventos B2B_MKT y Turnos DT'!$G$6:$G$456,"Hotel") -> 0 | M67: =SUMIFS('Eventos B2B_MKT y Turnos DT'!$K$6:$K$456,'Eventos B2B_MKT y Turnos DT'!$D$6:$D$456,Resumen!$B67,'Eventos B2B_MKT y Turnos DT'!$G$6:$G$456,"Marketing") -> 0 | N67: =SUMIF(Incidencias!$E$4:$E$89,$B67,Incidencias!$K$4:$K$89) -> 0 | O67: =SUM(D67:N67) -> 0 | P67: 24000 | R67: =IFERROR(Q67/O67,0) -> 0 | S67: =IFERROR(P67-Q67,"") -> 24000 | T67: =O67*(1-0.1525)-Q67 -> 0 | U67: =+IF(O67*(1-0.1525)-Q67=T67,"OK","REVISAR") -> OK
B68: =Nómina!D65 -> 18881513-8 | C68: =Nómina!E65 -> PAMELA CONSTANZA HUILITRARO QUEZADA | D68: =SUMIFS(BASE!$Q$3:$Q$453,BASE!$O$3:$O$453,Resumen!D$5,BASE!$B$3:$B$453,Resumen!$B68) -> 67059 | E68: =SUMIFS(BASE!$Q$3:$Q$453,BASE!$O$3:$O$453,Resumen!E$5,BASE!$B$3:$B$453,Resumen!$B68) -> 0 | F68: =SUMIFS(BASE!$Q$3:$Q$453,BASE!$O$3:$O$453,Resumen!F$5,BASE!$B$3:$B$453,Resumen!$B68) -> 146723 | G68: =SUMIFS(BASE!$Q$3:$Q$453,BASE!$O$3:$O$453,Resumen!G$5,BASE!$B$3:$B$453,Resumen!$B68) -> 0 | H68: =SUMIFS(BASE!$Q$3:$Q$453,BASE!$O$3:$O$453,Resumen!H$5,BASE!$B$3:$B$453,Resumen!$B68) -> 0 | I68: =SUMIFS(BASE!$Q$3:$Q$453,BASE!$O$3:$O$453,Resumen!I$5,BASE!$B$3:$B$453,Resumen!$B68) -> 22689 | J68: =SUMIFS(BASE!$Q$3:$Q$453,BASE!$O$3:$O$453,Resumen!J$5,BASE!$B$3:$B$453,Resumen!$B68) -> 0 | K68: =SUMIFS('Eventos B2B_MKT y Turnos DT'!$K$6:$K$456,'Eventos B2B_MKT y Turnos DT'!$D$6:$D$456,Resumen!$B68,'Eventos B2B_MKT y Turnos DT'!$G$6:$G$456,"B2B") -> 0 | L68: =SUMIFS('Eventos B2B_MKT y Turnos DT'!$K$6:$K$456,'Eventos B2B_MKT y Turnos DT'!$D$6:$D$456,Resumen!$B68,'Eventos B2B_MKT y Turnos DT'!$G$6:$G$456,"Hotel") -> 0 | M68: =SUMIFS('Eventos B2B_MKT y Turnos DT'!$K$6:$K$456,'Eventos B2B_MKT y Turnos DT'!$D$6:$D$456,Resumen!$B68,'Eventos B2B_MKT y Turnos DT'!$G$6:$G$456,"Marketing") -> 0 | N68: =SUMIF(Incidencias!$E$4:$E$89,$B68,Incidencias!$K$4:$K$89) -> 0 | O68: =SUM(D68:N68) -> 236471 | P68: 5.8207661e-11 | Q68: =+IF(AND(P68<>0,P68>O68*0.2),O68*0.2,P68) -> 5.8207661e-11 | R68: =IFERROR(Q68/O68,0) -> 2.4615137e-16 | S68: =IFERROR(P68-Q68,"") -> 0 | T68: =O68*(1-0.1525)-Q68 -> 200409.17 | U68: =+IF(O68*(1-0.1525)-Q68=T68,"OK","REVISAR") -> OK
B69: =Nómina!D66 -> 8008360-2 | C69: =Nómina!E66 -> PAMELA VERONICA CID NAVIA | D69: =SUMIFS(BASE!$Q$3:$Q$453,BASE!$O$3:$O$453,Resumen!D$5,BASE!$B$3:$B$453,Resumen!$B69) -> 440487 | E69: =SUMIFS(BASE!$Q$3:$Q$453,BASE!$O$3:$O$453,Resumen!E$5,BASE!$B$3:$B$453,Resumen!$B69) -> 22689 | F69: =SUMIFS(BASE!$Q$3:$Q$453,BASE!$O$3:$O$453,Resumen!F$5,BASE!$B$3:$B$453,Resumen!$B69) -> 68067 | G69: =SUMIFS(BASE!$Q$3:$Q$453,BASE!$O$3:$O$453,Resumen!G$5,BASE!$B$3:$B$453,Resumen!$B69) -> 0 | H69: =SUMIFS(BASE!$Q$3:$Q$453,BASE!$O$3:$O$453,Resumen!H$5,BASE!$B$3:$B$453,Resumen!$B69) -> 0 | I69: =SUMIFS(BASE!$Q$3:$Q$453,BASE!$O$3:$O$453,Resumen!I$5,BASE!$B$3:$B$453,Resumen!$B69) -> 0 | J69: =SUMIFS(BASE!$Q$3:$Q$453,BASE!$O$3:$O$453,Resumen!J$5,BASE!$B$3:$B$453,Resumen!$B69) -> 0 | K69: =SUMIFS('Eventos B2B_MKT y Turnos DT'!$K$6:$K$456,'Eventos B2B_MKT y Turnos DT'!$D$6:$D$456,Resumen!$B69,'Eventos B2B_MKT y Turnos DT'!$G$6:$G$456,"B2B") -> 0 | L69: =SUMIFS('Eventos B2B_MKT y Turnos DT'!$K$6:$K$456,'Eventos B2B_MKT y Turnos DT'!$D$6:$D$456,Resumen!$B69,'Eventos B2B_MKT y Turnos DT'!$G$6:$G$456,"Hotel") -> 0 | M69: =SUMIFS('Eventos B2B_MKT y Turnos DT'!$K$6:$K$456,'Eventos B2B_MKT y Turnos DT'!$D$6:$D$456,Resumen!$B69,'Eventos B2B_MKT y Turnos DT'!$G$6:$G$456,"Marketing") -> 0 | N69: =SUMIF(Incidencias!$E$4:$E$89,$B69,Incidencias!$K$4:$K$89) -> 0 | O69: =SUM(D69:N69) -> 531243 | P69: 0 | Q69: =+IF(AND(P69<>0,P69>O69*0.2),O69*0.2,P69) -> 0 | R69: =IFERROR(Q69/O69,0) -> 0 | S69: =IFERROR(P69-Q69,"") -> 0 | T69: =O69*(1-0.1525)-Q69 -> 450228.44 | U69: =+IF(O69*(1-0.1525)-Q69=T69,"OK","REVISAR") -> OK
B70: =Nómina!D67 -> 18725726-3 | C70: =Nómina!E67 -> RAFAEL EMILIANO RIQUELME VALDEBENITO | D70: =SUMIFS(BASE!$Q$3:$Q$453,BASE!$O$3:$O$453,Resumen!D$5,BASE!$B$3:$B$453,Resumen!$B70) -> 0 | E70: =SUMIFS(BASE!$Q$3:$Q$453,BASE!$O$3:$O$453,Resumen!E$5,BASE!$B$3:$B$453,Resumen!$B70) -> 0 | F70: =SUMIFS(BASE!$Q$3:$Q$453,BASE!$O$3:$O$453,Resumen!F$5,BASE!$B$3:$B$453,Resumen!$B70) -> 0 | G70: =SUMIFS(BASE!$Q$3:$Q$453,BASE!$O$3:$O$453,Resumen!G$5,BASE!$B$3:$B$453,Resumen!$B70) -> 0 | H70: =SUMIFS(BASE!$Q$3:$Q$453,BASE!$O$3:$O$453,Resumen!H$5,BASE!$B$3:$B$453,Resumen!$B70) -> 0 | I70: =SUMIFS(BASE!$Q$3:$Q$453,BASE!$O$3:$O$453,Resumen!I$5,BASE!$B$3:$B$453,Resumen!$B70) -> 0 | J70: =SUMIFS(BASE!$Q$3:$Q$453,BASE!$O$3:$O$453,Resumen!J$5,BASE!$B$3:$B$453,Resumen!$B70) -> 0 | K70: =SUMIFS('Eventos B2B_MKT y Turnos DT'!$K$6:$K$456,'Eventos B2B_MKT y Turnos DT'!$D$6:$D$456,Resumen!$B70,'Eventos B2B_MKT y Turnos DT'!$G$6:$G$456,"B2B") -> 0 | L70: =SUMIFS('Eventos B2B_MKT y Turnos DT'!$K$6:$K$456,'Eventos B2B_MKT y Turnos DT'!$D$6:$D$456,Resumen!$B70,'Eventos B2B_MKT y Turnos DT'!$G$6:$G$456,"Hotel") -> 46784 | M70: =SUMIFS('Eventos B2B_MKT y Turnos DT'!$K$6:$K$456,'Eventos B2B_MKT y Turnos DT'!$D$6:$D$456,Resumen!$B70,'Eventos B2B_MKT y Turnos DT'!$G$6:$G$456,"Marketing") -> 0 | N70: =SUMIF(Incidencias!$E$4:$E$89,$B70,Incidencias!$K$4:$K$89) -> 0 | O70: =SUM(D70:N70) -> 46784 | P70: 0 | Q70: =+IF(AND(P70<>0,P70>O70*0.2),O70*0.2,P70) -> 0 | R70: =IFERROR(Q70/O70,0) -> 0 | S70: =IFERROR(P70-Q70,"") -> 0 | T70: =O70*(1-0.1525)-Q70 -> 39649.44 | U70: =+IF(O70*(1-0.1525)-Q70=T70,"OK","REVISAR") -> OK
B71: =Nómina!D68 -> 27988098-6 | C71: =Nómina!E68 -> SERGIO RODRÍGUEZ | D71: =SUMIFS(BASE!$Q$3:$Q$453,BASE!$O$3:$O$453,Resumen!D$5,BASE!$B$3:$B$453,Resumen!$B71) -> 22689 | E71: =SUMIFS(BASE!$Q$3:$Q$453,BASE!$O$3:$O$453,Resumen!E$5,BASE!$B$3:$B$453,Resumen!$B71) -> 22689 | F71: =SUMIFS(BASE!$Q$3:$Q$453,BASE!$O$3:$O$453,Resumen!F$5,BASE!$B$3:$B$453,Resumen!$B71) -> 218319 | G71: =SUMIFS(BASE!$Q$3:$Q$453,BASE!$O$3:$O$453,Resumen!G$5,BASE!$B$3:$B$453,Resumen!$B71) -> 0 | H71: =SUMIFS(BASE!$Q$3:$Q$453,BASE!$O$3:$O$453,Resumen!H$5,BASE!$B$3:$B$453,Resumen!$B71) -> 0 | I71: =SUMIFS(BASE!$Q$3:$Q$453,BASE!$O$3:$O$453,Resumen!I$5,BASE!$B$3:$B$453,Resumen!$B71) -> 0 | J71: =SUMIFS(BASE!$Q$3:$Q$453,BASE!$O$3:$O$453,Resumen!J$5,BASE!$B$3:$B$453,Resumen!$B71) -> 0 | K71: =SUMIFS('Eventos B2B_MKT y Turnos DT'!$K$6:$K$456,'Eventos B2B_MKT y Turnos DT'!$D$6:$D$456,Resumen!$B71,'Eventos B2B_MKT y Turnos DT'!$G$6:$G$456,"B2B") -> 148236 | L71: =SUMIFS('Eventos B2B_MKT y Turnos DT'!$K$6:$K$456,'Eventos B2B_MKT y Turnos DT'!$D$6:$D$456,Resumen!$B71,'Eventos B2B_MKT y Turnos DT'!$G$6:$G$456,"Hotel") -> 46784 | M71: =SUMIFS('Eventos B2B_MKT y Turnos DT'!$K$6:$K$456,'Eventos B2B_MKT y Turnos DT'!$D$6:$D$456,Resumen!$B71,'Eventos B2B_MKT y Turnos DT'!$G$6:$G$456,"Marketing") -> 0 | N71: =SUMIF(Incidencias!$E$4:$E$89,$B71,Incidencias!$K$4:$K$89) -> 0 | O71: =SUM(D71:N71) -> 458717 | P71: 26750 | Q71: =+IF(AND(P71<>0,P71>O71*0.2),O71*0.2,P71) -> 26750 | R71: =IFERROR(Q71/O71,0) -> 0.058314822 | S71: =IFERROR(P71-Q71,"") -> 0 | T71: =O71*(1-0.1525)-Q71 -> 362012.66 | U71: =+IF(O71*(1-0.1525)-Q71=T71,"OK","REVISAR") -> OK
B72: =Nómina!D69 -> 19956304-1 | C72: =Nómina!E69 -> VALENTINA NICOLE JEREZ BRAVO | D72: =SUMIFS(BASE!$Q$3:$Q$453,BASE!$O$3:$O$453,Resumen!D$5,BASE!$B$3:$B$453,Resumen!$B72) -> 0 | E72: =SUMIFS(BASE!$Q$3:$Q$453,BASE!$O$3:$O$453,Resumen!E$5,BASE!$B$3:$B$453,Resumen!$B72) -> 0 | F72: =SUMIFS(BASE!$Q$3:$Q$453,BASE!$O$3:$O$453,Resumen!F$5,BASE!$B$3:$B$453,Resumen!$B72) -> 0 | G72: =SUMIFS(BASE!$Q$3:$Q$453,BASE!$O$3:$O$453,Resumen!G$5,BASE!$B$3:$B$453,Resumen!$B72) -> 0 | H72: =SUMIFS(BASE!$Q$3:$Q$453,BASE!$O$3:$O$453,Resumen!H$5,BASE!$B$3:$B$453,Resumen!$B72) -> 0 | I72: =SUMIFS(BASE!$Q$3:$Q$453,BASE!$O$3:$O$453,Resumen!I$5,BASE!$B$3:$B$453,Resumen!$B72) -> 0 | J72: =SUMIFS(BASE!$Q$3:$Q$453,BASE!$O$3:$O$453,Resumen!J$5,BASE!$B$3:$B$453,Resumen!$B72) -> 0 | K72: =SUMIFS('Eventos B2B_MKT y Turnos DT'!$K$6:$K$456,'Eventos B2B_MKT y Turnos DT'!$D$6:$D$456,Resumen!$B72,'Eventos B2B_MKT y Turnos DT'!$G$6:$G$456,"B2B") -> 0 | L72: =SUMIFS('Eventos B2B_MKT y Turnos DT'!$K$6:$K$456,'Eventos B2B_MKT y Turnos DT'!$D$6:$D$456,Resumen!$B72,'Eventos B2B_MKT y Turnos DT'!$G$6:$G$456,"Hotel") -> 0 | M72: =SUMIFS('Eventos B2B_MKT y Turnos DT'!$K$6:$K$456,'Eventos B2B_MKT y Turnos DT'!$D$6:$D$456,Resumen!$B72,'Eventos B2B_MKT y Turnos DT'!$G$6:$G$456,"Marketing") -> 0 | N72: =SUMIF(Incidencias!$E$4:$E$89,$B72,Incidencias!$K$4:$K$89) -> 0 | O72: =SUM(D72:N72) -> 0 | P72: 113235 | R72: =IFERROR(Q72/O72,0) -> 0 | S72: =IFERROR(P72-Q72,"") -> 113235 | T72: =O72*(1-0.1525)-Q72 -> 0 | U72: =+IF(O72*(1-0.1525)-Q72=T72,"OK","REVISAR") -> OK
B73: =Nómina!D70 -> 19700904-7 | C73: =Nómina!E70 -> VICTORIA ANTONIA CABEZAS VIDELA | D73: =SUMIFS(BASE!$Q$3:$Q$453,BASE!$O$3:$O$453,Resumen!D$5,BASE!$B$3:$B$453,Resumen!$B73) -> 0 | E73: =SUMIFS(BASE!$Q$3:$Q$453,BASE!$O$3:$O$453,Resumen!E$5,BASE!$B$3:$B$453,Resumen!$B73) -> 0 | F73: =SUMIFS(BASE!$Q$3:$Q$453,BASE!$O$3:$O$453,Resumen!F$5,BASE!$B$3:$B$453,Resumen!$B73) -> 22689 | G73: =SUMIFS(BASE!$Q$3:$Q$453,BASE!$O$3:$O$453,Resumen!G$5,BASE!$B$3:$B$453,Resumen!$B73) -> 0 | H73: =SUMIFS(BASE!$Q$3:$Q$453,BASE!$O$3:$O$453,Resumen!H$5,BASE!$B$3:$B$453,Resumen!$B73) -> 0 | I73: =SUMIFS(BASE!$Q$3:$Q$453,BASE!$O$3:$O$453,Resumen!I$5,BASE!$B$3:$B$453,Resumen!$B73) -> 0 | J73: =SUMIFS(BASE!$Q$3:$Q$453,BASE!$O$3:$O$453,Resumen!J$5,BASE!$B$3:$B$453,Resumen!$B73) -> 0 | K73: =SUMIFS('Eventos B2B_MKT y Turnos DT'!$K$6:$K$456,'Eventos B2B_MKT y Turnos DT'!$D$6:$D$456,Resumen!$B73,'Eventos B2B_MKT y Turnos DT'!$G$6:$G$456,"B2B") -> 0 | L73: =SUMIFS('Eventos B2B_MKT y Turnos DT'!$K$6:$K$456,'Eventos B2B_MKT y Turnos DT'!$D$6:$D$456,Resumen!$B73,'Eventos B2B_MKT y Turnos DT'!$G$6:$G$456,"Hotel") -> 23392 | M73: =SUMIFS('Eventos B2B_MKT y Turnos DT'!$K$6:$K$456,'Eventos B2B_MKT y Turnos DT'!$D$6:$D$456,Resumen!$B73,'Eventos B2B_MKT y Turnos DT'!$G$6:$G$456,"Marketing") -> 0 | N73: =SUMIF(Incidencias!$E$4:$E$89,$B73,Incidencias!$K$4:$K$89) -> 0 | O73: =SUM(D73:N73) -> 46081 | P73: 0 | Q73: =+IF(AND(P73<>0,P73>O73*0.2),O73*0.2,P73) -> 0 | R73: =IFERROR(Q73/O73,0) -> 0 | S73: =IFERROR(P73-Q73,"") -> 0 | T73: =O73*(1-0.1525)-Q73 -> 39053.647 | U73: =+IF(O73*(1-0.1525)-Q73=T73,"OK","REVISAR") -> OK
B74: =Nómina!D71 -> 26330714-3 | C74: =Nómina!E71 -> WENDY CAROLINA MENDEZ AVENDAÑO | D74: =SUMIFS(BASE!$Q$3:$Q$453,BASE!$O$3:$O$453,Resumen!D$5,BASE!$B$3:$B$453,Resumen!$B74) -> 61008 | E74: =SUMIFS(BASE!$Q$3:$Q$453,BASE!$O$3:$O$453,Resumen!E$5,BASE!$B$3:$B$453,Resumen!$B74) -> 0 | F74: =SUMIFS(BASE!$Q$3:$Q$453,BASE!$O$3:$O$453,Resumen!F$5,BASE!$B$3:$B$453,Resumen!$B74) -> 22689 | G74: =SUMIFS(BASE!$Q$3:$Q$453,BASE!$O$3:$O$453,Resumen!G$5,BASE!$B$3:$B$453,Resumen!$B74) -> 0 | H74: =SUMIFS(BASE!$Q$3:$Q$453,BASE!$O$3:$O$453,Resumen!H$5,BASE!$B$3:$B$453,Resumen!$B74) -> 0 | I74: =SUMIFS(BASE!$Q$3:$Q$453,BASE!$O$3:$O$453,Resumen!I$5,BASE!$B$3:$B$453,Resumen!$B74) -> 0 | J74: =SUMIFS(BASE!$Q$3:$Q$453,BASE!$O$3:$O$453,Resumen!J$5,BASE!$B$3:$B$453,Resumen!$B74) -> 0 | K74: =SUMIFS('Eventos B2B_MKT y Turnos DT'!$K$6:$K$456,'Eventos B2B_MKT y Turnos DT'!$D$6:$D$456,Resumen!$B74,'Eventos B2B_MKT y Turnos DT'!$G$6:$G$456,"B2B") -> 148236 | L74: =SUMIFS('Eventos B2B_MKT y Turnos DT'!$K$6:$K$456,'Eventos B2B_MKT y Turnos DT'!$D$6:$D$456,Resumen!$B74,'Eventos B2B_MKT y Turnos DT'!$G$6:$G$456,"Hotel") -> 0 | M74: =SUMIFS('Eventos B2B_MKT y Turnos DT'!$K$6:$K$456,'Eventos B2B_MKT y Turnos DT'!$D$6:$D$456,Resumen!$B74,'Eventos B2B_MKT y Turnos DT'!$G$6:$G$456,"Marketing") -> 0 | N74: =SUMIF(Incidencias!$E$4:$E$89,$B74,Incidencias!$K$4:$K$89) -> 0 | O74: =SUM(D74:N74) -> 231933 | P74: 0 | Q74: =+IF(AND(P74<>0,P74>O74*0.2),O74*0.2,P74) -> 0 | R74: =IFERROR(Q74/O74,0) -> 0 | S74: =IFERROR(P74-Q74,"") -> 0 | T74: =O74*(1-0.1525)-Q74 -> 196563.22 | U74: =+IF(O74*(1-0.1525)-Q74=T74,"OK","REVISAR") -> OK
B75: =Nómina!D72 -> 25310926-2 | C75: =Nómina!E72 -> WILLESKA ORTEGA JUSTO | D75: =SUMIFS(BASE!$Q$3:$Q$453,BASE!$O$3:$O$453,Resumen!D$5,BASE!$B$3:$B$453,Resumen!$B75) -> 66715 | E75: =SUMIFS(BASE!$Q$3:$Q$453,BASE!$O$3:$O$453,Resumen!E$5,BASE!$B$3:$B$453,Resumen!$B75) -> 0 | F75: =SUMIFS(BASE!$Q$3:$Q$453,BASE!$O$3:$O$453,Resumen!F$5,BASE!$B$3:$B$453,Resumen!$B75) -> 31765 | G75: =SUMIFS(BASE!$Q$3:$Q$453,BASE!$O$3:$O$453,Resumen!G$5,BASE!$B$3:$B$453,Resumen!$B75) -> 0 | H75: =SUMIFS(BASE!$Q$3:$Q$453,BASE!$O$3:$O$453,Resumen!H$5,BASE!$B$3:$B$453,Resumen!$B75) -> 0 | I75: =SUMIFS(BASE!$Q$3:$Q$453,BASE!$O$3:$O$453,Resumen!I$5,BASE!$B$3:$B$453,Resumen!$B75) -> 0 | J75: =SUMIFS(BASE!$Q$3:$Q$453,BASE!$O$3:$O$453,Resumen!J$5,BASE!$B$3:$B$453,Resumen!$B75) -> 0 | K75: =SUMIFS('Eventos B2B_MKT y Turnos DT'!$K$6:$K$456,'Eventos B2B_MKT y Turnos DT'!$D$6:$D$456,Resumen!$B75,'Eventos B2B_MKT y Turnos DT'!$G$6:$G$456,"B2B") -> 0 | L75: =SUMIFS('Eventos B2B_MKT y Turnos DT'!$K$6:$K$456,'Eventos B2B_MKT y Turnos DT'!$D$6:$D$456,Resumen!$B75,'Eventos B2B_MKT y Turnos DT'!$G$6:$G$456,"Hotel") -> 0 | M75: =SUMIFS('Eventos B2B_MKT y Turnos DT'!$K$6:$K$456,'Eventos B2B_MKT y Turnos DT'!$D$6:$D$456,Resumen!$B75,'Eventos B2B_MKT y Turnos DT'!$G$6:$G$456,"Marketing") -> 0 | N75: =SUMIF(Incidencias!$E$4:$E$89,$B75,Incidencias!$K$4:$K$89) -> 0 | O75: =SUM(D75:N75) -> 98480 | P75: 0 | Q75: =+IF(AND(P75<>0,P75>O75*0.2),O75*0.2,P75) -> 0 | R75: =IFERROR(Q75/O75,0) -> 0 | S75: =IFERROR(P75-Q75,"") -> 0 | T75: =O75*(1-0.1525)-Q75 -> 83461.8 | U75: =+IF(O75*(1-0.1525)-Q75=T75,"OK","REVISAR") -> OK
B76: =Nómina!D73 -> 17707188-9 | C76: =Nómina!E73 -> XIMENA ESTEFANIA PASTEN PINO | D76: =SUMIFS(BASE!$Q$3:$Q$453,BASE!$O$3:$O$453,Resumen!D$5,BASE!$B$3:$B$453,Resumen!$B76) -> 0 | E76: =SUMIFS(BASE!$Q$3:$Q$453,BASE!$O$3:$O$453,Resumen!E$5,BASE!$B$3:$B$453,Resumen!$B76) -> 0 | F76: =SUMIFS(BASE!$Q$3:$Q$453,BASE!$O$3:$O$453,Resumen!F$5,BASE!$B$3:$B$453,Resumen!$B76) -> 22689 | G76: =SUMIFS(BASE!$Q$3:$Q$453,BASE!$O$3:$O$453,Resumen!G$5,BASE!$B$3:$B$453,Resumen!$B76) -> 0 | H76: =SUMIFS(BASE!$Q$3:$Q$453,BASE!$O$3:$O$453,Resumen!H$5,BASE!$B$3:$B$453,Resumen!$B76) -> 0 | I76: =SUMIFS(BASE!$Q$3:$Q$453,BASE!$O$3:$O$453,Resumen!I$5,BASE!$B$3:$B$453,Resumen!$B76) -> 0 | J76: =SUMIFS(BASE!$Q$3:$Q$453,BASE!$O$3:$O$453,Resumen!J$5,BASE!$B$3:$B$453,Resumen!$B76) -> 0 | K76: =SUMIFS('Eventos B2B_MKT y Turnos DT'!$K$6:$K$456,'Eventos B2B_MKT y Turnos DT'!$D$6:$D$456,Resumen!$B76,'Eventos B2B_MKT y Turnos DT'!$G$6:$G$456,"B2B") -> 106639 | L76: =SUMIFS('Eventos B2B_MKT y Turnos DT'!$K$6:$K$456,'Eventos B2B_MKT y Turnos DT'!$D$6:$D$456,Resumen!$B76,'Eventos B2B_MKT y Turnos DT'!$G$6:$G$456,"Hotel") -> 23392 | M76: =SUMIFS('Eventos B2B_MKT y Turnos DT'!$K$6:$K$456,'Eventos B2B_MKT y Turnos DT'!$D$6:$D$456,Resumen!$B76,'Eventos B2B_MKT y Turnos DT'!$G$6:$G$456,"Marketing") -> 0 | N76: =SUMIF(Incidencias!$E$4:$E$89,$B76,Incidencias!$K$4:$K$89) -> 0 | O76: =SUM(D76:N76) -> 152720 | P76: 0 | Q76: =+IF(AND(P76<>0,P76>O76*0.2),O76*0.2,P76) -> 0 | R76: =IFERROR(Q76/O76,0) -> 0 | S76: =IFERROR(P76-Q76,"") -> 0 | T76: =O76*(1-0.1525)-Q76 -> 129430.2 | U76: =+IF(O76*(1-0.1525)-Q76=T76,"OK","REVISAR") -> OK
B77: =Nómina!D74 -> 18610367-K | C77: =Nómina!E74 -> YASNA DEL PILAR MATUS FUENTES | D77: =SUMIFS(BASE!$Q$3:$Q$453,BASE!$O$3:$O$453,Resumen!D$5,BASE!$B$3:$B$453,Resumen!$B77) -> 0 | E77: =SUMIFS(BASE!$Q$3:$Q$453,BASE!$O$3:$O$453,Resumen!E$5,BASE!$B$3:$B$453,Resumen!$B77) -> 0 | F77: =SUMIFS(BASE!$Q$3:$Q$453,BASE!$O$3:$O$453,Resumen!F$5,BASE!$B$3:$B$453,Resumen!$B77) -> 0 | G77: =SUMIFS(BASE!$Q$3:$Q$453,BASE!$O$3:$O$453,Resumen!G$5,BASE!$B$3:$B$453,Resumen!$B77) -> 0 | H77: =SUMIFS(BASE!$Q$3:$Q$453,BASE!$O$3:$O$453,Resumen!H$5,BASE!$B$3:$B$453,Resumen!$B77) -> 0 | I77: =SUMIFS(BASE!$Q$3:$Q$453,BASE!$O$3:$O$453,Resumen!I$5,BASE!$B$3:$B$453,Resumen!$B77) -> 0 | J77: =SUMIFS(BASE!$Q$3:$Q$453,BASE!$O$3:$O$453,Resumen!J$5,BASE!$B$3:$B$453,Resumen!$B77) -> 0 | K77: =SUMIFS('Eventos B2B_MKT y Turnos DT'!$K$6:$K$456,'Eventos B2B_MKT y Turnos DT'!$D$6:$D$456,Resumen!$B77,'Eventos B2B_MKT y Turnos DT'!$G$6:$G$456,"B2B") -> 0 | L77: =SUMIFS('Eventos B2B_MKT y Turnos DT'!$K$6:$K$456,'Eventos B2B_MKT y Turnos DT'!$D$6:$D$456,Resumen!$B77,'Eventos B2B_MKT y Turnos DT'!$G$6:$G$456,"Hotel") -> 0 | M77: =SUMIFS('Eventos B2B_MKT y Turnos DT'!$K$6:$K$456,'Eventos B2B_MKT y Turnos DT'!$D$6:$D$456,Resumen!$B77,'Eventos B2B_MKT y Turnos DT'!$G$6:$G$456,"Marketing") -> 0 | N77: =SUMIF(Incidencias!$E$4:$E$89,$B77,Incidencias!$K$4:$K$89) -> 0 | O77: =SUM(D77:N77) -> 0 | P77: 83754.185 | Q77: =+IF(AND(P77<>0,P77>O77*0.2),O77*0.2,P77) -> 0 | R77: =IFERROR(Q77/O77,0) -> 0 | S77: =IFERROR(P77-Q77,"") -> 83754.185 | T77: =O77*(1-0.1525)-Q77 -> 0 | U77: =+IF(O77*(1-0.1525)-Q77=T77,"OK","REVISAR") -> OK

Sheet Eventos B2B_MKT y Turnos DT
N2: Líneas de Negocio | O2: B2B | P2: =SUMIF($G$6:$G$55,O2,$K$6:$K$55) -> 509750
O3: Hotel | P3: =SUMIF($G$6:$G$55,O3,$K$6:$K$55) -> 327488
K4: =SUBTOTAL(9,K6:K1048576) -> 837238 | O4: Marketing | P4: =SUMIF($G$6:$G$55,O4,$K$6:$K$55) -> 0
B5: Año | C5: Mes | D5: RUT | E5: Nombre Tp | F5: Fecha Evento | G5: Línea de Negocio | H5: Cliente / Evento | I5: Hrs evento | J5: Tipo Servicio | K5: Comisión
B6: 2026 | C6: 7 | D6: 18725726-3 | E6: RAFAEL EMILIANO RIQUELME VALDEBENITO | F6: 46207 | G6: Hotel | H6: Doubletree Bloque 1 | I6: 4 | J6: Camilla | K6: 23392
B7: 2026 | C7: 7 | D7: 17707188-9 | E7: XIMENA ESTEFANIA PASTEN PINO | F7: 46207 | G7: Hotel | H7: Doubletree Bloque 1 | I7: 4 | J7: Camilla | K7: 23392
B8: 2026 | C8: 7 | D8: 19232974-4 | E8: JOSE IGNACIO PALMA CASANOVA | F8: 46207 | G8: Hotel | H8: Doubletree Bloque 2 | I8: 4 | J8: Camilla | K8: 23392
B9: 2026 | C9: 7 | D9: 13441148-1 | E9: CLAUDIA ESTRELLA ESPINOZA CANIUQUEO | F9: 46207 | G9: Hotel | H9: Doubletree Bloque 2 | I9: 4 | J9: Camilla | K9: 23392
B10: 2026 | C10: 7 | D10: 27988098-6 | E10: SERGIO RODRÍGUEZ | F10: 46208 | G10: Hotel | H10: Doubletree Bloque 1 | I10: 4 | J10: Camilla | K10: 23392
B11: 2026 | C11: 7 | D11: 13715658-K | E11: ALEJANDRA PAZ SANCHEZ LENERO | F11: 46208 | G11: Hotel | H11: Doubletree Bloque 1 | I11: 4 | J11: Camilla | K11: 23392
B12: 2026 | C12: 7 | D12: 17681238-9 | E12: IVVO LEANDRO VERGARA SALINAS | F12: 46208 | G12: Hotel | H12: Doubletree Bloque 2 | I12: 4 | J12: Camilla | K12: 23392
B13: 2026 | C13: 7 | D13: 26330714-3 | E13: WENDY CAROLINA MENDEZ AVENDAÑO | F13: 46210 | G13: B2B | H13: TECHSPERT | I13: 2 | J13: Silla | K13: 41597
B14: 2026 | C14: 7 | D14: 27988098-6 | E14: SERGIO RODRÍGUEZ | F14: 46210 | G14: B2B | H14: TECHSPERT | I14: 2 | J14: Silla | K14: 41597
B15: 2026 | C15: 7 | D15: 17707188-9 | E15: XIMENA ESTEFANIA PASTEN PINO | F15: 46212 | G15: B2B | H15: HATCH | I15: 6 | J15: Silla | K15: 106639
B16: 2026 | C16: 7 | D16: 26330714-3 | E16: WENDY CAROLINA MENDEZ AVENDAÑO | F16: 46212 | G16: B2B | H16: HATCH | I16: 6 | J16: Silla | K16: 106639
B17: 2026 | C17: 7 | D17: 27988098-6 | E17: SERGIO RODRÍGUEZ | F17: 46212 | G17: B2B | H17: HATCH | I17: 6 | J17: Silla | K17: 106639
... B25: 2026 | C25: 7 | D25: 19232974-4 | E25: JOSE IGNACIO PALMA CASANOVA | F25: 46215 | G25: Hotel | H25: Doubletree Bloque 2 | I25: 4 | J25: Camilla | K25: 23392

Sheet Incidencias
B2: INCIDENCIAS | K2: =SUBTOTAL(9,K4:K1048576) -> 45000
B3: Año | C3: Mes | D3: Quinc. | E3: RUT | F3: Terapeuta | G3: Fecha reserva | H3: Hora Reserva | I3: Nombre Cliente | J3: Línea de Negocio | K3: Monto Incidencia Tps | L3: Tipo de Incidencia | M3: Detalle Incidencia
B4: 2026 | C4: 7 | D4: 1 | E4: 17681238-9 | F4: IVVO LEANDRO VERGARA SALINAS | G4: 46212 | H4: 0.70833333 | I4: Bidasoa | J4: Hotel | K4: 15000 | L4: Cancelación hotel | M4: Huésped desiste del servicio.
B5: 2026 | C5: 7 | D5: 1 | E5: 12897620-5 | F5: EUGENIA ISABEL MONTOYA VIELMA | G5: 46212 | H5: 0.70833333 | I5: Bidasoa | J5: Hotel | K5: 15000 | L5: Cancelación hotel | M5: Huésped desiste del servicio.
B6: 2026 | C6: 7 | D6: 1 | E6: 17416146-1 | F6: MARIA JOSE BUSTOS PINCHULEF | G6: 46218 | H6: 0.75 | I6: Aubrey | J6: Hotel | K6: 15000 | L6: Error de agendamiento | M6: Se agendó servicio para día anterior al solicitado.

Sheet Detalle para terapeutas
C2: Seleccionar de la lista desplegable | F2: Total Hoja Resumen | G2: Validación
F3: =VLOOKUP(C6,Resumen!C:Q,13,0) -> 22689 | G3: =IF(F3=E13,"OK","REVISAR") -> REVISAR
B6: Nombre Terapeuta: | C6: BETTINA GAJARDO
B7: Mes:
B8: Quincena:
B10: RESUMEN
B12: Total Servicios | C12: Eventos | D12: Incidencias | E12: Monto Boleta | F12: Deuda total | G12: Descuentos | H12: % Dcto. | I12: Deuda Restante | J12: Monto a pago
B13: =SUM(D18:D101) -> 0 | C13: =SUM(H120:H140) -> 0 | D13: =SUM(G105:G114) -> 0 | E13: =SUM(B13:D13) -> 0 | F13: =VLOOKUP($C$6,Resumen!$C:$T,12,0) -> 0 | G13: =VLOOKUP($C$6,Resumen!$C:$T,13,0) -> 22689 | H13: =VLOOKUP($C$6,Resumen!$C:$T,14,0) -> 0 | I13: =VLOOKUP($C$6,Resumen!$C:$T,15,0) -> 0 | J13: =VLOOKUP($C$6,Resumen!$C:$T,16,0) -> 0
B15: SERVICIOS
B17: Terapeuta | C17: RUT | D17: Comisión | E17: Fecha reserva | F17: Línea de negocio | G17: Categoría | H17: Tipo | I17: Duración | J17: Servicio | K17: Zona | L17: Detalle | M17: Calificación servicio | N17: Calificación terapeuta | O17: Comentario usuario
B18: {=_xlfn._xlws.FILTER(BASE!A3:N186,BASE!A3:A186=C6,"")}
B102: INCIDENCIAS
B104: Nombre Tp | C104: Fecha reserva | D104: Hora Reserva | E104: Nombre Cliente | F104: Línea de Negocio | G104: Monto Incidencia Tps | H104: Tipo de Incidencia | I104: Detalle Incidencia
B105: {=_xlfn._xlws.FILTER(Incidencias!F4:M39,Incidencias!F4:F39=C6,"")}
B117: EVENTOS / TURNOS DT
B119: Terapeuta | C119: Fecha | D119: Línea de Negocio | E119: Cliente / Evento | F119: Hrs | G119: Tipo Servicio | H119: Comisión
B120: {=_xlfn._xlws.FILTER('Eventos B2B_MKT y Turnos DT'!E6:K156,'Eventos B2B_MKT y Turnos DT'!E6:E156=C6,"")}

Sheet BASE
P1: =SUBTOTAL(9,P3:P470) -> 6369900 | Q1: =SUBTOTAL(9,Q3:Q470) -> 3225204 | AG1: =SUBTOTAL(9,AG3:AG470) -> 6369900 | AH1: =SUBTOTAL(9,AH3:AH470) -> 5928960 | AI1: =SUBTOTAL(9,AI3:AI470) -> 278990 | AK1: =SUBTOTAL(9,AK3:AK470) -> 3899520 | AM1: =SUBTOTAL(9,AM3:AM186) -> 0
A2: Terapeuta | B2: RUT | C2: Comisión | D2: Fecha reserva | E2: Línea de negocio | F2: Categoría | G2: Tipo | H2: Duración | I2: Servicio | J2: Comuna | K2: Detalle | L2: Calificación servicio | M2: Calificación terapeuta | N2: Comentario usuario | O2: Tipo de Servicio | P2: Precio Lista | Q2: Comisión Tp | R2: Mes | S2: Día | T2: Quincena | U2: País | V2: ID Reserva | W2: Fecha pago | X2: Fecha reserva | Y2: Hora reserva | Z2: Método de pago | AA2: Plataforma | AB2: Línea de negocio | AC2: Categoría | AD2: Tipo | AE2: Duración | AF2: Servicio | AG2: Precio de lista | AH2: Monto pagado | AI2: Monto Certificado/Wallet | AJ2: Monto Promocode | AK2: Comisión terapeuta | AL2: Promocode | AM2: ID CR | AN2: ID Lote CR | AO2: Nombre Lote CR | AP2: Nombre Partnership | AQ2: ID Cliente | AR2: Nombre Cliente | AS2: Zona | AT2: Ciudad | AU2: ID Terapeuta | AV2: Nombre Terapeuta | AW2: Estatus | AX2: Comentarios internos | AY2: Calificación del servicio | AZ2: Calificación del terapeuta | BA2: Comentario del usuario | BB2: Link del Dashboard | BC2: TaxID Partnership
A3: =IFERROR(VLOOKUP(AV3,Nómina!B:E,4,0),"") -> PAMELA VERONICA CID NAVIA | B3: =IFERROR(VLOOKUP(A3,Nómina!E:F,2,0),"") -> 8008360-2 | C3: =IFERROR(Q3,"") -> 22689 | D3: =IFERROR(X3,"") -> 2026-07-01 | E3: =IFERROR(O3,"") -> CERTIFICADO B2C | F3: =IFERROR(AC3,"") -> Masaje | G3: =IFERROR(AD3,"") -> Individual | H3: =IFERROR(AE3,"") -> 60min | I3: =IFERROR(AF3,"") -> Relajante | J3: =IFERROR(AT3,"") -> VITACURA | K3: =IFERROR(AX3,"") -> Ninguno | L3: =IFERROR(AY3,"") -> 0 | M3: =IFERROR(AZ3,"") -> 0 | N3: =IFERROR(BA3,"") | O3: =+VLOOKUP(Z3,listas!$B:$C,2,0) -> CERTIFICADO B2C | P3: =AG3 -> 45000 | Q3: =IF(AC3="Extra",IF(AF3="Extra de transporte",ROUND(P3/1.19*0.95,0),ROUND(P3/1.19*0.6,0)),ROUND(P3/1.19*0.6,0)) -> 22689 | R3: =MONTH(X3) -> 7 | S3: =DAY(X3) -> 1 | T3: =IF(S3>15,2,1) -> 1 | U3: CL | V3: qQB5yF3zyz | W3: 2026-06-29 | X3: 2026-07-01 | Y3: 09:00 | Z3: Certificado B2C | AA3: Dashboard | AB3: B2C | AC3: Masaje | AD3: Individual | AE3: 60min | AF3: Relajante | AG3: 45000 | AH3: 0 | AI3: 45000 | AJ3: 0 | AK3: 27000 | AM3: enypO2xGpF | AQ3: n4GPXYix4T | AR3: Mariella Pellegrini | AS3: VITACURA | AT3: VITACURA | AU3: K4Rt2FH54k | AV3: Pamela Cid | AW3: Terminado | AX3: Ninguno | AY3: 0 | AZ3: 0 | BB3: https://admin.scape.mx/appointment/qQB5yF3zyz
A4: =IFERROR(VLOOKUP(AV4,Nómina!B:E,4,0),"") -> CLAUDIA ESTRELLA ESPINOZA CANIUQUEO | B4: =IFERROR(VLOOKUP(A4,Nómina!E:F,2,0),"") -> 13441148-1 | C4: =IFERROR(Q4,"") -> 22689 | D4: =IFERROR(X4,"") -> 2026-07-01 | E4: =IFERROR(O4,"") -> CERTIFICADO B2B | F4: =IFERROR(AC4,"") -> Masaje | G4: =IFERROR(AD4,"") -> Individual | H4: =IFERROR(AE4,"") -> 60min | I4: =IFERROR(AF4,"") -> Relajante | J4: =IFERROR(AT4,"") -> ESTACIÓN CENTRAL | K4: =IFERROR(AX4,"") -> Ninguno | L4: =IFERROR(AY4,"") -> 0 | M4: =IFERROR(AZ4,"") -> 0 | N4: =IFERROR(BA4,"") | O4: =+VLOOKUP(Z4,listas!$B:$C,2,0) -> CERTIFICADO B2B | P4: =AG4 -> 45000 | Q4: =IF(AC4="Extra",IF(AF4="Extra de transporte",ROUND(P4/1.19*0.95,0),ROUND(P4/1.19*0.6,0)),ROUND(P4/1.19*0.6,0)) -> 22689 | R4: =MONTH(X4) -> 7 | S4: =DAY(X4) -> 1 | T4: =IF(S4>15,2,1) -> 1 | U4: CL | V4: 4fSPotDG0D | W4: 2026-07-02 | X4: 2026-07-01 | Y4: 11:00 | Z4: Certificado B2B | AA4: Dashboard | AB4: B2B | AC4: Masaje | AD4: Individual | AE4: 60min | AF4: Relajante | AG4: 45000 | AH4: 0 | AI4: 45000 | AJ4: 0 | AK4: 27000 | AM4: IMYsRBDRAV | AN4: DbxjRuFBeH | AO4: Galgo60 | AQ4: w0BFLkhpWC | AR4: Dayana Gonzalez Arismendy | AS4: ESTACIÓN CENTRAL | AT4: ESTACIÓN CENTRAL | AU4: AlqePd7Qkf | AV4: Claudia Espinoza | AW4: Terminado | AX4: Ninguno | AY4: 0 | AZ4: 0 | BB4: https://admin.scape.mx/appointment/4fSPotDG0D
A5: =IFERROR(VLOOKUP(AV5,Nómina!B:E,4,0),"") -> GENESIS VALENTINA SALAZAR GUEVARA | B5: =IFERROR(VLOOKUP(A5,Nómina!E:F,2,0),"") -> 27828546-4 | C5: =IFERROR(Q5,"") -> 22689 | D5: =IFERROR(X5,"") -> 2026-07-01 | E5: =IFERROR(O5,"") -> B2C | F5: =IFERROR(AC5,"") -> Masaje | G5: =IFERROR(AD5,"") -> Individual | H5: =IFERROR(AE5,"") -> 60min | I5: =IFERROR(AF5,"") -> Relajante | J5: =IFERROR(AT5,"") -> LAS CONDES | K5: =IFERROR(AX5,"") -> Ninguno | L5: =IFERROR(AY5,"") -> 0 | M5: =IFERROR(AZ5,"") -> 0 | N5: =IFERROR(BA5,"") | O5: =+VLOOKUP(Z5,listas!$B:$C,2,0) -> B2C | P5: =AG5 -> 45000 | Q5: =IF(AC5="Extra",IF(AF5="Extra de transporte",ROUND(P5/1.19*0.95,0),ROUND(P5/1.19*0.6,0)),ROUND(P5/1.19*0.6,0)) -> 22689 | R5: =MONTH(X5) -> 7 | S5: =DAY(X5) -> 1 | T5: =IF(S5>15,2,1) -> 1 | U5: CL | V5: B89Wrkf48I | W5: 2026-06-21 | X5: 2026-07-01 | Y5: 17:00 | Z5: MercadoPago | AA5: Web | AB5: B2C | AC5: Masaje | AD5: Individual | AE5: 60min | AF5: Relajante | AG5: 45000 | AH5: 45000 | AI5: 0 | AJ5: 0 | AK5: 27000 | AQ5: mIoUUAyjSk | AR5: Rosario Vacarezza Armendariz | AS5: LAS CONDES | AT5: LAS CONDES | AU5: TcqJ1GTAe6 | AV5: Valentina Salazar Guevara | AW5: Terminado | AX5: Ninguno | AY5: 0 | AZ5: 0 | BB5: https://admin.scape.mx/appointment/B89Wrkf48I
A6: =IFERROR(VLOOKUP(AV6,Nómina!B:E,4,0),"") -> PAMELA CONSTANZA HUILITRARO QUEZADA | B6: =IFERROR(VLOOKUP(A6,Nómina!E:F,2,0),"") -> 18881513-8 | C6: =IFERROR(Q6,"") -> 31765 | D6: =IFERROR(X6,"") -> 2026-07-01 | E6: =IFERROR(O6,"") -> HOTEL | F6: =IFERROR(AC6,"") -> Masaje | G6: =IFERROR(AD6,"") -> Individual | H6: =IFERROR(AE6,"") -> 90min | I6: =IFERROR(AF6,"") -> Tejido profundo | J6: =IFERROR(AT6,"") -> VITACURA | K6: =IFERROR(AX6,"") -> Huésped: Fernando Gelman. Hab: TBC. | L6: =IFERROR(AY6,"") -> 0 | M6: =IFERROR(AZ6,"") -> 0 | N6: =IFERROR(BA6,"") | O6: =+VLOOKUP(Z6,listas!$B:$C,2,0) -> HOTEL | P6: =AG6 -> 63000 | Q6: =IF(AC6="Extra",IF(AF6="Extra de transporte",ROUND(P6/1.19*0.95,0),ROUND(P6/1.19*0.6,0)),ROUND(P6/1.19*0.6,0)) -> 31765 | R6: =MONTH(X6) -> 7 | S6: =DAY(X6) -> 1 | T6: =IF(S6>15,2,1) -> 1 | U6: CL | V6: iCSfEb8NDQ | W6: 2026-07-01 | X6: 2026-07-01 | Y6: 17:00 | Z6: Hotel | AA6: Dashboard | AB6: Hotel | AC6: Masaje | AD6: Individual | AE6: 90min | AF6: Tejido profundo | AG6: 63000 | AH6: 63000 | AI6: 0 | AJ6: 0 | AK6: 37800 | AQ6: OLPG5ZHFBh | AR6: Bidasoa | AS6: VITACURA | AT6: VITACURA | AU6: lHeDnjpSlr | AV6: Pamela Huilitraro Quezada | AW6: Terminado | AX6: Huésped: Fernando Gelman. Hab: TBC. | AY6: 0 | AZ6: 0 | BB6: https://admin.scape.mx/appointment/iCSfEb8NDQ
A7: =IFERROR(VLOOKUP(AV7,Nómina!B:E,4,0),"") -> SERGIO RODRÍGUEZ | B7: =IFERROR(VLOOKUP(A7,Nómina!E:F,2,0),"") -> 27988098-6 | C7: =IFERROR(Q7,"") -> 22689 | D7: =IFERROR(X7,"") -> 2026-07-01 | E7: =IFERROR(O7,"") -> HOTEL | F7: =IFERROR(AC7,"") -> Masaje | G7: =IFERROR(AD7,"") -> Pareja | H7: =IFERROR(AE7,"") -> 60min | I7: =IFERROR(AF7,"") -> Relajante | J7: =IFERROR(AT7,"") -> PROVIDENCIA | K7: =IFERROR(AX7,"") -> Huéspedes: Andres Valenzuela & Dominique Rousseau. Hab: 206. | L7: =IFERROR(AY7,"") -> 0 | M7: =IFERROR(AZ7,"") -> 0 | N7: =IFERROR(BA7,"") | O7: =+VLOOKUP(Z7,listas!$B:$C,2,0) -> HOTEL | P7: =AG7 -> 45000 | Q7: =IF(AC7="Extra",IF(AF7="Extra de transporte",ROUND(P7/1.19*0.95,0),ROUND(P7/1.19*0.6,0)),ROUND(P7/1.19*0.6,0)) -> 22689 | R7: =MONTH(X7) -> 7 | S7: =DAY(X7) -> 1 | T7: =IF(S7>15,2,1) -> 1 | U7: CL | V7: YiZcUqymqq | W7: 2026-06-30 | X7: 2026-07-01 | Y7: 18:00 | Z7: Hotel | AA7: Dashboard | AB7: Hotel | AC7: Masaje | AD7: Pareja | AE7: 60min | AF7: Relajante | AG7: 45000 | AH7: 45000 | AI7: 0 | AJ7: 0 | AK7: 27000 | AQ7: hPFEtZ3KGh | AR7: Aubrey Hotel Boutique | AS7: PROVIDENCIA | AT7: PROVIDENCIA | AU7: mG3LpIYbKw | AV7: Sergio Rodríguez | AW7: Terminado | AX7: Huéspedes: Andres Valenzuela & Dominique Rousseau. Hab: 206. | AY7: 0 | AZ7: 0 | BB7: https://admin.scape.mx/appointment/YiZcUqymqq
A8: =IFERROR(VLOOKUP(AV8,Nómina!B:E,4,0),"") -> CLAUDIA ESTRELLA ESPINOZA CANIUQUEO | B8: =IFERROR(VLOOKUP(A8,Nómina!E:F,2,0),"") -> 13441148-1 | C8: =IFERROR(Q8,"") -> 22689 | D8: =IFERROR(X8,"") -> 2026-07-01 | E8: =IFERROR(O8,"") -> HOTEL | F8: =IFERROR(AC8,"") -> Masaje | G8: =IFERROR(AD8,"") -> Pareja | H8: =IFERROR(AE8,"") -> 60min | I8: =IFERROR(AF8,"") -> Relajante | J8: =IFERROR(AT8,"") -> PROVIDENCIA | K8: =IFERROR(AX8,"") -> Huéspedes: Andres Valenzuela & Dominique Rousseau. Hab: 206. | L8: =IFERROR(AY8,"") -> 0 | M8: =IFERROR(AZ8,"") -> 0 | N8: =IFERROR(BA8,"") | O8: =+VLOOKUP(Z8,listas!$B:$C,2,0) -> HOTEL | P8: =AG8 -> 45000 | Q8: =IF(AC8="Extra",IF(AF8="Extra de transporte",ROUND(P8/1.19*0.95,0),ROUND(P8/1.19*0.6,0)),ROUND(P8/1.19*0.6,0)) -> 22689 | R8: =MONTH(X8) -> 7 | S8: =DAY(X8) -> 1 | T8: =IF(S8>15,2,1) -> 1 | U8: CL | V8: YiZcUqymqq | W8: 2026-06-30 | X8: 2026-07-01 | Y8: 18:00 | Z8: Hotel | AA8: Dashboard | AB8: Hotel | AC8: Masaje | AD8: Pareja | AE8: 60min | AF8: Relajante | AG8: 45000 | AH8: 45000 | AI8: 0 | AJ8: 0 | AK8: 27000 | AQ8: hPFEtZ3KGh | AR8: Aubrey Hotel Boutique | AS8: PROVIDENCIA | AT8: PROVIDENCIA | AU8: AlqePd7Qkf | AV8: Claudia Espinoza | AW8: Terminado | AX8: Huéspedes: Andres Valenzuela & Dominique Rousseau. Hab: 206. | AY8: 0 | AZ8: 0 | BB8: https://admin.scape.mx/appointment/YiZcUqymqq
A9: =IFERROR(VLOOKUP(AV9,Nómina!B:E,4,0),"") -> DANIELA ANTONIA ALARCON ELIZALDE | B9: =IFERROR(VLOOKUP(A9,Nómina!E:F,2,0),"") -> 15893769-7 | C9: =IFERROR(Q9,"") -> 22689 | D9: =IFERROR(X9,"") -> 2026-07-02 | E9: =IFERROR(O9,"") -> B2C | F9: =IFERROR(AC9,"") -> Masaje | G9: =IFERROR(AD9,"") -> Individual | H9: =IFERROR(AE9,"") -> 60min | I9: =IFERROR(AF9,"") -> Relajante | J9: =IFERROR(AT9,"") -> SANTIAGO DE CHILE | K9: =IFERROR(AX9,"") -> Ninguno | L9: =IFERROR(AY9,"") -> 0 | M9: =IFERROR(AZ9,"") -> 0 | N9: =IFERROR(BA9,"") | O9: =+VLOOKUP(Z9,listas!$B:$C,2,0) -> B2C | P9: =AG9 -> 45000 | Q9: =IF(AC9="Extra",IF(AF9="Extra de transporte",ROUND(P9/1.19*0.95,0),ROUND(P9/1.19*0.6,0)),ROUND(P9/1.19*0.6,0)) -> 22689 | R9: =MONTH(X9) -> 7 | S9: =DAY(X9) -> 2 | T9: =IF(S9>15,2,1) -> 1 | U9: CL | V9: JALwUoNm1p | W9: 2026-07-02 | X9: 2026-07-02 | Y9: 14:00 | Z9: MercadoPago | AA9: App | AB9: B2C | AC9: Masaje | AD9: Individual | AE9: 60min | AF9: Relajante | AG9: 45000 | AH9: 40500 | AI9: 0 | AJ9: 4500 | AK9: 27000 | AL9: REGRESA | AQ9: RquYBkiwrv | AR9: Magdalena Casanueva | AS9: LO BARNECHEA | AT9: SANTIAGO DE CHILE | AU9: s676FCCH2w | AV9: Daniela Alarcón | AW9: Terminado | AX9: Ninguno | AY9: 0 | AZ9: 0 | BB9: https://admin.scape.mx/appointment/JALwUoNm1p
A10: =IFERROR(VLOOKUP(AV10,Nómina!B:E,4,0),"") -> DANIELA ANTONIA ALARCON ELIZALDE | B10: =IFERROR(VLOOKUP(A10,Nómina!E:F,2,0),"") -> 15893769-7 | C10: =IFERROR(Q10,"") -> 5042 | D10: =IFERROR(X10,"") -> 2026-07-02 | E10: =IFERROR(O10,"") -> B2C | F10: =IFERROR(AC10,"") -> Addon | G10: =IFERROR(AD10,"") -> Individual | H10: =IFERROR(AE10,"") -> 15min | I10: =IFERROR(AF10,"") -> Craneofacial | J10: =IFERROR(AT10,"") -> SANTIAGO DE CHILE | K10: =IFERROR(AX10,"") -> Ninguno | L10: =IFERROR(AY10,"") -> 0 | M10: =IFERROR(AZ10,"") -> 0 | N10: =IFERROR(BA10,"") | O10: =+VLOOKUP(Z10,listas!$B:$C,2,0) -> B2C | P10: =AG10 -> 10000 | Q10: =IF(AC10="Extra",IF(AF10="Extra de transporte",ROUND(P10/1.19*0.95,0),ROUND(P10/1.19*0.6,0)),ROUND(P10/1.19*0.6,0)) -> 5042 | R10: =MONTH(X10) -> 7 | S10: =DAY(X10) -> 2 | T10: =IF(S10>15,2,1) -> 1 | U10: CL | V10: JALwUoNm1p | W10: 2026-07-02 | X10: 2026-07-02 | Y10: 14:00 | Z10: MercadoPago | AA10: App | AB10: B2C | AC10: Addon | AD10: Individual | AE10: 15min | AF10: Craneofacial | AG10: 10000 | AH10: 9000 | AI10: 0 | AJ10: 1000 | AK10: 6000 | AL10: REGRESA | AQ10: RquYBkiwrv | AR10: Magdalena Casanueva | AS10: LO BARNECHEA | AT10: SANTIAGO DE CHILE | AU10: s676FCCH2w | AV10: Daniela Alarcón | AW10: Terminado | AX10: Ninguno | AY10: 0 | AZ10: 0 | BB10: https://admin.scape.mx/appointment/JALwUoNm1p
A11: =IFERROR(VLOOKUP(AV11,Nómina!B:E,4,0),"") -> DANIELA ANTONIA ALARCON ELIZALDE | B11: =IFERROR(VLOOKUP(A11,Nómina!E:F,2,0),"") -> 15893769-7 | C11: =IFERROR(Q11,"") -> 3185 | D11: =IFERROR(X11,"") -> 2026-07-02 | E11: =IFERROR(O11,"") -> B2C | F11: =IFERROR(AC11,"") -> Extra | G11: =IFERROR(AD11,"") -> Individual | H11: =IFERROR(AE11,"") -> - | I11: =IFERROR(AF11,"") -> Extra de transporte | J11: =IFERROR(AT11,"") -> SANTIAGO DE CHILE | K11: =IFERROR(AX11,"") -> Ninguno | L11: =IFERROR(AY11,"") -> 0 | M11: =IFERROR(AZ11,"") -> 0 | N11: =IFERROR(BA11,"") | O11: =+VLOOKUP(Z11,listas!$B:$C,2,0) -> B2C | P11: =AG11 -> 3990 | Q11: =IF(AC11="Extra",IF(AF11="Extra de transporte",ROUND(P11/1.19*0.95,0),ROUND(P11/1.19*0.6,0)),ROUND(P11/1.19*0.6,0)) -> 3185 | R11: =MONTH(X11) -> 7 | S11: =DAY(X11) -> 2 | T11: =IF(S11>15,2,1) -> 1 | U11: CL | V11: JALwUoNm1p | W11: 2026-07-02 | X11: 2026-07-02 | Y11: 14:00 | Z11: MercadoPago | AA11: App | AB11: B2C | AC11: Extra | AD11: Individual | AE11: - | AF11: Extra de transporte | AG11: 3990 | AH11: 3990 | AI11: 0 | AJ11: 0 | AK11: 3990 | AL11: REGRESA | AQ11: RquYBkiwrv | AR11: Magdalena Casanueva | AS11: LO BARNECHEA | AT11: SANTIAGO DE CHILE | AU11: s676FCCH2w | AV11: Daniela Alarcón | AW11: Terminado | AX11: Ninguno | AY11: 0 | AZ11: 0 | BB11: https://admin.scape.mx/appointment/JALwUoNm1p
A12: =IFERROR(VLOOKUP(AV12,Nómina!B:E,4,0),"") -> PAMELA VERONICA CID NAVIA | B12: =IFERROR(VLOOKUP(A12,Nómina!E:F,2,0),"") -> 8008360-2 | C12: =IFERROR(Q12,"") -> 22689 | D12: =IFERROR(X12,"") -> 2026-07-03 | E12: =IFERROR(O12,"") -> HOTEL | F12: =IFERROR(AC12,"") -> Masaje | G12: =IFERROR(AD12,"") -> Individual | H12: =IFERROR(AE12,"") -> 60min | I12: =IFERROR(AF12,"") -> Relajante | J12: =IFERROR(AT12,"") -> VITACURA | K12: =IFERROR(AX12,"") -> Habitación 607 | L12: =IFERROR(AY12,"") -> 0 | M12: =IFERROR(AZ12,"") -> 0 | N12: =IFERROR(BA12,"") | O12: =+VLOOKUP(Z12,listas!$B:$C,2,0) -> HOTEL | P12: =AG12 -> 45000 | Q12: =IF(AC12="Extra",IF(AF12="Extra de transporte",ROUND(P12/1.19*0.95,0),ROUND(P12/1.19*0.6,0)),ROUND(P12/1.19*0.6,0)) -> 22689 | R12: =MONTH(X12) -> 7 | S12: =DAY(X12) -> 3 | T12: =IF(S12>15,2,1) -> 1 | U12: CL | V12: DiEDsDnENu | W12: 2026-07-03 | X12: 2026-07-03 | Y12: 14:00 | Z12: Hotel | AA12: Dashboard | AB12: Hotel | AC12: Masaje | AD12: Individual | AE12: 60min | AF12: Relajante | AG12: 45000 | AH12: 45000 | AI12: 0 | AJ12: 0 | AK12: 27000 | AQ12: Bixoh0LizH | AR12: Hotel Pullman Vitacura | AS12: VITACURA | AT12: VITACURA | AU12: K4Rt2FH54k | AV12: Pamela Cid | AW12: Terminado | AX12: Habitación 607 | AY12: 0 | AZ12: 0 | BB12: https://admin.scape.mx/appointment/DiEDsDnENu
A13: =IFERROR(VLOOKUP(AV13,Nómina!B:E,4,0),"") -> PAMELA CONSTANZA HUILITRARO QUEZADA | B13: =IFERROR(VLOOKUP(A13,Nómina!E:F,2,0),"") -> 18881513-8 | C13: =IFERROR(Q13,"") -> 31765 | D13: =IFERROR(X13,"") -> 2026-07-03 | E13: =IFERROR(O13,"") -> HOTEL | F13: =IFERROR(AC13,"") -> Masaje | G13: =IFERROR(AD13,"") -> Individual | H13: =IFERROR(AE13,"") -> 90min | I13: =IFERROR(AF13,"") -> Tejido profundo | J13: =IFERROR(AT13,"") -> SANTIAGO DE CHILE | K13: =IFERROR(AX13,"") -> Huésped: Donald Moore. Hab: 706. | L13: =IFERROR(AY13,"") -> 0 | M13: =IFERROR(AZ13,"") -> 0 | N13: =IFERROR(BA13,"") | O13: =+VLOOKUP(Z13,listas!$B:$C,2,0) -> HOTEL | P13: =AG13 -> 63000 | Q13: =IF(AC13="Extra",IF(AF13="Extra de transporte",ROUND(P13/1.19*0.95,0),ROUND(P13/1.19*0.6,0)),ROUND(P13/1.19*0.6,0)) -> 31765 | R13: =MONTH(X13) -> 7 | S13: =DAY(X13) -> 3 | T13: =IF(S13>15,2,1) -> 1 | U13: CL | V13: OVvsoEIs4l | W13: 2026-07-02 | X13: 2026-07-03 | Y13: 16:00 | Z13: Hotel | AA13: Dashboard | AB13: Hotel | AC13: Masaje | AD13: Individual | AE13: 90min | AF13: Tejido profundo | AG13: 63000 | AH13: 63000 | AI13: 0 | AJ13: 0 | AK13: 37800 | AQ13: dStJ6DrFlA | AR13: Debaines | AS13: SANTIAGO CENTRO | AT13: SANTIAGO DE CHILE | AU13: lHeDnjpSlr | AV13: Pamela Huilitraro Quezada | AW13: Terminado | AX13: Huésped: Donald Moore. Hab: 706. | AY13: 0 | AZ13: 0 | BB13: https://admin.scape.mx/appointment/OVvsoEIs4l
A14: =IFERROR(VLOOKUP(AV14,Nómina!B:E,4,0),"") -> PAMELA CONSTANZA HUILITRARO QUEZADA | B14: =IFERROR(VLOOKUP(A14,Nómina!E:F,2,0),"") -> 18881513-8 | C14: =IFERROR(Q14,"") -> 5042 | D14: =IFERROR(X14,"") -> 2026-07-03 | E14: =IFERROR(O14,"") -> HOTEL | F14: =IFERROR(AC14,"") -> Addon | G14: =IFERROR(AD14,"") -> Individual | H14: =IFERROR(AE14,"") -> 15min | I14: =IFERROR(AF14,"") -> Reflexología | J14: =IFERROR(AT14,"") -> SANTIAGO DE CHILE | K14: =IFERROR(AX14,"") -> Huésped: Donald Moore. Hab: 706. | L14: =IFERROR(AY14,"") -> 0 | M14: =IFERROR(AZ14,"") -> 0 | N14: =IFERROR(BA14,"") | O14: =+VLOOKUP(Z14,listas!$B:$C,2,0) -> HOTEL | P14: =AG14 -> 10000 | Q14: =IF(AC14="Extra",IF(AF14="Extra de transporte",ROUND(P14/1.19*0.95,0),ROUND(P14/1.19*0.6,0)),ROUND(P14/1.19*0.6,0)) -> 5042 | R14: =MONTH(X14) -> 7 | S14: =DAY(X14) -> 3 | T14: =IF(S14>15,2,1) -> 1 | U14: CL | V14: OVvsoEIs4l | W14: 2026-07-02 | X14: 2026-07-03 | Y14: 16:00 | Z14: Hotel | AA14: Dashboard | AB14: Hotel | AC14: Addon | AD14: Individual | AE14: 15min | AF14: Reflexología | AG14: 10000 | AH14: 10000 | AI14: 0 | AJ14: 0 | AK14: 6000 | AQ14: dStJ6DrFlA | AR14: Debaines | AS14: SANTIAGO CENTRO | AT14: SANTIAGO DE CHILE | AU14: lHeDnjpSlr | AV14: Pamela Huilitraro Quezada | AW14: Terminado | AX14: Huésped: Donald Moore. Hab: 706. | AY14: 0 | AZ14: 0 | BB14: https://admin.scape.mx/appointment/OVvsoEIs4l
A15: =IFERROR(VLOOKUP(AV15,Nómina!B:E,4,0),"") -> PAMELA CONSTANZA HUILITRARO QUEZADA | B15: =IFERROR(VLOOKUP(A15,Nómina!E:F,2,0),"") -> 18881513-8 | C15: =IFERROR(Q15,"") -> 5042 | D15: =IFERROR(X15,"") -> 2026-07-03 | E15: =IFERROR(O15,"") -> HOTEL | F15: =IFERROR(AC15,"") -> Addon | G15: =IFERROR(AD15,"") -> Individual | H15: =IFERROR(AE15,"") -> 15min | I15: =IFERROR(AF15,"") -> Craneofacial | J15: =IFERROR(AT15,"") -> SANTIAGO DE CHILE | K15: =IFERROR(AX15,"") -> Huésped: Donald Moore. Hab: 706. | L15: =IFERROR(AY15,"") -> 0 | M15: =IFERROR(AZ15,"") -> 0 | N15: =IFERROR(BA15,"") | O15: =+VLOOKUP(Z15,listas!$B:$C,2,0) -> HOTEL | P15: =AG15 -> 10000 | Q15: =IF(AC15="Extra",IF(AF15="Extra de transporte",ROUND(P15/1.19*0.95,0),ROUND(P15/1.19*0.6,0)),ROUND(P15/1.19*0.6,0)) -> 5042 | R15: =MONTH(X15) -> 7 | S15: =DAY(X15) -> 3 | T15: =IF(S15>15,2,1) -> 1 | U15: CL | V15: OVvsoEIs4l | W15: 2026-07-02 | X15: 2026-07-03 | Y15: 16:00 | Z15: Hotel | AA15: Dashboard | AB15: Hotel | AC15: Addon | AD15: Individual | AE15: 15min | AF15: Craneofacial | AG15: 10000 | AH15: 10000 | AI15: 0 | AJ15: 0 | AK15: 6000 | AQ15: dStJ6DrFlA | AR15: Debaines | AS15: SANTIAGO CENTRO | AT15: SANTIAGO DE CHILE | AU15: lHeDnjpSlr | AV15: Pamela Huilitraro Quezada | AW15: Terminado | AX15: Huésped: Donald Moore. Hab: 706. | AY15: 0 | AZ15: 0 | BB15: https://admin.scape.mx/appointment/OVvsoEIs4l
A16: =IFERROR(VLOOKUP(AV16,Nómina!B:E,4,0),"") -> MACARENA SOFIA GONZALEZ BORQUEZ | B16: =IFERROR(VLOOKUP(A16,Nómina!E:F,2,0),"") -> 17325262-5 | C16: =IFERROR(Q16,"") -> 22689 | D16: =IFERROR(X16,"") -> 2026-07-03 | E16: =IFERROR(O16,"") -> MARKETING | F16: =IFERROR(AC16,"") -> Masaje | G16: =IFERROR(AD16,"") -> Individual | H16: =IFERROR(AE16,"") -> 60min | I16: =IFERROR(AF16,"") -> Relajante | J16: =IFERROR(AT16,"") -> SANTIAGO DE CHILE | K16: =IFERROR(AX16,"") -> Ninguno | L16: =IFERROR(AY16,"") -> 0 | M16: =IFERROR(AZ16,"") -> 0 | N16: =IFERROR(BA16,"") | O16: =+VLOOKUP(Z16,listas!$B:$C,2,0) -> MARKETING | P16: =AG16 -> 45000 | Q16: =IF(AC16="Extra",IF(AF16="Extra de transporte",ROUND(P16/1.19*0.95,0),ROUND(P16/1.19*0.6,0)),ROUND(P16/1.19*0.6,0)) -> 22689 | R16: =MONTH(X16) -> 7 | S16: =DAY(X16) -> 3 | T16: =IF(S16>15,2,1) -> 1 | U16: CL | V16: JMMJCArMNY | W16: 2026-07-01 | X16: 2026-07-03 | Y16: 18:00 | Z16: Marketing | AA16: Dashboard | AB16: Marketing | AC16: Masaje | AD16: Individual | AE16: 60min | AF16: Relajante | AG16: 45000 | AH16: 0 | AI16: 0 | AJ16: 0 | AK16: 27000 | AQ16: ZxKbestgvA | AR16: Diana Bolocco Fonck | AS16: LO BARNECHEA | AT16: SANTIAGO DE CHILE | AU16: KaasnzolTJ | AV16: Maku González Borquez | AW16: Terminado | AX16: Ninguno | AY16: 0 | AZ16: 0 | BB16: https://admin.scape.mx/appointment/JMMJCArMNY
A17: =IFERROR(VLOOKUP(AV17,Nómina!B:E,4,0),"") -> MACARENA SOFIA GONZALEZ BORQUEZ | B17: =IFERROR(VLOOKUP(A17,Nómina!E:F,2,0),"") -> 17325262-5 | C17: =IFERROR(Q17,"") -> 3185 | D17: =IFERROR(X17,"") -> 2026-07-03 | E17: =IFERROR(O17,"") -> MARKETING | F17: =IFERROR(AC17,"") -> Extra | G17: =IFERROR(AD17,"") -> Individual | H17: =IFERROR(AE17,"") -> - | I17: =IFERROR(AF17,"") -> Extra de transporte | J17: =IFERROR(AT17,"") -> SANTIAGO DE CHILE | K17: =IFERROR(AX17,"") -> Ninguno | L17: =IFERROR(AY17,"") -> 0 | M17: =IFERROR(AZ17,"") -> 0 | N17: =IFERROR(BA17,"") | O17: =+VLOOKUP(Z17,listas!$B:$C,2,0) -> MARKETING | P17: =AG17 -> 3990 | Q17: =IF(AC17="Extra",IF(AF17="Extra de transporte",ROUND(P17/1.19*0.95,0),ROUND(P17/1.19*0.6,0)),ROUND(P17/1.19*0.6,0)) -> 3185 | R17: =MONTH(X17) -> 7 | S17: =DAY(X17) -> 3 | T17: =IF(S17>15,2,1) -> 1 | U17: CL | V17: JMMJCArMNY | W17: 2026-07-01 | X17: 2026-07-03 | Y17: 18:00 | Z17: Marketing | AA17: Dashboard | AB17: Marketing | AC17: Extra | AD17: Individual | AE17: - | AF17: Extra de transporte | AG17: 3990 | AH17: 3990 | AI17: 0 | AJ17: 0 | AK17: 3990 | AQ17: ZxKbestgvA | AR17: Diana Bolocco Fonck | AS17: LO BARNECHEA | AT17: SANTIAGO DE CHILE | AU17: KaasnzolTJ | AV17: Maku González Borquez | AW17: Terminado | AX17: Ninguno | AY17: 0 | AZ17: 0 | BB17: https://admin.scape.mx/appointment/JMMJCArMNY
A18: =IFERROR(VLOOKUP(AV18,Nómina!B:E,4,0),"") -> CLAUDIA ESTRELLA ESPINOZA CANIUQUEO | B18: =IFERROR(VLOOKUP(A18,Nómina!E:F,2,0),"") -> 13441148-1 | C18: =IFERROR(Q18,"") -> 31765 | D18: =IFERROR(X18,"") -> 2026-07-03 | E18: =IFERROR(O18,"") -> B2C | F18: =IFERROR(AC18,"") -> Masaje | G18: =IFERROR(AD18,"") -> Individual | H18: =IFERROR(AE18,"") -> 90min | I18: =IFERROR(AF18,"") -> Tejido profundo | J18: =IFERROR(AT18,"") -> SANTIAGO DE CHILE | K18: =IFERROR(AX18,"") -> se libera por enfermedad viral | L18: =IFERROR(AY18,"") -> 4 | M18: =IFERROR(AZ18,"") -> 5 | N18: =IFERROR(BA18,"") | O18: =+VLOOKUP(Z18,listas!$B:$C,2,0) -> B2C | P18: =AG18 -> 63000 | Q18: =IF(AC18="Extra",IF(AF18="Extra de transporte",ROUND(P18/1.19*0.95,0),ROUND(P18/1.19*0.6,0)),ROUND(P18/1.19*0.6,0)) -> 31765 | R18: =MONTH(X18) -> 7 | S18: =DAY(X18) -> 3 | T18: =IF(S18>15,2,1) -> 1 | U18: CL | V18: qSdRlkTh8N | W18: 2026-06-26 | X18: 2026-07-03 | Y18: 19:00 | Z18: MercadoPago | AA18: App | AB18: B2C | AC18: Masaje | AD18: Individual | AE18: 90min | AF18: Tejido profundo | AG18: 63000 | AH18: 63000 | AI18: 0 | AJ18: 0 | AK18: 37800 | AQ18: 44JFbPXfzj | AR18: María Angélica Cossio Jara | AS18: SANTIAGO CENTRO | AT18: SANTIAGO DE CHILE | AU18: AlqePd7Qkf | AV18: Claudia Espinoza | AW18: Terminado | AX18: se libera por enfermedad viral | AY18: 4 | AZ18: 5 | BB18: https://admin.scape.mx/appointment/qSdRlkTh8N
A19: =IFERROR(VLOOKUP(AV19,Nómina!B:E,4,0),"") -> CLAUDIA ESTRELLA ESPINOZA CANIUQUEO | B19: =IFERROR(VLOOKUP(A19,Nómina!E:F,2,0),"") -> 13441148-1 | C19: =IFERROR(Q19,"") -> 6050 | D19: =IFERROR(X19,"") -> 2026-07-03 | E19: =IFERROR(O19,"") -> B2C | F19: =IFERROR(AC19,"") -> Addon | G19: =IFERROR(AD19,"") -> Individual | H19: =IFERROR(AE19,"") -> 15min | I19: =IFERROR(AF19,"") -> Yoga Facial | J19: =IFERROR(AT19,"") -> SANTIAGO DE CHILE | K19: =IFERROR(AX19,"") -> se libera por enfermedad viral | L19: =IFERROR(AY19,"") -> 4 | M19: =IFERROR(AZ19,"") -> 5 | N19: =IFERROR(BA19,"") | O19: =+VLOOKUP(Z19,listas!$B:$C,2,0) -> B2C | P19: =AG19 -> 12000 | Q19: =IF(AC19="Extra",IF(AF19="Extra de transporte",ROUND(P19/1.19*0.95,0),ROUND(P19/1.19*0.6,0)),ROUND(P19/1.19*0.6,0)) -> 6050 | R19: =MONTH(X19) -> 7 | S19: =DAY(X19) -> 3 | T19: =IF(S19>15,2,1) -> 1 | U19: CL | V19: qSdRlkTh8N | W19: 2026-06-26 | X19: 2026-07-03 | Y19: 19:00 | Z19: MercadoPago | AA19: App | AB19: B2C | AC19: Addon | AD19: Individual | AE19: 15min | AF19: Yoga Facial | AG19: 12000 | AH19: 12000 | AI19: 0 | AJ19: 0 | AK19: 7200 | AQ19: 44JFbPXfzj | AR19: María Angélica Cossio Jara | AS19: SANTIAGO CENTRO | AT19: SANTIAGO DE CHILE | AU19: AlqePd7Qkf | AV19: Claudia Espinoza | AW19: Terminado | AX19: se libera por enfermedad viral | AY19: 4 | AZ19: 5 | BB19: https://admin.scape.mx/appointment/qSdRlkTh8N
A20: =IFERROR(VLOOKUP(AV20,Nómina!B:E,4,0),"") -> CLAUDIA ESTRELLA ESPINOZA CANIUQUEO | B20: =IFERROR(VLOOKUP(A20,Nómina!E:F,2,0),"") -> 13441148-1 | C20: =IFERROR(Q20,"") -> 2521 | D20: =IFERROR(X20,"") -> 2026-07-03 | E20: =IFERROR(O20,"") -> B2C | F20: =IFERROR(AC20,"") -> Extra | G20: =IFERROR(AD20,"") -> Individual | H20: =IFERROR(AE20,"") -> - | I20: =IFERROR(AF20,"") -> Extra por festivo o fin de semana | J20: =IFERROR(AT20,"") -> SANTIAGO DE CHILE | K20: =IFERROR(AX20,"") -> se libera por enfermedad viral | L20: =IFERROR(AY20,"") -> 4 | M20: =IFERROR(AZ20,"") -> 5 | N20: =IFERROR(BA20,"") | O20: =+VLOOKUP(Z20,listas!$B:$C,2,0) -> B2C | P20: =AG20 -> 5000 | Q20: =IF(AC20="Extra",IF(AF20="Extra de transporte",ROUND(P20/1.19*0.95,0),ROUND(P20/1.19*0.6,0)),ROUND(P20/1.19*0.6,0)) -> 2521 | R20: =MONTH(X20) -> 7 | S20: =DAY(X20) -> 3 | T20: =IF(S20>15,2,1) -> 1 | U20: CL | V20: qSdRlkTh8N | W20: 2026-06-26 | X20: 2026-07-03 | Y20: 19:00 | Z20: MercadoPago | AA20: App | AB20: B2C | AC20: Extra | AD20: Individual | AE20: - | AF20: Extra por festivo o fin de semana | AG20: 5000 | AH20: 5000 | AI20: 0 | AJ20: 0 | AK20: 5000 | AQ20: 44JFbPXfzj | AR20: María Angélica Cossio Jara | AS20: SANTIAGO CENTRO | AT20: SANTIAGO DE CHILE | AU20: AlqePd7Qkf | AV20: Claudia Espinoza | AW20: Terminado | AX20: se libera por enfermedad viral | AY20: 4 | AZ20: 5 | BB20: https://admin.scape.mx/appointment/qSdRlkTh8N
A21: =IFERROR(VLOOKUP(AV21,Nómina!B:E,4,0),"") -> GENESIS VALENTINA SALAZAR GUEVARA | B21: =IFERROR(VLOOKUP(A21,Nómina!E:F,2,0),"") -> 27828546-4 | C21: =IFERROR(Q21,"") -> 22689 | D21: =IFERROR(X21,"") -> 2026-07-03 | E21: =IFERROR(O21,"") -> B2C | F21: =IFERROR(AC21,"") -> Masaje | G21: =IFERROR(AD21,"") -> Individual | H21: =IFERROR(AE21,"") -> 60min | I21: =IFERROR(AF21,"") -> Tejido profundo | J21: =IFERROR(AT21,"") -> LAS CONDES | K21: =IFERROR(AX21,"") -> Ninguno | L21: =IFERROR(AY21,"") -> 0 | M21: =IFERROR(AZ21,"") -> 0 | N21: =IFERROR(BA21,"") | O21: =+VLOOKUP(Z21,listas!$B:$C,2,0) -> B2C | P21: =AG21 -> 45000 | Q21: =IF(AC21="Extra",IF(AF21="Extra de transporte",ROUND(P21/1.19*0.95,0),ROUND(P21/1.19*0.6,0)),ROUND(P21/1.19*0.6,0)) -> 22689 | R21: =MONTH(X21) -> 7 | S21: =DAY(X21) -> 3 | T21: =IF(S21>15,2,1) -> 1 | U21: CL | V21: he0VwsjaVz | W21: 2026-07-02 | X21: 2026-07-03 | Y21: 19:00 | Z21: MercadoPago | AA21: App | AB21: B2C | AC21: Masaje | AD21: Individual | AE21: 60min | AF21: Tejido profundo | AG21: 45000 | AH21: 45000 | AI21: 0 | AJ21: 0 | AK21: 27000 | AQ21: nBknYlqovO | AR21: Francisca Velasco Guzmán | AS21: LAS CONDES | AT21: LAS CONDES | AU21: TcqJ1GTAe6 | AV21: Valentina Salazar Guevara | AW21: Terminado | AX21: Ninguno | AY21: 0 | AZ21: 0 | BB21: https://admin.scape.mx/appointment/he0VwsjaVz
A22: =IFERROR(VLOOKUP(AV22,Nómina!B:E,4,0),"") -> GENESIS VALENTINA SALAZAR GUEVARA | B22: =IFERROR(VLOOKUP(A22,Nómina!E:F,2,0),"") -> 27828546-4 | C22: =IFERROR(Q22,"") -> 5042 | D22: =IFERROR(X22,"") -> 2026-07-03 | E22: =IFERROR(O22,"") -> B2C | F22: =IFERROR(AC22,"") -> Addon | G22: =IFERROR(AD22,"") -> Individual | H22: =IFERROR(AE22,"") -> 15min | I22: =IFERROR(AF22,"") -> Masaje Tiempo Extra | J22: =IFERROR(AT22,"") -> LAS CONDES | K22: =IFERROR(AX22,"") -> Ninguno | L22: =IFERROR(AY22,"") -> 0 | M22: =IFERROR(AZ22,"") -> 0 | N22: =IFERROR(BA22,"") | O22: =+VLOOKUP(Z22,listas!$B:$C,2,0) -> B2C | P22: =AG22 -> 10000 | Q22: =IF(AC22="Extra",IF(AF22="Extra de transporte",ROUND(P22/1.19*0.95,0),ROUND(P22/1.19*0.6,0)),ROUND(P22/1.19*0.6,0)) -> 5042 | R22: =MONTH(X22) -> 7 | S22: =DAY(X22) -> 3 | T22: =IF(S22>15,2,1) -> 1 | U22: CL | V22: he0VwsjaVz | W22: 2026-07-02 | X22: 2026-07-03 | Y22: 19:00 | Z22: MercadoPago | AA22: App | AB22: B2C | AC22: Addon | AD22: Individual | AE22: 15min | AF22: Masaje Tiempo Extra | AG22: 10000 | AH22: 10000 | AI22: 0 | AJ22: 0 | AK22: 6000 | AQ22: nBknYlqovO | AR22: Francisca Velasco Guzmán | AS22: LAS CONDES | AT22: LAS CONDES | AU22: TcqJ1GTAe6 | AV22: Valentina Salazar Guevara | AW22: Terminado | AX22: Ninguno | AY22: 0 | AZ22: 0 | BB22: https://admin.scape.mx/appointment/he0VwsjaVz
A23: =IFERROR(VLOOKUP(AV23,Nómina!B:E,4,0),"") -> MARIA ELIANA BENAVIDES HIGUERA | B23: =IFERROR(VLOOKUP(A23,Nómina!E:F,2,0),"") -> 15168787-3 | C23: =IFERROR(Q23,"") -> 22689 | D23: =IFERROR(X23,"") -> 2026-07-03 | E23: =IFERROR(O23,"") -> HOTEL | F23: =IFERROR(AC23,"") -> Masaje | G23: =IFERROR(AD23,"") -> Individual | H23: =IFERROR(AE23,"") -> 60min | I23: =IFERROR(AF23,"") -> Tejido profundo | J23: =IFERROR(AT23,"") -> LAS CONDES | K23: =IFERROR(AX23,"") -> Huésped: Tobias Musonda. Hab: 1012. Solicita: Benjamín Suazo. | L23: =IFERROR(AY23,"") -> 0 | M23: =IFERROR(AZ23,"") -> 0 | N23: =IFERROR(BA23,"") | O23: =+VLOOKUP(Z23,listas!$B:$C,2,0) -> HOTEL | P23: =AG23 -> 45000 | Q23: =IF(AC23="Extra",IF(AF23="Extra de transporte",ROUND(P23/1.19*0.95,0),ROUND(P23/1.19*0.6,0)),ROUND(P23/1.19*0.6,0)) -> 22689 | R23: =MONTH(X23) -> 7 | S23: =DAY(X23) -> 3 | T23: =IF(S23>15,2,1) -> 1 | U23: CL | V23: cXSA6nSHl9 | W23: 2026-07-03 | X23: 2026-07-03 | Y23: 19:00 | Z23: Hotel | AA23: Dashboard | AB23: Hotel | AC23: Masaje | AD23: Individual | AE23: 60min | AF23: Tejido profundo | AG23: 45000 | AH23: 45000 | AI23: 0 | AJ23: 0 | AK23: 27000 | AQ23: 8LOSg5cHsn | AR23: Doubletree Las Condes | AS23: LAS CONDES | AT23: LAS CONDES | AU23: OBiYJqDd10 | AV23: Eliana Benavides | AW23: Terminado | AX23: Huésped: Tobias Musonda. Hab: 1012. Solicita: Benjamín Suazo. | AY23: 0 | AZ23: 0 | BB23: https://admin.scape.mx/appointment/cXSA6nSHl9
... A57: =IFERROR(VLOOKUP(AV57,Nómina!B:E,4,0),"") -> GENESIS VALENTINA SALAZAR GUEVARA | B57: =IFERROR(VLOOKUP(A57,Nómina!E:F,2,0),"") -> 27828546-4 | C57: =IFERROR(Q57,"") -> 22689 | D57: =IFERROR(X57,"") -> 2026-07-06 | E57: =IFERROR(O57,"") -> HOTEL | F57: =IFERROR(AC57,"") -> Masaje | G57: =IFERROR(AD57,"") -> Individual | H57: =IFERROR(AE57,"") -> 60min | I57: =IFERROR(AF57,"") -> Tejido profundo | J57: =IFERROR(AT57,"") -> VITACURA | K57: =IFERROR(AX57,"") -> Habitación 406 | L57: =IFERROR(AY57,"") -> 0 | M57: =IFERROR(AZ57,"") -> 0 | N57: =IFERROR(BA57,"") | O57: =+VLOOKUP(Z57,listas!$B:$C,2,0) -> HOTEL | P57: =AG57 -> 45000 | Q57: =IF(AC57="Extra",IF(AF57="Extra de transporte",ROUND(P57/1.19*0.95,0),ROUND(P57/1.19*0.6,0)),ROUND(P57/1.19*0.6,0)) -> 22689 | R57: =MONTH(X57) -> 7 | S57: =DAY(X57) -> 6 | T57: =IF(S57>15,2,1) -> 1 | U57: CL | V57: BP7Y3AcaKp | W57: 2026-07-06 | X57: 2026-07-06 | Y57: 17:30 | Z57: Hotel | AA57: Dashboard | AB57: Hotel | AC57: Masaje | AD57: Individual | AE57: 60min | AF57: Tejido profundo | AG57: 45000 | AH57: 45000 | AI57: 0 | AJ57: 0 | AK57: 27000 | AQ57: OLPG5ZHFBh | AR57: Bidasoa | AS57: VITACURA | AT57: VITACURA | AU57: TcqJ1GTAe6 | AV57: Valentina Salazar Guevara | AW57: Terminado | AX57: Habitación 406 | AY57: 0 | AZ57: 0 | BB57: https://admin.scape.mx/appointment/BP7Y3AcaKp
A58: =IFERROR(VLOOKUP(AV58,Nómina!B:E,4,0),"") -> GENESIS DANIELA PIMENTEL HERRERA | B58: =IFERROR(VLOOKUP(A58,Nómina!E:F,2,0),"") -> 26598096-1 | C58: =IFERROR(Q58,"") -> 22689 | D58: =IFERROR(X58,"") -> 2026-07-06 | E58: =IFERROR(O58,"") -> B2C | F58: =IFERROR(AC58,"") -> Masaje | G58: =IFERROR(AD58,"") -> Individual | H58: =IFERROR(AE58,"") -> 60min | I58: =IFERROR(AF58,"") -> Deportivo | J58: =IFERROR(AT58,"") -> VITACURA | K58: =IFERROR(AX58,"") -> Ninguno | L58: =IFERROR(AY58,"") -> 5 | M58: =IFERROR(AZ58,"") -> 5 | N58: =IFERROR(BA58,"") -> Me encantó mi terapeuta Génesis. Espectacular el masaje y le dio énfasis a lo que yo necesitaba. | O58: =+VLOOKUP(Z58,listas!$B:$C,2,0) -> B2C | P58: =AG58 -> 45000 | Q58: =IF(AC58="Extra",IF(AF58="Extra de transporte",ROUND(P58/1.19*0.95,0),ROUND(P58/1.19*0.6,0)),ROUND(P58/1.19*0.6,0)) -> 22689 | R58: =MONTH(X58) -> 7 | S58: =DAY(X58) -> 6 | T58: =IF(S58>15,2,1) -> 1 | U58: CL | V58: BzikGz0h23 | W58: 2026-07-06 | X58: 2026-07-06 | Y58: 21:00 | Z58: MercadoPago | AA58: App | AB58: B2C | AC58: Masaje | AD58: Individual | AE58: 60min | AF58: Deportivo | AG58: 45000 | AH58: 45000 | AI58: 0 | AJ58: 0 | AK58: 27000 | AQ58: 0Pd11TFENJ | AR58: Camila Echeverria | AS58: VITACURA | AT58: VITACURA | AU58: WQqvAzSfjW | AV58: Génesis Pimentel | AW58: Terminado | AX58: Ninguno | AY58: 5 | AZ58: 5 | BA58: Me encantó mi terapeuta Génesis. Espectacular el masaje y le dio énfasis a lo que yo necesitaba. | BB58: https://admin.scape.mx/appointment/BzikGz0h23
A59: =IFERROR(VLOOKUP(AV59,Nómina!B:E,4,0),"") -> GENESIS DANIELA PIMENTEL HERRERA | B59: =IFERROR(VLOOKUP(A59,Nómina!E:F,2,0),"") -> 26598096-1 | C59: =IFERROR(Q59,"") -> 31765 | D59: =IFERROR(X59,"") -> 2026-07-07 | E59: =IFERROR(O59,"") -> B2C | F59: =IFERROR(AC59,"") -> Masaje | G59: =IFERROR(AD59,"") -> Individual | H59: =IFERROR(AE59,"") -> 90min | I59: =IFERROR(AF59,"") -> Tejido profundo | J59: =IFERROR(AT59,"") -> PROVIDENCIA | K59: =IFERROR(AX59,"") -> Ninguno | L59: =IFERROR(AY59,"") -> 0 | M59: =IFERROR(AZ59,"") -> 0 | N59: =IFERROR(BA59,"") | O59: =+VLOOKUP(Z59,listas!$B:$C,2,0) -> B2C | P59: =AG59 -> 63000 | Q59: =IF(AC59="Extra",IF(AF59="Extra de transporte",ROUND(P59/1.19*0.95,0),ROUND(P59/1.19*0.6,0)),ROUND(P59/1.19*0.6,0)) -> 31765 | R59: =MONTH(X59) -> 7 | S59: =DAY(X59) -> 7 | T59: =IF(S59>15,2,1) -> 1 | U59: CL | V59: 1zZm6yVbHg | W59: 2026-07-07 | X59: 2026-07-07 | Y59: 20:00 | Z59: MercadoPago | AA59: App | AB59: B2C | AC59: Masaje | AD59: Individual | AE59: 90min | AF59: Tejido profundo | AG59: 63000 | AH59: 63000 | AI59: 0 | AJ59: 0 | AK59: 37800 | AQ59: 4oDojB1O4e | AR59: luz maria trivelli | AS59: PROVIDENCIA | AT59: PROVIDENCIA | AU59: WQqvAzSfjW | AV59: Génesis Pimentel | AW59: Terminado | AX59: Ninguno | AY59: 0 | AZ59: 0 | BB59: https://admin.scape.mx/appointment/1zZm6yVbHg
A60: =IFERROR(VLOOKUP(AV60,Nómina!B:E,4,0),"") -> DANIELA ANTONIA ALARCON ELIZALDE | B60: =IFERROR(VLOOKUP(A60,Nómina!E:F,2,0),"") -> 15893769-7 | C60: =IFERROR(Q60,"") -> 22689 | D60: =IFERROR(X60,"") -> 2026-07-07 | E60: =IFERROR(O60,"") -> B2C | F60: =IFERROR(AC60,"") -> Masaje | G60: =IFERROR(AD60,"") -> Individual | H60: =IFERROR(AE60,"") -> 60min | I60: =IFERROR(AF60,"") -> Relajante | J60: =IFERROR(AT60,"") -> LAS CONDES | K60: =IFERROR(AX60,"") -> Ninguno | L60: =IFERROR(AY60,"") -> 0 | M60: =IFERROR(AZ60,"") -> 0 | N60: =IFERROR(BA60,"") | O60: =+VLOOKUP(Z60,listas!$B:$C,2,0) -> B2C | P60: =AG60 -> 45000 | Q60: =IF(AC60="Extra",IF(AF60="Extra de transporte",ROUND(P60/1.19*0.95,0),ROUND(P60/1.19*0.6,0)),ROUND(P60/1.19*0.6,0)) -> 22689 | R60: =MONTH(X60) -> 7 | S60: =DAY(X60) -> 7 | T60: =IF(S60>15,2,1) -> 1 | U60: CL | V60: UFgL1FmQrC | W60: 2026-07-07 | X60: 2026-07-07 | Y60: 20:30 | Z60: MercadoPago | AA60: App | AB60: B2C | AC60: Masaje | AD60: Individual | AE60: 60min | AF60: Relajante | AG60: 45000 | AH60: 40500 | AI60: 0 | AJ60: 4500 | AK60: 27000 | AL60: soyte10 | AQ60: s1TG7FOQXT | AR60: Catalina Fernandez Demaria | AS60: LAS CONDES | AT60: LAS CONDES | AU60: s676FCCH2w | AV60: Daniela Alarcón | AW60: Terminado | AX60: Ninguno | AY60: 0 | AZ60: 0 | BB60: https://admin.scape.mx/appointment/UFgL1FmQrC
A61: =IFERROR(VLOOKUP(AV61,Nómina!B:E,4,0),"") -> DANIELA ANTONIA ALARCON ELIZALDE | B61: =IFERROR(VLOOKUP(A61,Nómina!E:F,2,0),"") -> 15893769-7 | C61: =IFERROR(Q61,"") -> 10084 | D61: =IFERROR(X61,"") -> 2026-07-07 | E61: =IFERROR(O61,"") -> B2C | F61: =IFERROR(AC61,"") -> Addon | G61: =IFERROR(AD61,"") -> Individual | H61: =IFERROR(AE61,"") -> 30min | I61: =IFERROR(AF61,"") -> Drenaje Linfático | J61: =IFERROR(AT61,"") -> LAS CONDES | K61: =IFERROR(AX61,"") -> Ninguno | L61: =IFERROR(AY61,"") -> 0 | M61: =IFERROR(AZ61,"") -> 0 | N61: =IFERROR(BA61,"") | O61: =+VLOOKUP(Z61,listas!$B:$C,2,0) -> B2C | P61: =AG61 -> 20000 | Q61: =IF(AC61="Extra",IF(AF61="Extra de transporte",ROUND(P61/1.19*0.95,0),ROUND(P61/1.19*0.6,0)),ROUND(P61/1.19*0.6,0)) -> 10084 | R61: =MONTH(X61) -> 7 | S61: =DAY(X61) -> 7 | T61: =IF(S61>15,2,1) -> 1 | U61: CL | V61: UFgL1FmQrC | W61: 2026-07-07 | X61: 2026-07-07 | Y61: 20:30 | Z61: MercadoPago | AA61: App | AB61: B2C | AC61: Addon | AD61: Individual | AE61: 30min | AF61: Drenaje Linfático | AG61: 20000 | AH61: 18000 | AI61: 0 | AJ61: 2000 | AK61: 9720 | AL61: soyte10 | AQ61: s1TG7FOQXT | AR61: Catalina Fernandez Demaria | AS61: LAS CONDES | AT61: LAS CONDES | AU61: s676FCCH2w | AV61: Daniela Alarcón | AW61: Terminado | AX61: Ninguno | AY61: 0 | AZ61: 0 | BB61: https://admin.scape.mx/appointment/UFgL1FmQrC
A62: =IFERROR(VLOOKUP(AV62,Nómina!B:E,4,0),"") -> GENESIS DANIELA PIMENTEL HERRERA | B62: =IFERROR(VLOOKUP(A62,Nómina!E:F,2,0),"") -> 26598096-1 | C62: =IFERROR(Q62,"") -> 31765 | D62: =IFERROR(X62,"") -> 2026-07-08 | E62: =IFERROR(O62,"") -> HOTEL | F62: =IFERROR(AC62,"") -> Masaje | G62: =IFERROR(AD62,"") -> Individual | H62: =IFERROR(AE62,"") -> 90min | I62: =IFERROR(AF62,"") -> Tejido profundo | J62: =IFERROR(AT62,"") -> SANTIAGO DE CHILE | K62: =IFERROR(AX62,"") -> Nombre huésped: Mordechai Walder Número de habitación: 905 | L62: =IFERROR(AY62,"") -> 0 | M62: =IFERROR(AZ62,"") -> 0 | N62: =IFERROR(BA62,"") | O62: =+VLOOKUP(Z62,listas!$B:$C,2,0) -> HOTEL | P62: =AG62 -> 63000 | Q62: =IF(AC62="Extra",IF(AF62="Extra de transporte",ROUND(P62/1.19*0.95,0),ROUND(P62/1.19*0.6,0)),ROUND(P62/1.19*0.6,0)) -> 31765 | R62: =MONTH(X62) -> 7 | S62: =DAY(X62) -> 8 | T62: =IF(S62>15,2,1) -> 1 | U62: CL | V62: ok1hoQ8uxM | W62: 2026-07-07 | X62: 2026-07-08 | Y62: 10:00 | Z62: Hotel | AA62: Dashboard | AB62: Hotel | AC62: Masaje | AD62: Individual | AE62: 90min | AF62: Tejido profundo | AG62: 63000 | AH62: 63000 | AI62: 0 | AJ62: 0 | AK62: 37800 | AQ62: dStJ6DrFlA | AR62: Debaines | AS62: SANTIAGO CENTRO | AT62: SANTIAGO DE CHILE | AU62: WQqvAzSfjW | AV62: Génesis Pimentel | AW62: Terminado | AX62: Nombre huésped: Mordechai Walder Número de habitación: 905 | AY62: 0 | AZ62: 0 | BB62: https://admin.scape.mx/appointment/ok1hoQ8uxM
A63: =IFERROR(VLOOKUP(AV63,Nómina!B:E,4,0),"") -> GENESIS DANIELA PIMENTEL HERRERA | B63: =IFERROR(VLOOKUP(A63,Nómina!E:F,2,0),"") -> 26598096-1 | C63: =IFERROR(Q63,"") -> 5042 | D63: =IFERROR(X63,"") -> 2026-07-08 | E63: =IFERROR(O63,"") -> HOTEL | F63: =IFERROR(AC63,"") -> Addon | G63: =IFERROR(AD63,"") -> Individual | H63: =IFERROR(AE63,"") -> 15min | I63: =IFERROR(AF63,"") -> Craneofacial | J63: =IFERROR(AT63,"") -> SANTIAGO DE CHILE | K63: =IFERROR(AX63,"") -> Nombre huésped: Mordechai Walder Número de habitación: 905 | L63: =IFERROR(AY63,"") -> 0 | M63: =IFERROR(AZ63,"") -> 0 | N63: =IFERROR(BA63,"") | O63: =+VLOOKUP(Z63,listas!$B:$C,2,0) -> HOTEL | P63: =AG63 -> 10000 | Q63: =IF(AC63="Extra",IF(AF63="Extra de transporte",ROUND(P63/1.19*0.95,0),ROUND(P63/1.19*0.6,0)),ROUND(P63/1.19*0.6,0)) -> 5042 | R63: =MONTH(X63) -> 7 | S63: =DAY(X63) -> 8 | T63: =IF(S63>15,2,1) -> 1 | U63: CL | V63: ok1hoQ8uxM | W63: 2026-07-07 | X63: 2026-07-08 | Y63: 10:00 | Z63: Hotel | AA63: Dashboard | AB63: Hotel | AC63: Addon | AD63: Individual | AE63: 15min | AF63: Craneofacial | AG63: 10000 | AH63: 10000 | AI63: 0 | AJ63: 0 | AK63: 6000 | AQ63: dStJ6DrFlA | AR63: Debaines | AS63: SANTIAGO CENTRO | AT63: SANTIAGO DE CHILE | AU63: WQqvAzSfjW | AV63: Génesis Pimentel | AW63: Terminado | AX63: Nombre huésped: Mordechai Walder Número de habitación: 905 | AY63: 0 | AZ63: 0 | BB63: https://admin.scape.mx/appointment/ok1hoQ8uxM
A64: =IFERROR(VLOOKUP(AV64,Nómina!B:E,4,0),"") -> GENESIS DANIELA PIMENTEL HERRERA | B64: =IFERROR(VLOOKUP(A64,Nómina!E:F,2,0),"") -> 26598096-1 | C64: =IFERROR(Q64,"") -> 6050 | D64: =IFERROR(X64,"") -> 2026-07-08 | E64: =IFERROR(O64,"") -> HOTEL | F64: =IFERROR(AC64,"") -> Addon | G64: =IFERROR(AD64,"") -> Individual | H64: =IFERROR(AE64,"") -> 15min | I64: =IFERROR(AF64,"") -> Yoga Facial | J64: =IFERROR(AT64,"") -> SANTIAGO DE CHILE | K64: =IFERROR(AX64,"") -> Nombre huésped: Mordechai Walder Número de habitación: 905 | L64: =IFERROR(AY64,"") -> 0 | M64: =IFERROR(AZ64,"") -> 0 | N64: =IFERROR(BA64,"") | O64: =+VLOOKUP(Z64,listas!$B:$C,2,0) -> HOTEL | P64: =AG64 -> 12000 | Q64: =IF(AC64="Extra",IF(AF64="Extra de transporte",ROUND(P64/1.19*0.95,0),ROUND(P64/1.19*0.6,0)),ROUND(P64/1.19*0.6,0)) -> 6050 | R64: =MONTH(X64) -> 7 | S64: =DAY(X64) -> 8 | T64: =IF(S64>15,2,1) -> 1 | U64: CL | V64: ok1hoQ8uxM | W64: 2026-07-07 | X64: 2026-07-08 | Y64: 10:00 | Z64: Hotel | AA64: Dashboard | AB64: Hotel | AC64: Addon | AD64: Individual | AE64: 15min | AF64: Yoga Facial | AG64: 12000 | AH64: 12000 | AI64: 0 | AJ64: 0 | AK64: 7200 | AQ64: dStJ6DrFlA | AR64: Debaines | AS64: SANTIAGO CENTRO | AT64: SANTIAGO DE CHILE | AU64: WQqvAzSfjW | AV64: Génesis Pimentel | AW64: Terminado | AX64: Nombre huésped: Mordechai Walder Número de habitación: 905 | AY64: 0 | AZ64: 0 | BB64: https://admin.scape.mx/appointment/ok1hoQ8uxM
A65: =IFERROR(VLOOKUP(AV65,Nómina!B:E,4,0),"") -> MARIA MAGDALENA CASTRO MORGADO | B65: =IFERROR(VLOOKUP(A65,Nómina!E:F,2,0),"") -> 13335240-6 | C65: =IFERROR(Q65,"") -> 22689 | D65: =IFERROR(X65,"") -> 2026-07-08 | E65: =IFERROR(O65,"") -> B2C | F65: =IFERROR(AC65,"") -> Masaje | G65: =IFERROR(AD65,"") -> Individual | H65: =IFERROR(AE65,"") -> 60min | I65: =IFERROR(AF65,"") -> Prenatal | J65: =IFERROR(AT65,"") -> CHICUREO | K65: =IFERROR(AX65,"") -> Ninguno | L65: =IFERROR(AY65,"") -> 5 | M65: =IFERROR(AZ65,"") -> 5 | N65: =IFERROR(BA65,"") -> Excelente!! Me encantó, nada que decir de Magdalena. Gracias | O65: =+VLOOKUP(Z65,listas!$B:$C,2,0) -> B2C | P65: =AG65 -> 45000 | Q65: =IF(AC65="Extra",IF(AF65="Extra de transporte",ROUND(P65/1.19*0.95,0),ROUND(P65/1.19*0.6,0)),ROUND(P65/1.19*0.6,0)) -> 22689 | R65: =MONTH(X65) -> 7 | S65: =DAY(X65) -> 8 | T65: =IF(S65>15,2,1) -> 1 | U65: CL | V65: 403utqoTwQ | W65: 2026-07-07 | X65: 2026-07-08 | Y65: 10:30 | Z65: MercadoPago | AA65: App | AB65: B2C | AC65: Masaje | AD65: Individual | AE65: 60min | AF65: Prenatal | AG65: 45000 | AH65: 45000 | AI65: 0 | AJ65: 0 | AK65: 27000 | AQ65: YKj5c0OZg9 | AR65: Romina Arias | AS65: CHICUREO | AT65: CHICUREO | AU65: LZexIBKIb9 | AV65: Magdalena Castro Morgado | AW65: Terminado | AX65: Ninguno | AY65: 5 | AZ65: 5 | BA65: Excelente!! Me encantó, nada que decir de Magdalena. Gracias | BB65: https://admin.scape.mx/appointment/403utqoTwQ
A66: =IFERROR(VLOOKUP(AV66,Nómina!B:E,4,0),"") -> MARIA MAGDALENA CASTRO MORGADO | B66: =IFERROR(VLOOKUP(A66,Nómina!E:F,2,0),"") -> 13335240-6 | C66: =IFERROR(Q66,"") -> 5580 | D66: =IFERROR(X66,"") -> 2026-07-08 | E66: =IFERROR(O66,"") -> B2C | F66: =IFERROR(AC66,"") -> Extra | G66: =IFERROR(AD66,"") -> Individual | H66: =IFERROR(AE66,"") -> - | I66: =IFERROR(AF66,"") -> Extra de transporte | J66: =IFERROR(AT66,"") -> CHICUREO | K66: =IFERROR(AX66,"") -> Ninguno | L66: =IFERROR(AY66,"") -> 5 | M66: =IFERROR(AZ66,"") -> 5 | N66: =IFERROR(BA66,"") -> Excelente!! Me encantó, nada que decir de Magdalena. Gracias | O66: =+VLOOKUP(Z66,listas!$B:$C,2,0) -> B2C | P66: =AG66 -> 6990 | Q66: =IF(AC66="Extra",IF(AF66="Extra de transporte",ROUND(P66/1.19*0.95,0),ROUND(P66/1.19*0.6,0)),ROUND(P66/1.19*0.6,0)) -> 5580 | R66: =MONTH(X66) -> 7 | S66: =DAY(X66) -> 8 | T66: =IF(S66>15,2,1) -> 1 | U66: CL | V66: 403utqoTwQ | W66: 2026-07-07 | X66: 2026-07-08 | Y66: 10:30 | Z66: MercadoPago | AA66: App | AB66: B2C | AC66: Extra | AD66: Individual | AE66: - | AF66: Extra de transporte | AG66: 6990 | AH66: 6990 | AI66: 0 | AJ66: 0 | AK66: 6990 | AQ66: YKj5c0OZg9 | AR66: Romina Arias | AS66: CHICUREO | AT66: CHICUREO | AU66: LZexIBKIb9 | AV66: Magdalena Castro Morgado | AW66: Terminado | AX66: Ninguno | AY66: 5 | AZ66: 5 | BA66: Excelente!! Me encantó, nada que decir de Magdalena. Gracias | BB66: https://admin.scape.mx/appointment/403utqoTwQ
A67: =IFERROR(VLOOKUP(AV67,Nómina!B:E,4,0),"") -> CLAUDIA MARIA HERNANDEZ CONTRERAS | B67: =IFERROR(VLOOKUP(A67,Nómina!E:F,2,0),"") -> 23098075-6 | C67: =IFERROR(Q67,"") -> 22689 | D67: =IFERROR(X67,"") -> 2026-07-08 | E67: =IFERROR(O67,"") -> B2C | F67: =IFERROR(AC67,"") -> Masaje | G67: =IFERROR(AD67,"") -> Individual | H67: =IFERROR(AE67,"") -> 60min | I67: =IFERROR(AF67,"") -> Tejido profundo | J67: =IFERROR(AT67,"") -> VITACURA | K67: =IFERROR(AX67,"") -> Ninguno | L67: =IFERROR(AY67,"") -> 0 | M67: =IFERROR(AZ67,"") -> 0 | N67: =IFERROR(BA67,"") | O67: =+VLOOKUP(Z67,listas!$B:$C,2,0) -> B2C | P67: =AG67 -> 45000 | Q67: =IF(AC67="Extra",IF(AF67="Extra de transporte",ROUND(P67/1.19*0.95,0),ROUND(P67/1.19*0.6,0)),ROUND(P67/1.19*0.6,0)) -> 22689 | R67: =MONTH(X67) -> 7 | S67: =DAY(X67) -> 8 | T67: =IF(S67>15,2,1) -> 1 | U67: CL | V67: 7hPNZ9C9bX | W67: 2026-07-08 | X67: 2026-07-08 | Y67: 14:30 | Z67: MercadoPago | AA67: App | AB67: B2C | AC67: Masaje | AD67: Individual | AE67: 60min | AF67: Tejido profundo | AG67: 45000 | AH67: 45000 | AI67: 0 | AJ67: 0 | AK67: 27000 | AQ67: YpkJROzFdn | AR67: Florencia Morales | AS67: VITACURA | AT67: VITACURA | AU67: VU9Xqc5mzI | AV67: Claudia Hernández | AW67: Terminado | AX67: Ninguno | AY67: 0 | AZ67: 0 | BB67: https://admin.scape.mx/appointment/7hPNZ9C9bX
A68: =IFERROR(VLOOKUP(AV68,Nómina!B:E,4,0),"") -> PAMELA VERONICA CID NAVIA | B68: =IFERROR(VLOOKUP(A68,Nómina!E:F,2,0),"") -> 8008360-2 | C68: =IFERROR(Q68,"") -> 22689 | D68: =IFERROR(X68,"") -> 2026-07-08 | E68: =IFERROR(O68,"") -> B2C | F68: =IFERROR(AC68,"") -> Masaje | G68: =IFERROR(AD68,"") -> Individual | H68: =IFERROR(AE68,"") -> 60min | I68: =IFERROR(AF68,"") -> Tejido profundo | J68: =IFERROR(AT68,"") -> LAS CONDES | K68: =IFERROR(AX68,"") -> Ninguno | L68: =IFERROR(AY68,"") -> 0 | M68: =IFERROR(AZ68,"") -> 0 | N68: =IFERROR(BA68,"") | O68: =+VLOOKUP(Z68,listas!$B:$C,2,0) -> B2C | P68: =AG68 -> 45000 | Q68: =IF(AC68="Extra",IF(AF68="Extra de transporte",ROUND(P68/1.19*0.95,0),ROUND(P68/1.19*0.6,0)),ROUND(P68/1.19*0.6,0)) -> 22689 | R68: =MONTH(X68) -> 7 | S68: =DAY(X68) -> 8 | T68: =IF(S68>15,2,1) -> 1 | U68: CL | V68: nSqJI9AD3n | W68: 2026-07-08 | X68: 2026-07-08 | Y68: 15:00 | Z68: MercadoPago | AA68: App | AB68: B2C | AC68: Masaje | AD68: Individual | AE68: 60min | AF68: Tejido profundo | AG68: 45000 | AH68: 45000 | AI68: 0 | AJ68: 0 | AK68: 27000 | AQ68: eniZon8OF8 | AR68: Valentina Perez Merino | AS68: LAS CONDES | AT68: LAS CONDES | AU68: K4Rt2FH54k | AV68: Pamela Cid | AW68: Terminado | AX68: Ninguno | AY68: 0 | AZ68: 0 | BB68: https://admin.scape.mx/appointment/nSqJI9AD3n
A69: =IFERROR(VLOOKUP(AV69,Nómina!B:E,4,0),"") -> PAMELA VERONICA CID NAVIA | B69: =IFERROR(VLOOKUP(A69,Nómina!E:F,2,0),"") -> 8008360-2 | C69: =IFERROR(Q69,"") -> 9076 | D69: =IFERROR(X69,"") -> 2026-07-08 | E69: =IFERROR(O69,"") -> B2C | F69: =IFERROR(AC69,"") -> Addon | G69: =IFERROR(AD69,"") -> Individual | H69: =IFERROR(AE69,"") -> 30min | I69: =IFERROR(AF69,"") -> Craneofacial | J69: =IFERROR(AT69,"") -> LAS CONDES | K69: =IFERROR(AX69,"") -> Ninguno | L69: =IFERROR(AY69,"") -> 0 | M69: =IFERROR(AZ69,"") -> 0 | N69: =IFERROR(BA69,"") | O69: =+VLOOKUP(Z69,listas!$B:$C,2,0) -> B2C | P69: =AG69 -> 18000 | Q69: =IF(AC69="Extra",IF(AF69="Extra de transporte",ROUND(P69/1.19*0.95,0),ROUND(P69/1.19*0.6,0)),ROUND(P69/1.19*0.6,0)) -> 9076 | R69: =MONTH(X69) -> 7 | S69: =DAY(X69) -> 8 | T69: =IF(S69>15,2,1) -> 1 | U69: CL | V69: nSqJI9AD3n | W69: 2026-07-08 | X69: 2026-07-08 | Y69: 15:00 | Z69: MercadoPago | AA69: App | AB69: B2C | AC69: Addon | AD69: Individual | AE69: 30min | AF69: Craneofacial | AG69: 18000 | AH69: 18000 | AI69: 0 | AJ69: 0 | AK69: 10800 | AQ69: eniZon8OF8 | AR69: Valentina Perez Merino | AS69: LAS CONDES | AT69: LAS CONDES | AU69: K4Rt2FH54k | AV69: Pamela Cid | AW69: Terminado | AX69: Ninguno | AY69: 0 | AZ69: 0 | BB69: https://admin.scape.mx/appointment/nSqJI9AD3n
A70: =IFERROR(VLOOKUP(AV70,Nómina!B:E,4,0),"") -> ALEJANDRA PAZ SANCHEZ LENERO | B70: =IFERROR(VLOOKUP(A70,Nómina!E:F,2,0),"") -> 13715658-K | C70: =IFERROR(Q70,"") -> 22689 | D70: =IFERROR(X70,"") -> 2026-07-08 | E70: =IFERROR(O70,"") -> HOTEL | F70: =IFERROR(AC70,"") -> Masaje | G70: =IFERROR(AD70,"") -> Individual | H70: =IFERROR(AE70,"") -> 60min | I70: =IFERROR(AF70,"") -> Relajante | J70: =IFERROR(AT70,"") -> VITACURA | K70: =IFERROR(AX70,"") -> Huésped: Jesus Lopez Hab: 403 | L70: =IFERROR(AY70,"") -> 0 | M70: =IFERROR(AZ70,"") -> 0 | N70: =IFERROR(BA70,"") | O70: =+VLOOKUP(Z70,listas!$B:$C,2,0) -> HOTEL | P70: =AG70 -> 45000 | Q70: =IF(AC70="Extra",IF(AF70="Extra de transporte",ROUND(P70/1.19*0.95,0),ROUND(P70/1.19*0.6,0)),ROUND(P70/1.19*0.6,0)) -> 22689 | R70: =MONTH(X70) -> 7 | S70: =DAY(X70) -> 8 | T70: =IF(S70>15,2,1) -> 1 | U70: CL | V70: yMaLlR9YPD | W70: 2026-07-08 | X70: 2026-07-08 | Y70: 17:30 | Z70: Hotel | AA70: Dashboard | AB70: Hotel | AC70: Masaje | AD70: Individual | AE70: 60min | AF70: Relajante | AG70: 45000 | AH70: 45000 | AI70: 0 | AJ70: 0 | AK70: 27000 | AQ70: jlKOcsP0YM | AR70: Hotel Director | AS70: VITACURA | AT70: VITACURA | AU70: lEyyrcskFP | AV70: Alejandra Sánchez | AW70: Terminado | AX70: Huésped: Jesus Lopez Hab: 403 | AY70: 0 | AZ70: 0 | BB70: https://admin.scape.mx/appointment/yMaLlR9YPD
A71: =IFERROR(VLOOKUP(AV71,Nómina!B:E,4,0),"") -> PAMELA VERONICA CID NAVIA | B71: =IFERROR(VLOOKUP(A71,Nómina!E:F,2,0),"") -> 8008360-2 | C71: =IFERROR(Q71,"") -> 22689 | D71: =IFERROR(X71,"") -> 2026-07-08 | E71: =IFERROR(O71,"") -> B2C | F71: =IFERROR(AC71,"") -> Masaje | G71: =IFERROR(AD71,"") -> Pareja | H71: =IFERROR(AE71,"") -> 60min | I71: =IFERROR(AF71,"") -> Relajante | J71: =IFERROR(AT71,"") -> PROVIDENCIA | K71: =IFERROR(AX71,"") -> Ninguno | L71: =IFERROR(AY71,"") -> 0 | M71: =IFERROR(AZ71,"") -> 0 | N71: =IFERROR(BA71,"") | O71: =+VLOOKUP(Z71,listas!$B:$C,2,0) -> B2C | P71: =AG71 -> 45000 | Q71: =IF(AC71="Extra",IF(AF71="Extra de transporte",ROUND(P71/1.19*0.95,0),ROUND(P71/1.19*0.6,0)),ROUND(P71/1.19*0.6,0)) -> 22689 | R71: =MONTH(X71) -> 7 | S71: =DAY(X71) -> 8 | T71: =IF(S71>15,2,1) -> 1 | U71: CL | V71: HtVfGeRM7N | W71: 2026-07-06 | X71: 2026-07-08 | Y71: 22:00 | Z71: MercadoPago | AA71: Web | AB71: B2C | AC71: Masaje | AD71: Pareja | AE71: 60min | AF71: Relajante | AG71: 45000 | AH71: 38250 | AI71: 0 | AJ71: 6750 | AK71: 27000 | AL71: SOYTE | AQ71: 8gMlgSnlDX | AR71: Barbara Maldonado Ojeda | AS71: PROVIDENCIA | AT71: PROVIDENCIA | AU71: K4Rt2FH54k | AV71: Pamela Cid | AW71: Terminado | AX71: Ninguno | AY71: 0 | AZ71: 0 | BB71: https://admin.scape.mx/appointment/HtVfGeRM7N
A72: =IFERROR(VLOOKUP(AV72,Nómina!B:E,4,0),"") -> GENESIS DANIELA PIMENTEL HERRERA | B72: =IFERROR(VLOOKUP(A72,Nómina!E:F,2,0),"") -> 26598096-1 | C72: =IFERROR(Q72,"") -> 22689 | D72: =IFERROR(X72,"") -> 2026-07-08 | E72: =IFERROR(O72,"") -> B2C | F72: =IFERROR(AC72,"") -> Masaje | G72: =IFERROR(AD72,"") -> Pareja | H72: =IFERROR(AE72,"") -> 60min | I72: =IFERROR(AF72,"") -> Relajante | J72: =IFERROR(AT72,"") -> PROVIDENCIA | K72: =IFERROR(AX72,"") -> Ninguno | L72: =IFERROR(AY72,"") -> 0 | M72: =IFERROR(AZ72,"") -> 0 | N72: =IFERROR(BA72,"") | O72: =+VLOOKUP(Z72,listas!$B:$C,2,0) -> B2C | P72: =AG72 -> 45000 | Q72: =IF(AC72="Extra",IF(AF72="Extra de transporte",ROUND(P72/1.19*0.95,0),ROUND(P72/1.19*0.6,0)),ROUND(P72/1.19*0.6,0)) -> 22689 | R72: =MONTH(X72) -> 7 | S72: =DAY(X72) -> 8 | T72: =IF(S72>15,2,1) -> 1 | U72: CL | V72: HtVfGeRM7N | W72: 2026-07-06 | X72: 2026-07-08 | Y72: 22:00 | Z72: MercadoPago | AA72: Web | AB72: B2C | AC72: Masaje | AD72: Pareja | AE72: 60min | AF72: Relajante | AG72: 45000 | AH72: 38250 | AI72: 0 | AJ72: 6750 | AK72: 27000 | AL72: SOYTE | AQ72: 8gMlgSnlDX | AR72: Barbara Maldonado Ojeda | AS72: PROVIDENCIA | AT72: PROVIDENCIA | AU72: WQqvAzSfjW | AV72: Génesis Pimentel | AW72: Terminado | AX72: Ninguno | AY72: 0 | AZ72: 0 | BB72: https://admin.scape.mx/appointment/HtVfGeRM7N
A73: =IFERROR(VLOOKUP(AV73,Nómina!B:E,4,0),"") -> DANIELA ANTONIA ALARCON ELIZALDE | B73: =IFERROR(VLOOKUP(A73,Nómina!E:F,2,0),"") -> 15893769-7 | C73: =IFERROR(Q73,"") -> 22689 | D73: =IFERROR(X73,"") -> 2026-07-09 | E73: =IFERROR(O73,"") -> ALIANZA | F73: =IFERROR(AC73,"") -> Masaje | G73: =IFERROR(AD73,"") -> Individual | H73: =IFERROR(AE73,"") -> 60min | I73: =IFERROR(AF73,"") -> Relajante | J73: =IFERROR(AT73,"") -> CERRILLOS | K73: =IFERROR(AX73,"") -> Código Bigbox: DDNKPU2K | L73: =IFERROR(AY73,"") -> 0 | M73: =IFERROR(AZ73,"") -> 0 | N73: =IFERROR(BA73,"") | O73: =+VLOOKUP(Z73,listas!$B:$C,2,0) -> ALIANZA | P73: =AG73 -> 45000 | Q73: =IF(AC73="Extra",IF(AF73="Extra de transporte",ROUND(P73/1.19*0.95,0),ROUND(P73/1.19*0.6,0)),ROUND(P73/1.19*0.6,0)) -> 22689 | R73: =MONTH(X73) -> 7 | S73: =DAY(X73) -> 9 | T73: =IF(S73>15,2,1) -> 1 | U73: CL | V73: hJfk1FipGO | W73: 2026-07-07 | X73: 2026-07-09 | Y73: 11:00 | Z73: bigbox_chile | AA73: Dashboard | AB73: Alianza | AC73: Masaje | AD73: Individual | AE73: 60min | AF73: Relajante | AG73: 45000 | AH73: 45000 | AI73: 0 | AJ73: 0 | AK73: 27000 | AQ73: g0i9IVEy3R | AR73: Natalia Sepulveda | AS73: CERRILLOS | AT73: CERRILLOS | AU73: s676FCCH2w | AV73: Daniela Alarcón | AW73: Terminado | AX73: Código Bigbox: DDNKPU2K | AY73: 0 | AZ73: 0 | BB73: https://admin.scape.mx/appointment/hJfk1FipGO
A74: =IFERROR(VLOOKUP(AV74,Nómina!B:E,4,0),"") -> WILLESKA ORTEGA JUSTO | B74: =IFERROR(VLOOKUP(A74,Nómina!E:F,2,0),"") -> 25310926-2 | C74: =IFERROR(Q74,"") -> 22689 | D74: =IFERROR(X74,"") -> 2026-07-09 | E74: =IFERROR(O74,"") -> B2C | F74: =IFERROR(AC74,"") -> Masaje | G74: =IFERROR(AD74,"") -> Individual | H74: =IFERROR(AE74,"") -> 60min | I74: =IFERROR(AF74,"") -> Deportivo | J74: =IFERROR(AT74,"") -> SANTIAGO DE CHILE | K74: =IFERROR(AX74,"") -> Ninguno | L74: =IFERROR(AY74,"") -> 0 | M74: =IFERROR(AZ74,"") -> 0 | N74: =IFERROR(BA74,"") | O74: =+VLOOKUP(Z74,listas!$B:$C,2,0) -> B2C | P74: =AG74 -> 45000 | Q74: =IF(AC74="Extra",IF(AF74="Extra de transporte",ROUND(P74/1.19*0.95,0),ROUND(P74/1.19*0.6,0)),ROUND(P74/1.19*0.6,0)) -> 22689 | R74: =MONTH(X74) -> 7 | S74: =DAY(X74) -> 9 | T74: =IF(S74>15,2,1) -> 1 | U74: CL | V74: G5NBCZMr3m | W74: 2026-07-08 | X74: 2026-07-09 | Y74: 13:30 | Z74: MercadoPago | AA74: Web | AB74: B2C | AC74: Masaje | AD74: Individual | AE74: 60min | AF74: Deportivo | AG74: 45000 | AH74: 45000 | AI74: 0 | AJ74: 0 | AK74: 27000 | AQ74: JfIaYeeEAY | AR74: Fernanda Arrasate | AS74: LO BARNECHEA | AT74: SANTIAGO DE CHILE | AU74: sCjPHkWoRk | AV74: Willeska Ortega | AW74: Terminado | AX74: Ninguno | AY74: 0 | AZ74: 0 | BB74: https://admin.scape.mx/appointment/G5NBCZMr3m
A75: =IFERROR(VLOOKUP(AV75,Nómina!B:E,4,0),"") -> WILLESKA ORTEGA JUSTO | B75: =IFERROR(VLOOKUP(A75,Nómina!E:F,2,0),"") -> 25310926-2 | C75: =IFERROR(Q75,"") -> 9076 | D75: =IFERROR(X75,"") -> 2026-07-09 | E75: =IFERROR(O75,"") -> B2C | F75: =IFERROR(AC75,"") -> Addon | G75: =IFERROR(AD75,"") -> Individual | H75: =IFERROR(AE75,"") -> 30min | I75: =IFERROR(AF75,"") -> Craneofacial | J75: =IFERROR(AT75,"") -> SANTIAGO DE CHILE | K75: =IFERROR(AX75,"") -> Ninguno | L75: =IFERROR(AY75,"") -> 0 | M75: =IFERROR(AZ75,"") -> 0 | N75: =IFERROR(BA75,"") | O75: =+VLOOKUP(Z75,listas!$B:$C,2,0) -> B2C | P75: =AG75 -> 18000 | Q75: =IF(AC75="Extra",IF(AF75="Extra de transporte",ROUND(P75/1.19*0.95,0),ROUND(P75/1.19*0.6,0)),ROUND(P75/1.19*0.6,0)) -> 9076 | R75: =MONTH(X75) -> 7 | S75: =DAY(X75) -> 9 | T75: =IF(S75>15,2,1) -> 1 | U75: CL | V75: G5NBCZMr3m | W75: 2026-07-08 | X75: 2026-07-09 | Y75: 13:30 | Z75: MercadoPago | AA75: Web | AB75: B2C | AC75: Addon | AD75: Individual | AE75: 30min | AF75: Craneofacial | AG75: 18000 | AH75: 18000 | AI75: 0 | AJ75: 0 | AK75: 10800 | AQ75: JfIaYeeEAY | AR75: Fernanda Arrasate | AS75: LO BARNECHEA | AT75: SANTIAGO DE CHILE | AU75: sCjPHkWoRk | AV75: Willeska Ortega | AW75: Terminado | AX75: Ninguno | AY75: 0 | AZ75: 0 | BB75: https://admin.scape.mx/appointment/G5NBCZMr3m
A76: =IFERROR(VLOOKUP(AV76,Nómina!B:E,4,0),"") -> WILLESKA ORTEGA JUSTO | B76: =IFERROR(VLOOKUP(A76,Nómina!E:F,2,0),"") -> 25310926-2 | C76: =IFERROR(Q76,"") -> 3185 | D76: =IFERROR(X76,"") -> 2026-07-09 | E76: =IFERROR(O76,"") -> B2C | F76: =IFERROR(AC76,"") -> Extra | G76: =IFERROR(AD76,"") -> Individual | H76: =IFERROR(AE76,"") -> - | I76: =IFERROR(AF76,"") -> Extra de transporte | J76: =IFERROR(AT76,"") -> SANTIAGO DE CHILE | K76: =IFERROR(AX76,"") -> Ninguno | L76: =IFERROR(AY76,"") -> 0 | M76: =IFERROR(AZ76,"") -> 0 | N76: =IFERROR(BA76,"") | O76: =+VLOOKUP(Z76,listas!$B:$C,2,0) -> B2C | P76: =AG76 -> 3990 | Q76: =IF(AC76="Extra",IF(AF76="Extra de transporte",ROUND(P76/1.19*0.95,0),ROUND(P76/1.19*0.6,0)),ROUND(P76/1.19*0.6,0)) -> 3185 | R76: =MONTH(X76) -> 7 | S76: =DAY(X76) -> 9 | T76: =IF(S76>15,2,1) -> 1 | U76: CL | V76: G5NBCZMr3m | W76: 2026-07-08 | X76: 2026-07-09 | Y76: 13:30 | Z76: MercadoPago | AA76: Web | AB76: B2C | AC76: Extra | AD76: Individual | AE76: - | AF76: Extra de transporte | AG76: 3990 | AH76: 3990 | AI76: 0 | AJ76: 0 | AK76: 3990 | AQ76: JfIaYeeEAY | AR76: Fernanda Arrasate | AS76: LO BARNECHEA | AT76: SANTIAGO DE CHILE | AU76: sCjPHkWoRk | AV76: Willeska Ortega | AW76: Terminado | AX76: Ninguno | AY76: 0 | AZ76: 0 | BB76: https://admin.scape.mx/appointment/G5NBCZMr3m
A77: =IFERROR(VLOOKUP(AV77,Nómina!B:E,4,0),"") -> MARIA ELIANA BENAVIDES HIGUERA | B77: =IFERROR(VLOOKUP(A77,Nómina!E:F,2,0),"") -> 15168787-3 | C77: =IFERROR(Q77,"") -> 31765 | D77: =IFERROR(X77,"") -> 2026-07-09 | E77: =IFERROR(O77,"") -> HOTEL | F77: =IFERROR(AC77,"") -> Masaje | G77: =IFERROR(AD77,"") -> Individual | H77: =IFERROR(AE77,"") -> 90min | I77: =IFERROR(AF77,"") -> Drenaje Linfático | J77: =IFERROR(AT77,"") -> LAS CONDES | K77: =IFERROR(AX77,"") -> Nombre huésped: Maria Reumann Número de habitación: 1210 | L77: =IFERROR(AY77,"") -> 0 | M77: =IFERROR(AZ77,"") -> 0 | N77: =IFERROR(BA77,"") | O77: =+VLOOKUP(Z77,listas!$B:$C,2,0) -> HOTEL | P77: =AG77 -> 63000 | Q77: =IF(AC77="Extra",IF(AF77="Extra de transporte",ROUND(P77/1.19*0.95,0),ROUND(P77/1.19*0.6,0)),ROUND(P77/1.19*0.6,0)) -> 31765 | R77: =MONTH(X77) -> 7 | S77: =DAY(X77) -> 9 | T77: =IF(S77>15,2,1) -> 1 | U77: CL | V77: Y7brrKvrBZ | W77: 2026-07-09 | X77: 2026-07-09 | Y77: 16:00 | Z77: Hotel | AA77: Dashboard | AB77: Hotel | AC77: Masaje | AD77: Individual | AE77: 90min | AF77: Drenaje Linfático | AG77: 63000 | AH77: 63000 | AI77: 0 | AJ77: 0 | AK77: 37800 | AQ77: 8LOSg5cHsn | AR77: Doubletree Las Condes | AS77: LAS CONDES | AT77: LAS CONDES | AU77: OBiYJqDd10 | AV77: Eliana Benavides | AW77: Terminado | AX77: Nombre huésped: Maria Reumann Número de habitación: 1210 | AY77: 0 | AZ77: 0 | BB77: https://admin.scape.mx/appointment/Y7brrKvrBZ
A78: =IFERROR(VLOOKUP(AV78,Nómina!B:E,4,0),"") -> MARIA ELIANA BENAVIDES HIGUERA | B78: =IFERROR(VLOOKUP(A78,Nómina!E:F,2,0),"") -> 15168787-3 | C78: =IFERROR(Q78,"") -> 6050 | D78: =IFERROR(X78,"") -> 2026-07-09 | E78: =IFERROR(O78,"") -> HOTEL | F78: =IFERROR(AC78,"") -> Addon | G78: =IFERROR(AD78,"") -> Individual | H78: =IFERROR(AE78,"") -> 15min | I78: =IFERROR(AF78,"") -> Yoga Facial | J78: =IFERROR(AT78,"") -> LAS CONDES | K78: =IFERROR(AX78,"") -> Nombre huésped: Maria Reumann Número de habitación: 1210 | L78: =IFERROR(AY78,"") -> 0 | M78: =IFERROR(AZ78,"") -> 0 | N78: =IFERROR(BA78,"") | O78: =+VLOOKUP(Z78,listas!$B:$C,2,0) -> HOTEL | P78: =AG78 -> 12000 | Q78: =IF(AC78="Extra",IF(AF78="Extra de transporte",ROUND(P78/1.19*0.95,0),ROUND(P78/1.19*0.6,0)),ROUND(P78/1.19*0.6,0)) -> 6050 | R78: =MONTH(X78) -> 7 | S78: =DAY(X78) -> 9 | T78: =IF(S78>15,2,1) -> 1 | U78: CL | V78: Y7brrKvrBZ | W78: 2026-07-09 | X78: 2026-07-09 | Y78: 16:00 | Z78: Hotel | AA78: Dashboard | AB78: Hotel | AC78: Addon | AD78: Individual | AE78: 15min | AF78: Yoga Facial | AG78: 12000 | AH78: 12000 | AI78: 0 | AJ78: 0 | AK78: 7200 | AQ78: 8LOSg5cHsn | AR78: Doubletree Las Condes | AS78: LAS CONDES | AT78: LAS CONDES | AU78: OBiYJqDd10 | AV78: Eliana Benavides | AW78: Terminado | AX78: Nombre huésped: Maria Reumann Número de habitación: 1210 | AY78: 0 | AZ78: 0 | BB78: https://admin.scape.mx/appointment/Y7brrKvrBZ
A79: =IFERROR(VLOOKUP(AV79,Nómina!B:E,4,0),"") -> PAMELA VERONICA CID NAVIA | B79: =IFERROR(VLOOKUP(A79,Nómina!E:F,2,0),"") -> 8008360-2 | C79: =IFERROR(Q79,"") -> 22689 | D79: =IFERROR(X79,"") -> 2026-07-09 | E79: =IFERROR(O79,"") -> B2C | F79: =IFERROR(AC79,"") -> Masaje | G79: =IFERROR(AD79,"") -> Individual | H79: =IFERROR(AE79,"") -> 60min | I79: =IFERROR(AF79,"") -> Tejido profundo | J79: =IFERROR(AT79,"") -> LA REINA | K79: =IFERROR(AX79,"") -> Ninguno | L79: =IFERROR(AY79,"") -> 0 | M79: =IFERROR(AZ79,"") -> 0 | N79: =IFERROR(BA79,"") | O79: =+VLOOKUP(Z79,listas!$B:$C,2,0) -> B2C | P79: =AG79 -> 45000 | Q79: =IF(AC79="Extra",IF(AF79="Extra de transporte",ROUND(P79/1.19*0.95,0),ROUND(P79/1.19*0.6,0)),ROUND(P79/1.19*0.6,0)) -> 22689 | R79: =MONTH(X79) -> 7 | S79: =DAY(X79) -> 9 | T79: =IF(S79>15,2,1) -> 1 | U79: CL | V79: 6wiUzuzZjI | W79: 2026-06-11 | X79: 2026-07-09 | Y79: 19:00 | Z79: Wallet+MercadoPago | AA79: App | AB79: B2C | AC79: Masaje | AD79: Individual | AE79: 60min | AF79: Tejido profundo | AG79: 45000 | AH79: 5000 | AI79: 40000 | AJ79: 0 | AK79: 27000 | AQ79: 4mZUHGo1Ok | AR79: Nicole Sternsdorff | AS79: LA REINA | AT79: LA REINA | AU79: K4Rt2FH54k | AV79: Pamela Cid | AW79: Terminado | AX79: Ninguno | AY79: 0 | AZ79: 0 | BB79: https://admin.scape.mx/appointment/6wiUzuzZjI
A80: =IFERROR(VLOOKUP(AV80,Nómina!B:E,4,0),"") -> EUGENIA ISABEL MONTOYA VIELMA | B80: =IFERROR(VLOOKUP(A80,Nómina!E:F,2,0),"") -> 12897620-5 | C80: =IFERROR(Q80,"") -> 22689 | D80: =IFERROR(X80,"") -> 2026-07-09 | E80: =IFERROR(O80,"") -> HOTEL | F80: =IFERROR(AC80,"") -> Masaje | G80: =IFERROR(AD80,"") -> Individual | H80: =IFERROR(AE80,"") -> 60min | I80: =IFERROR(AF80,"") -> Relajante | J80: =IFERROR(AT80,"") -> VITACURA | K80: =IFERROR(AX80,"") -> Habitación por confirmar | L80: =IFERROR(AY80,"") -> 0 | M80: =IFERROR(AZ80,"") -> 0 | N80: =IFERROR(BA80,"") | O80: =+VLOOKUP(Z80,listas!$B:$C,2,0) -> HOTEL | P80: =AG80 -> 45000 | Q80: =IF(AC80="Extra",IF(AF80="Extra de transporte",ROUND(P80/1.19*0.95,0),ROUND(P80/1.19*0.6,0)),ROUND(P80/1.19*0.6,0)) -> 22689 | R80: =MONTH(X80) -> 7 | S80: =DAY(X80) -> 9 | T80: =IF(S80>15,2,1) -> 1 | U80: CL | V80: bB9iI1qKAi | W80: 2026-07-06 | X80: 2026-07-09 | Y80: 19:00 | Z80: Hotel | AA80: Dashboard | AB80: Hotel | AC80: Masaje | AD80: Individual | AE80: 60min | AF80: Relajante | AG80: 45000 | AH80: 45000 | AI80: 0 | AJ80: 0 | AK80: 27000 | AQ80: OLPG5ZHFBh | AR80: Bidasoa | AS80: VITACURA | AT80: VITACURA | AU80: AHYLXCkIKG | AV80: Eugenia Montoya | AW80: Terminado | AX80: Habitación por confirmar | AY80: 0 | AZ80: 0 | BB80: https://admin.scape.mx/appointment/bB9iI1qKAi
A81: =IFERROR(VLOOKUP(AV81,Nómina!B:E,4,0),"") -> PAMELA CONSTANZA HUILITRARO QUEZADA | B81: =IFERROR(VLOOKUP(A81,Nómina!E:F,2,0),"") -> 18881513-8 | C81: =IFERROR(Q81,"") -> 22689 | D81: =IFERROR(X81,"") -> 2026-07-09 | E81: =IFERROR(O81,"") -> HOTEL | F81: =IFERROR(AC81,"") -> Masaje | G81: =IFERROR(AD81,"") -> Individual | H81: =IFERROR(AE81,"") -> 60min | I81: =IFERROR(AF81,"") -> Prenatal | J81: =IFERROR(AT81,"") -> VITACURA | K81: =IFERROR(AX81,"") -> Habitación por confirmar | L81: =IFERROR(AY81,"") -> 0 | M81: =IFERROR(AZ81,"") -> 0 | N81: =IFERROR(BA81,"") | O81: =+VLOOKUP(Z81,listas!$B:$C,2,0) -> HOTEL | P81: =AG81 -> 45000 | Q81: =IF(AC81="Extra",IF(AF81="Extra de transporte",ROUND(P81/1.19*0.95,0),ROUND(P81/1.19*0.6,0)),ROUND(P81/1.19*0.6,0)) -> 22689 | R81: =MONTH(X81) -> 7 | S81: =DAY(X81) -> 9 | T81: =IF(S81>15,2,1) -> 1 | U81: CL | V81: 4A9VSDFdqG | W81: 2026-07-06 | X81: 2026-07-09 | Y81: 19:00 | Z81: Hotel | AA81: Dashboard | AB81: Hotel | AC81: Masaje | AD81: Individual | AE81: 60min | AF81: Prenatal | AG81: 45000 | AH81: 45000 | AI81: 0 | AJ81: 0 | AK81: 27000 | AQ81: OLPG5ZHFBh | AR81: Bidasoa | AS81: VITACURA | AT81: VITACURA | AU81: lHeDnjpSlr | AV81: Pamela Huilitraro Quezada | AW81: Terminado | AX81: Habitación por confirmar | AY81: 0 | AZ81: 0 | BB81: https://admin.scape.mx/appointment/4A9VSDFdqG
A82: =IFERROR(VLOOKUP(AV82,Nómina!B:E,4,0),"") -> IVVO LEANDRO VERGARA SALINAS | B82: =IFERROR(VLOOKUP(A82,Nómina!E:F,2,0),"") -> 17681238-9 | C82: =IFERROR(Q82,"") -> 22689 | D82: =IFERROR(X82,"") -> 2026-07-09 | E82: =IFERROR(O82,"") -> HOTEL | F82: =IFERROR(AC82,"") -> Masaje | G82: =IFERROR(AD82,"") -> Individual | H82: =IFERROR(AE82,"") -> 60min | I82: =IFERROR(AF82,"") -> Tejido profundo | J82: =IFERROR(AT82,"") -> VITACURA | K82: =IFERROR(AX82,"") -> Habitación por confirmar | L82: =IFERROR(AY82,"") -> 0 | M82: =IFERROR(AZ82,"") -> 0 | N82: =IFERROR(BA82,"") | O82: =+VLOOKUP(Z82,listas!$B:$C,2,0) -> HOTEL | P82: =AG82 -> 45000 | Q82: =IF(AC82="Extra",IF(AF82="Extra de transporte",ROUND(P82/1.19*0.95,0),ROUND(P82/1.19*0.6,0)),ROUND(P82/1.19*0.6,0)) -> 22689 | R82: =MONTH(X82) -> 7 | S82: =DAY(X82) -> 9 | T82: =IF(S82>15,2,1) -> 1 | U82: CL | V82: BwmlYA6jXv | W82: 2026-07-06 | X82: 2026-07-09 | Y82: 19:00 | Z82: Hotel | AA82: Dashboard | AB82: Hotel | AC82: Masaje | AD82: Individual | AE82: 60min | AF82: Tejido profundo | AG82: 45000 | AH82: 45000 | AI82: 0 | AJ82: 0 | AK82: 27000 | AQ82: OLPG5ZHFBh | AR82: Bidasoa | AS82: VITACURA | AT82: VITACURA | AU82: oLYO1T51F3 | AV82: Ivvo Vergara Salinas | AW82: Terminado | AX82: Habitación por confirmar | AY82: 0 | AZ82: 0 | BB82: https://admin.scape.mx/appointment/BwmlYA6jXv
A83: =IFERROR(VLOOKUP(AV83,Nómina!B:E,4,0),"") -> SERGIO RODRÍGUEZ | B83: =IFERROR(VLOOKUP(A83,Nómina!E:F,2,0),"") -> 27988098-6 | C83: =IFERROR(Q83,"") -> 22689 | D83: =IFERROR(X83,"") -> 2026-07-09 | E83: =IFERROR(O83,"") -> HOTEL | F83: =IFERROR(AC83,"") -> Masaje | G83: =IFERROR(AD83,"") -> Individual | H83: =IFERROR(AE83,"") -> 60min | I83: =IFERROR(AF83,"") -> Relajante | J83: =IFERROR(AT83,"") -> VITACURA | K83: =IFERROR(AX83,"") -> Habitación por confirmar | L83: =IFERROR(AY83,"") -> 0 | M83: =IFERROR(AZ83,"") -> 0 | N83: =IFERROR(BA83,"") | O83: =+VLOOKUP(Z83,listas!$B:$C,2,0) -> HOTEL | P83: =AG83 -> 45000 | Q83: =IF(AC83="Extra",IF(AF83="Extra de transporte",ROUND(P83/1.19*0.95,0),ROUND(P83/1.19*0.6,0)),ROUND(P83/1.19*0.6,0)) -> 22689 | R83: =MONTH(X83) -> 7 | S83: =DAY(X83) -> 9 | T83: =IF(S83>15,2,1) -> 1 | U83: CL | V83: h1XUfdINFo | W83: 2026-07-06 | X83: 2026-07-09 | Y83: 19:00 | Z83: Hotel | AA83: Dashboard | AB83: Hotel | AC83: Masaje | AD83: Individual | AE83: 60min | AF83: Relajante | AG83: 45000 | AH83: 45000 | AI83: 0 | AJ83: 0 | AK83: 27000 | AQ83: OLPG5ZHFBh | AR83: Bidasoa | AS83: VITACURA | AT83: VITACURA | AU83: mG3LpIYbKw | AV83: Sergio Rodríguez | AW83: Terminado | AX83: Habitación por confirmar | AY83: 0 | AZ83: 0 | BB83: https://admin.scape.mx/appointment/h1XUfdINFo
A84: =IFERROR(VLOOKUP(AV84,Nómina!B:E,4,0),"") -> SERGIO RODRÍGUEZ | B84: =IFERROR(VLOOKUP(A84,Nómina!E:F,2,0),"") -> 27988098-6 | C84: =IFERROR(Q84,"") -> 22689 | D84: =IFERROR(X84,"") -> 2026-07-09 | E84: =IFERROR(O84,"") -> HOTEL | F84: =IFERROR(AC84,"") -> Masaje | G84: =IFERROR(AD84,"") -> Individual | H84: =IFERROR(AE84,"") -> 60min | I84: =IFERROR(AF84,"") -> Relajante | J84: =IFERROR(AT84,"") -> VITACURA | K84: =IFERROR(AX84,"") -> Habitación por confirmar | L84: =IFERROR(AY84,"") -> 0 | M84: =IFERROR(AZ84,"") -> 0 | N84: =IFERROR(BA84,"") | O84: =+VLOOKUP(Z84,listas!$B:$C,2,0) -> HOTEL | P84: =AG84 -> 45000 | Q84: =IF(AC84="Extra",IF(AF84="Extra de transporte",ROUND(P84/1.19*0.95,0),ROUND(P84/1.19*0.6,0)),ROUND(P84/1.19*0.6,0)) -> 22689 | R84: =MONTH(X84) -> 7 | S84: =DAY(X84) -> 9 | T84: =IF(S84>15,2,1) -> 1 | U84: CL | V84: 8fyu0S1PRy | W84: 2026-07-06 | X84: 2026-07-09 | Y84: 20:00 | Z84: Hotel | AA84: Dashboard | AB84: Hotel | AC84: Masaje | AD84: Individual | AE84: 60min | AF84: Relajante | AG84: 45000 | AH84: 45000 | AI84: 0 | AJ84: 0 | AK84: 27000 | AQ84: OLPG5ZHFBh | AR84: Bidasoa | AS84: VITACURA | AT84: VITACURA | AU84: mG3LpIYbKw | AV84: Sergio Rodríguez | AW84: Terminado | AX84: Habitación por confirmar | AY84: 0 | AZ84: 0 | BB84: https://admin.scape.mx/appointment/8fyu0S1PRy
... A92: =IFERROR(VLOOKUP(AV92,Nómina!B:E,4,0),"") -> PAMELA VERONICA CID NAVIA | B92: =IFERROR(VLOOKUP(A92,Nómina!E:F,2,0),"") -> 8008360-2 | C92: =IFERROR(Q92,"") -> 5042 | D92: =IFERROR(X92,"") -> 2026-07-09 | E92: =IFERROR(O92,"") -> B2C | F92: =IFERROR(AC92,"") -> Addon | G92: =IFERROR(AD92,"") -> Individual | H92: =IFERROR(AE92,"") -> 15min | I92: =IFERROR(AF92,"") -> Craneofacial | J92: =IFERROR(AT92,"") -> CERRILLOS | K92: =IFERROR(AX92,"") -> Ninguno | L92: =IFERROR(AY92,"") -> 0 | M92: =IFERROR(AZ92,"") -> 0 | N92: =IFERROR(BA92,"") | O92: =+VLOOKUP(Z92,listas!$B:$C,2,0) -> B2C | P92: =AG92 -> 10000 | Q92: =IF(AC92="Extra",IF(AF92="Extra de transporte",ROUND(P92/1.19*0.95,0),ROUND(P92/1.19*0.6,0)),ROUND(P92/1.19*0.6,0)) -> 5042 | R92: =MONTH(X92) -> 7 | S92: =DAY(X92) -> 9 | T92: =IF(S92>15,2,1) -> 1 | U92: CL | V92: uSz0k9wWsk | W92: 2026-07-09 | X92: 2026-07-09 | Y92: 21:00 | Z92: MercadoPago | AA92: Dashboard | AB92: B2C | AC92: Addon | AD92: Individual | AE92: 15min | AF92: Craneofacial | AG92: 10000 | AH92: 10000 | AI92: 0 | AJ92: 0 | AK92: 6000 | AQ92: Xz8yUcGlQQ | AR92: Fernanda Vargas | AS92: CERRILLOS | AT92: CERRILLOS | AU92: K4Rt2FH54k | AV92: Pamela Cid | AW92: Terminado | AX92: Ninguno | AY92: 0 | AZ92: 0 | BB92: https://admin.scape.mx/appointment/uSz0k9wWsk
A93: =IFERROR(VLOOKUP(AV93,Nómina!B:E,4,0),"") -> SERGIO RODRÍGUEZ | B93: =IFERROR(VLOOKUP(A93,Nómina!E:F,2,0),"") -> 27988098-6 | C93: =IFERROR(Q93,"") -> 22689 | D93: =IFERROR(X93,"") -> 2026-07-10 | E93: =IFERROR(O93,"") -> CERTIFICADO B2C | F93: =IFERROR(AC93,"") -> Masaje | G93: =IFERROR(AD93,"") -> Individual | H93: =IFERROR(AE93,"") -> 60min | I93: =IFERROR(AF93,"") -> Relajante | J93: =IFERROR(AT93,"") -> CERRILLOS | K93: =IFERROR(AX93,"") -> Ninguno | L93: =IFERROR(AY93,"") -> 0 | M93: =IFERROR(AZ93,"") -> 0 | N93: =IFERROR(BA93,"") | O93: =+VLOOKUP(Z93,listas!$B:$C,2,0) -> CERTIFICADO B2C | P93: =AG93 -> 45000 | Q93: =IF(AC93="Extra",IF(AF93="Extra de transporte",ROUND(P93/1.19*0.95,0),ROUND(P93/1.19*0.6,0)),ROUND(P93/1.19*0.6,0)) -> 22689 | R93: =MONTH(X93) -> 7 | S93: =DAY(X93) -> 10 | T93: =IF(S93>15,2,1) -> 1 | U93: CL | V93: 4BePcXFwV4 | W93: 2026-07-07 | X93: 2026-07-10 | Y93: 10:00 | Z93: Certificado B2C | AA93: Dashboard | AB93: B2C | AC93: Masaje | AD93: Individual | AE93: 60min | AF93: Relajante | AG93: 45000 | AH93: 0 | AI93: 45000 | AJ93: 0 | AK93: 27000 | AM93: Bo6XWn3CeB | AQ93: vJ2VPCGUwR | AR93: Manuela Pérez Danús | AS93: CERRILLOS | AT93: CERRILLOS | AU93: mG3LpIYbKw | AV93: Sergio Rodríguez | AW93: Terminado | AX93: Ninguno | AY93: 0 | AZ93: 0 | BB93: https://admin.scape.mx/appointment/4BePcXFwV4
A94: =IFERROR(VLOOKUP(AV94,Nómina!B:E,4,0),"") -> PAMELA VERONICA CID NAVIA | B94: =IFERROR(VLOOKUP(A94,Nómina!E:F,2,0),"") -> 8008360-2 | C94: =IFERROR(Q94,"") -> 22689 | D94: =IFERROR(X94,"") -> 2026-07-10 | E94: =IFERROR(O94,"") -> HOTEL | F94: =IFERROR(AC94,"") -> Masaje | G94: =IFERROR(AD94,"") -> Individual | H94: =IFERROR(AE94,"") -> 60min | I94: =IFERROR(AF94,"") -> Relajante | J94: =IFERROR(AT94,"") -> VITACURA | K94: =IFERROR(AX94,"") -> Nombre huésped: jonathan saliba Número de habitación:607 | L94: =IFERROR(AY94,"") -> 0 | M94: =IFERROR(AZ94,"") -> 0 | N94: =IFERROR(BA94,"") | O94: =+VLOOKUP(Z94,listas!$B:$C,2,0) -> HOTEL | P94: =AG94 -> 45000 | Q94: =IF(AC94="Extra",IF(AF94="Extra de transporte",ROUND(P94/1.19*0.95,0),ROUND(P94/1.19*0.6,0)),ROUND(P94/1.19*0.6,0)) -> 22689 | R94: =MONTH(X94) -> 7 | S94: =DAY(X94) -> 10 | T94: =IF(S94>15,2,1) -> 1 | U94: CL | V94: 36GqosOOeh | W94: 2026-07-10 | X94: 2026-07-10 | Y94: 14:00 | Z94: Hotel | AA94: Dashboard | AB94: Hotel | AC94: Masaje | AD94: Individual | AE94: 60min | AF94: Relajante | AG94: 45000 | AH94: 45000 | AI94: 0 | AJ94: 0 | AK94: 27000 | AQ94: Bixoh0LizH | AR94: Hotel Pullman Vitacura | AS94: VITACURA | AT94: VITACURA | AU94: K4Rt2FH54k | AV94: Pamela Cid | AW94: Terminado | AX94: Nombre huésped: jonathan saliba Número de habitación:607 | AY94: 0 | AZ94: 0 | BB94: https://admin.scape.mx/appointment/36GqosOOeh
A95: =IFERROR(VLOOKUP(AV95,Nómina!B:E,4,0),"") -> EUGENIA ISABEL MONTOYA VIELMA | B95: =IFERROR(VLOOKUP(A95,Nómina!E:F,2,0),"") -> 12897620-5 | C95: =IFERROR(Q95,"") -> 22689 | D95: =IFERROR(X95,"") -> 2026-07-10 | E95: =IFERROR(O95,"") -> B2C | F95: =IFERROR(AC95,"") -> Masaje | G95: =IFERROR(AD95,"") -> Individual | H95: =IFERROR(AE95,"") -> 60min | I95: =IFERROR(AF95,"") -> Relajante | J95: =IFERROR(AT95,"") -> PROVIDENCIA | K95: =IFERROR(AX95,"") -> Ninguno | L95: =IFERROR(AY95,"") -> 0 | M95: =IFERROR(AZ95,"") -> 0 | N95: =IFERROR(BA95,"") | O95: =+VLOOKUP(Z95,listas!$B:$C,2,0) -> B2C | P95: =AG95 -> 45000 | Q95: =IF(AC95="Extra",IF(AF95="Extra de transporte",ROUND(P95/1.19*0.95,0),ROUND(P95/1.19*0.6,0)),ROUND(P95/1.19*0.6,0)) -> 22689 | R95: =MONTH(X95) -> 7 | S95: =DAY(X95) -> 10 | T95: =IF(S95>15,2,1) -> 1 | U95: CL | V95: dHtEEFzJbT | W95: 2026-07-08 | X95: 2026-07-10 | Y95: 17:30 | Z95: MercadoPago | AA95: Web | AB95: B2C | AC95: Masaje | AD95: Individual | AE95: 60min | AF95: Relajante | AG95: 45000 | AH95: 40500 | AI95: 0 | AJ95: 4500 | AK95: 27000 | AL95: BUK2026 | AQ95: RZpWSBL7sP | AR95: Isabel Valenzuela | AS95: PROVIDENCIA | AT95: PROVIDENCIA | AU95: AHYLXCkIKG | AV95: Eugenia Montoya | AW95: Terminado | AX95: Ninguno | AY95: 0 | AZ95: 0 | BB95: https://admin.scape.mx/appointment/dHtEEFzJbT
A96: =IFERROR(VLOOKUP(AV96,Nómina!B:E,4,0),"") -> GENESIS VALENTINA SALAZAR GUEVARA | B96: =IFERROR(VLOOKUP(A96,Nómina!E:F,2,0),"") -> 27828546-4 | C96: =IFERROR(Q96,"") -> 22689 | D96: =IFERROR(X96,"") -> 2026-07-10 | E96: =IFERROR(O96,"") -> HOTEL | F96: =IFERROR(AC96,"") -> Masaje | G96: =IFERROR(AD96,"") -> Individual | H96: =IFERROR(AE96,"") -> 60min | I96: =IFERROR(AF96,"") -> Tejido profundo | J96: =IFERROR(AT96,"") -> VITACURA | K96: =IFERROR(AX96,"") -> Huésped: Emma Curnow. Hab: 406. Solicita: Danilo. | L96: =IFERROR(AY96,"") -> 0 | M96: =IFERROR(AZ96,"") -> 0 | N96: =IFERROR(BA96,"") | O96: =+VLOOKUP(Z96,listas!$B:$C,2,0) -> HOTEL | P96: =AG96 -> 45000 | Q96: =IF(AC96="Extra",IF(AF96="Extra de transporte",ROUND(P96/1.19*0.95,0),ROUND(P96/1.19*0.6,0)),ROUND(P96/1.19*0.6,0)) -> 22689 | R96: =MONTH(X96) -> 7 | S96: =DAY(X96) -> 10 | T96: =IF(S96>15,2,1) -> 1 | U96: CL | V96: Z9K5Kn83x4 | W96: 2026-07-06 | X96: 2026-07-10 | Y96: 18:00 | Z96: Hotel | AA96: Dashboard | AB96: Hotel | AC96: Masaje | AD96: Individual | AE96: 60min | AF96: Tejido profundo | AG96: 45000 | AH96: 45000 | AI96: 0 | AJ96: 0 | AK96: 27000 | AQ96: OLPG5ZHFBh | AR96: Bidasoa | AS96: VITACURA | AT96: VITACURA | AU96: TcqJ1GTAe6 | AV96: Valentina Salazar Guevara | AW96: Terminado | AX96: Huésped: Emma Curnow. Hab: 406. Solicita: Danilo. | AY96: 0 | AZ96: 0 | BB96: https://admin.scape.mx/appointment/Z9K5Kn83x4
A97: =IFERROR(VLOOKUP(AV97,Nómina!B:E,4,0),"") -> MARIA ELIANA BENAVIDES HIGUERA | B97: =IFERROR(VLOOKUP(A97,Nómina!E:F,2,0),"") -> 15168787-3 | C97: =IFERROR(Q97,"") -> 22689 | D97: =IFERROR(X97,"") -> 2026-07-10 | E97: =IFERROR(O97,"") -> B2C | F97: =IFERROR(AC97,"") -> Masaje | G97: =IFERROR(AD97,"") -> Individual | H97: =IFERROR(AE97,"") -> 60min | I97: =IFERROR(AF97,"") -> Relajante | J97: =IFERROR(AT97,"") -> LAS CONDES | K97: =IFERROR(AX97,"") -> Ninguno | L97: =IFERROR(AY97,"") -> 0 | M97: =IFERROR(AZ97,"") -> 0 | N97: =IFERROR(BA97,"") | O97: =+VLOOKUP(Z97,listas!$B:$C,2,0) -> B2C | P97: =AG97 -> 45000 | Q97: =IF(AC97="Extra",IF(AF97="Extra de transporte",ROUND(P97/1.19*0.95,0),ROUND(P97/1.19*0.6,0)),ROUND(P97/1.19*0.6,0)) -> 22689 | R97: =MONTH(X97) -> 7 | S97: =DAY(X97) -> 10 | T97: =IF(S97>15,2,1) -> 1 | U97: CL | V97: CMdVLrIndo | W97: 2026-07-07 | X97: 2026-07-10 | Y97: 18:00 | Z97: MercadoPago | AA97: App | AB97: B2C | AC97: Masaje | AD97: Individual | AE97: 60min | AF97: Relajante | AG97: 45000 | AH97: 40500 | AI97: 0 | AJ97: 4500 | AK97: 27000 | AL97: BUK2026 | AQ97: ohGwHx9tn6 | AR97: Josefina Novoa | AS97: LAS CONDES | AT97: LAS CONDES | AU97: OBiYJqDd10 | AV97: Eliana Benavides | AW97: Terminado | AX97: Ninguno | AY97: 0 | AZ97: 0 | BB97: https://admin.scape.mx/appointment/CMdVLrIndo
A98: =IFERROR(VLOOKUP(AV98,Nómina!B:E,4,0),"") -> KARIN BRILOVICH KLEINKOPF | B98: =IFERROR(VLOOKUP(A98,Nómina!E:F,2,0),"") -> 9384198-0 | C98: =IFERROR(Q98,"") -> 22689 | D98: =IFERROR(X98,"") -> 2026-07-10 | E98: =IFERROR(O98,"") -> B2C | F98: =IFERROR(AC98,"") -> Masaje | G98: =IFERROR(AD98,"") -> Individual | H98: =IFERROR(AE98,"") -> 60min | I98: =IFERROR(AF98,"") -> Tejido profundo | J98: =IFERROR(AT98,"") -> SANTIAGO DE CHILE | K98: =IFERROR(AX98,"") -> Ninguno | L98: =IFERROR(AY98,"") -> 0 | M98: =IFERROR(AZ98,"") -> 0 | N98: =IFERROR(BA98,"") | O98: =+VLOOKUP(Z98,listas!$B:$C,2,0) -> B2C | P98: =AG98 -> 45000 | Q98: =IF(AC98="Extra",IF(AF98="Extra de transporte",ROUND(P98/1.19*0.95,0),ROUND(P98/1.19*0.6,0)),ROUND(P98/1.19*0.6,0)) -> 22689 | R98: =MONTH(X98) -> 7 | S98: =DAY(X98) -> 10 | T98: =IF(S98>15,2,1) -> 1 | U98: CL | V98: YHGNM81wjL | W98: 2026-07-09 | X98: 2026-07-10 | Y98: 19:00 | Z98: Wallet+MercadoPago | AA98: App | AB98: B2C | AC98: Masaje | AD98: Individual | AE98: 60min | AF98: Tejido profundo | AG98: 45000 | AH98: 15000 | AI98: 30000 | AJ98: 0 | AK98: 27000 | AQ98: sSQKUIOTtM | AR98: Daniela Pliego | AS98: LO BARNECHEA | AT98: SANTIAGO DE CHILE | AU98: Gng1E8S7ih | AV98: Karin Brilovich | AW98: Terminado | AX98: Ninguno | AY98: 0 | AZ98: 0 | BB98: https://admin.scape.mx/appointment/YHGNM81wjL
A99: =IFERROR(VLOOKUP(AV99,Nómina!B:E,4,0),"") -> KARIN BRILOVICH KLEINKOPF | B99: =IFERROR(VLOOKUP(A99,Nómina!E:F,2,0),"") -> 9384198-0 | C99: =IFERROR(Q99,"") -> 5042 | D99: =IFERROR(X99,"") -> 2026-07-10 | E99: =IFERROR(O99,"") -> B2C | F99: =IFERROR(AC99,"") -> Addon | G99: =IFERROR(AD99,"") -> Individual | H99: =IFERROR(AE99,"") -> 15min | I99: =IFERROR(AF99,"") -> Masaje Tiempo Extra | J99: =IFERROR(AT99,"") -> SANTIAGO DE CHILE | K99: =IFERROR(AX99,"") -> Ninguno | L99: =IFERROR(AY99,"") -> 0 | M99: =IFERROR(AZ99,"") -> 0 | N99: =IFERROR(BA99,"") | O99: =+VLOOKUP(Z99,listas!$B:$C,2,0) -> B2C | P99: =AG99 -> 10000 | Q99: =IF(AC99="Extra",IF(AF99="Extra de transporte",ROUND(P99/1.19*0.95,0),ROUND(P99/1.19*0.6,0)),ROUND(P99/1.19*0.6,0)) -> 5042 | R99: =MONTH(X99) -> 7 | S99: =DAY(X99) -> 10 | T99: =IF(S99>15,2,1) -> 1 | U99: CL | V99: YHGNM81wjL | W99: 2026-07-09 | X99: 2026-07-10 | Y99: 19:00 | Z99: Wallet+MercadoPago | AA99: App | AB99: B2C | AC99: Addon | AD99: Individual | AE99: 15min | AF99: Masaje Tiempo Extra | AG99: 10000 | AH99: 0 | AI99: 10000 | AJ99: 0 | AK99: 6000 | AQ99: sSQKUIOTtM | AR99: Daniela Pliego | AS99: LO BARNECHEA | AT99: SANTIAGO DE CHILE | AU99: Gng1E8S7ih | AV99: Karin Brilovich | AW99: Terminado | AX99: Ninguno | AY99: 0 | AZ99: 0 | BB99: https://admin.scape.mx/appointment/YHGNM81wjL
A100: =IFERROR(VLOOKUP(AV100,Nómina!B:E,4,0),"") -> KARIN BRILOVICH KLEINKOPF | B100: =IFERROR(VLOOKUP(A100,Nómina!E:F,2,0),"") -> 9384198-0 | C100: =IFERROR(Q100,"") -> 5042 | D100: =IFERROR(X100,"") -> 2026-07-10 | E100: =IFERROR(O100,"") -> B2C | F100: =IFERROR(AC100,"") -> Addon | G100: =IFERROR(AD100,"") -> Individual | H100: =IFERROR(AE100,"") -> 15min | I100: =IFERROR(AF100,"") -> Reflexología | J100: =IFERROR(AT100,"") -> SANTIAGO DE CHILE | K100: =IFERROR(AX100,"") -> Ninguno | L100: =IFERROR(AY100,"") -> 0 | M100: =IFERROR(AZ100,"") -> 0 | N100: =IFERROR(BA100,"") | O100: =+VLOOKUP(Z100,listas!$B:$C,2,0) -> B2C | P100: =AG100 -> 10000 | Q100: =IF(AC100="Extra",IF(AF100="Extra de transporte",ROUND(P100/1.19*0.95,0),ROUND(P100/1.19*0.6,0)),ROUND(P100/1.19*0.6,0)) -> 5042 | R100: =MONTH(X100) -> 7 | S100: =DAY(X100) -> 10 | T100: =IF(S100>15,2,1) -> 1 | U100: CL | V100: YHGNM81wjL | W100: 2026-07-09 | X100: 2026-07-10 | Y100: 19:00 | Z100: Wallet+MercadoPago | AA100: App | AB100: B2C | AC100: Addon | AD100: Individual | AE100: 15min | AF100: Reflexología | AG100: 10000 | AH100: 0 | AI100: 10000 | AJ100: 0 | AK100: 6000 | AQ100: sSQKUIOTtM | AR100: Daniela Pliego | AS100: LO BARNECHEA | AT100: SANTIAGO DE CHILE | AU100: Gng1E8S7ih | AV100: Karin Brilovich | AW100: Terminado | AX100: Ninguno | AY100: 0 | AZ100: 0 | BB100: https://admin.scape.mx/appointment/YHGNM81wjL
A101: =IFERROR(VLOOKUP(AV101,Nómina!B:E,4,0),"") -> KARIN BRILOVICH KLEINKOPF | B101: =IFERROR(VLOOKUP(A101,Nómina!E:F,2,0),"") -> 9384198-0 | C101: =IFERROR(Q101,"") -> 3185 | D101: =IFERROR(X101,"") -> 2026-07-10 | E101: =IFERROR(O101,"") -> B2C | F101: =IFERROR(AC101,"") -> Extra | G101: =IFERROR(AD101,"") -> Individual | H101: =IFERROR(AE101,"") -> - | I101: =IFERROR(AF101,"") -> Extra de transporte | J101: =IFERROR(AT101,"") -> SANTIAGO DE CHILE | K101: =IFERROR(AX101,"") -> Ninguno | L101: =IFERROR(AY101,"") -> 0 | M101: =IFERROR(AZ101,"") -> 0 | N101: =IFERROR(BA101,"") | O101: =+VLOOKUP(Z101,listas!$B:$C,2,0) -> B2C | P101: =AG101 -> 3990 | Q101: =IF(AC101="Extra",IF(AF101="Extra de transporte",ROUND(P101/1.19*0.95,0),ROUND(P101/1.19*0.6,0)),ROUND(P101/1.19*0.6,0)) -> 3185 | R101: =MONTH(X101) -> 7 | S101: =DAY(X101) -> 10 | T101: =IF(S101>15,2,1) -> 1 | U101: CL | V101: YHGNM81wjL | W101: 2026-07-09 | X101: 2026-07-10 | Y101: 19:00 | Z101: Wallet+MercadoPago | AA101: App | AB101: B2C | AC101: Extra | AD101: Individual | AE101: - | AF101: Extra de transporte | AG101: 3990 | AH101: 0 | AI101: 3990 | AJ101: 0 | AK101: 3990 | AQ101: sSQKUIOTtM | AR101: Daniela Pliego | AS101: LO BARNECHEA | AT101: SANTIAGO DE CHILE | AU101: Gng1E8S7ih | AV101: Karin Brilovich | AW101: Terminado | AX101: Ninguno | AY101: 0 | AZ101: 0 | BB101: https://admin.scape.mx/appointment/YHGNM81wjL
A102: =IFERROR(VLOOKUP(AV102,Nómina!B:E,4,0),"") -> PAMELA VERONICA CID NAVIA | B102: =IFERROR(VLOOKUP(A102,Nómina!E:F,2,0),"") -> 8008360-2 | C102: =IFERROR(Q102,"") -> 22689 | D102: =IFERROR(X102,"") -> 2026-07-10 | E102: =IFERROR(O102,"") -> B2C | F102: =IFERROR(AC102,"") -> Masaje | G102: =IFERROR(AD102,"") -> Individual | H102: =IFERROR(AE102,"") -> 60min | I102: =IFERROR(AF102,"") -> Relajante | J102: =IFERROR(AT102,"") -> LAS CONDES | K102: =IFERROR(AX102,"") -> Ninguno | L102: =IFERROR(AY102,"") -> 0 | M102: =IFERROR(AZ102,"") -> 0 | N102: =IFERROR(BA102,"") | O102: =+VLOOKUP(Z102,listas!$B:$C,2,0) -> B2C | P102: =AG102 -> 45000 | Q102: =IF(AC102="Extra",IF(AF102="Extra de transporte",ROUND(P102/1.19*0.95,0),ROUND(P102/1.19*0.6,0)),ROUND(P102/1.19*0.6,0)) -> 22689 | R102: =MONTH(X102) -> 7 | S102: =DAY(X102) -> 10 | T102: =IF(S102>15,2,1) -> 1 | U102: CL | V102: LDTpydLOFi | W102: 2026-07-10 | X102: 2026-07-10 | Y102: 19:00 | Z102: MercadoPago | AA102: App | AB102: B2C | AC102: Masaje | AD102: Individual | AE102: 60min | AF102: Relajante | AG102: 45000 | AH102: 45000 | AI102: 0 | AJ102: 0 | AK102: 27000 | AQ102: EPJuAZeOOf | AR102: Belen Said | AS102: LAS CONDES | AT102: LAS CONDES | AU102: K4Rt2FH54k | AV102: Pamela Cid | AW102: Terminado | AX102: Ninguno | AY102: 0 | AZ102: 0 | BB102: https://admin.scape.mx/appointment/LDTpydLOFi
